Workbook
Name alloc_stu_grp: [1]stu_alloc!$B$2:$B$54
Name alloc_stu_grp: [2]stu_alloc!$B$2:$B$54
Name c_date: Report!$C$11
Name co_idx: [1]Report!$B$2
Name co_idx: [2]Report!$B$2
Name end_date: [1]Params!$B$7
Name end_date: [2]Params!$B$7
Name Ex_code: [2]Report!$B$4
Name Ex_code: [1]Report!$B$4
Name Ex_code: Report!$B$1
Name exch_code: [1]Params!$B$4
Name exch_code: [2]Params!$B$4
Name Master_mode: [1]hparams!#REF!
Name Master_mode: [2]hparams!#REF!
Name Setup_status: #REF!
Name st_id: #REF!
Name start_date: [1]Params!$B$8
Name start_date: [2]Params!$B$8
Name stu_grp: #REF!
Name stu_grp: #REF!
Name stu_idx: [1]hparams!$B$4
Name stu_idx: [2]hparams!$B$4
Name stu_key_id: [1]hparams!$B$3
Name stu_key_id: [2]hparams!$B$3

Sheet Instructions
A2: Individual Report - Excel Workbook Template | D2: Write your company name, Code and Sector here
A3: Student Number: | B3: 25062683 | D3: Company name | E3: Code | F3: Sector
B4: WORKBOOK TABS | D4: TELECOM PLUS PLC | E4: Communications | F4: TEP
A5: Instructions | B5: This page guides you through much of the preparation for the assignment.
A6: Co. Names | B6: List of all companies for which we have data and allocation to student. Please delete this sheet once you found your company.
A7: FTSE Data | B7: This has the daily cloing prices for a five year period, for the FTSE 350, FTSE-All shares, FTSE 100 Index for for comparison purposes, wherever applicable.
A8: Example Data | B8: This has the daily share prices for a five year period, for the FTSE 350 (FTSEAS) and for each company being allocated. (Example)
A9: Report | B9: In this worksheet you will build your summary of the company analysis (for use in your word report).
A10: Ret_data | B10: You will calculate the daily returns on this sheet.
A11: IS data | B11: This is where you will paste 3 years of Income Statements .
A12: SoFP data | B12: This is where you will paste 3 years of Statements of Financial Position (Balance Sheets)
A13: Custom Data | B13: Get 3 years of ratios for your assigned company and its competitor.
A14: Mkt_calc | B14: This is where you will put all of your market analysis calculations (risk and return in relation to share price).
A15: Fin_Calc | B15: This is where you will put all of your financial analysis calculations (based on the data in the financial statements) and create relevant charts or tables .
B17: INSTRUCTIONS
A18: 1 | B18: In this tab input your student number.
A19: 2 | B19: In tab 'Report' for the company you have been allocated, insert the company code (that the exchange uses) the official company name, and the sector in which it operates.
A20: 3 | B20: In tab 'Ret_data' calculate the daily returns (%) from the historical daily prices (found in the 'Data' tab) for your company the FTSE All-Shares or FTSE350 and/or competitor. Time period is 01/01/2022 to 31/12/2024 (3 years)
A21: 4 | B21: Extract the Income statement (IS) data and Statements of financial position (SoFP) data for each year ending 2022-2025 (3 years of data). Paste the data into the tabs 'IS data' and 'SoFP data' respectively.
A22: 5 | B22: Extract the various ratios for your company and a competitor for the same time period. Paste the data into the 'Custom data' tab and analyse the data creating useful charts/tables.
A23: 6 | B23: In tab 'Mkt_calc' calculate; the daily volatility and average returns, the annual returns and the volatility in each year. Then calculate the overall returns for the whole five years. In this tab you should include the Beta and PE ratio (collected from Yahoo finance ). You will need this for section 3 of your word report ' Market report'.
A24: 7 | B24: In tab 'Fin_calc' perform the analysis - ratio analysis over time and in comparison . Create the charts and tables in this tab. You will need this for section 2 of your word report ' Financial report'.
A25: 8 | B25: In tab 'Report' put all charts and tables that you will be utilising in your word report, these will be duplicates of the charts and tables in 'Fin_calc' and 'Mkt_calc'. Make sure that you number them so that you can cross reference to your report.
A26: 9 | B26: Tidy up the workbook and make it presentable/professional.
A28: REMEMBER: | B28: Regularly save copies of the workbook adding a version number on each save.
B29: Look up the company on FAME, Hargreaves Lansdown and Yahoo finance, to find information about the company and the sector it operates in.

Sheet Co. Names
A1: Company name | B1: BvD sector | C1: Ticker symbol | E1: Students Allocation
A2: LEGAL & GENERAL GROUP PLC | B2: Banking, Insurance & Financial Services | C2: LGEN | E2: Phan Hoàng | F2: An | J2: Once you identified your company please delete this sheet
A3: ADMIRAL GROUP PLC | B3: Banking, Insurance & Financial Services | C3: ADM | E3: Trương Bùi Thành | F3: An
A4: INVESTEC PLC | B4: Banking, Insurance & Financial Services | C4: INVP | E4: Lê Nguyễn Vân | F4: Anh
A5: CMC MARKETS PLC | B5: Banking, Insurance & Financial Services | C5: CMCX | E5: Nguyễn Phương | F5: Anh
A6: GENUS PLC | B6: Biotechnology and Life Sciences | C6: GNS | E6: Trần Duy | F6: Bảo
A7: OXFORD NANOPORE TECHNOLOGIES PLC | B7: Biotechnology and Life Sciences | C7: ONT | E7: Nguyễn Thanh | F7: Bình
A8: CURRYS PLC | B8: Business Services | C8: CURY | E8: Đậu Minh | F8: Châu
A9: EASYJET PLC | B9: Business Services | C9: EZJ | E9: Hoàng Đức | F9: Cường
A10: MITIE GROUP PLC | B10: Business Services | C10: MTO | E10: Trần Minh | F10: Đăng
A11: ITV PLC | B11: Business Services | C11: ITV | E11: Lê Ngân | F11: Hà
A12: SEVERN TRENT PLC | B12: Business Services | C12: SVT | E12: Tăng Thu | F12: Hằng
A13: VODAFONE GROUP PUBLIC LIMITED COMPANY | B13: Communications | C13: VOD | E13: Nguyễn Xuân | F13: Hậu
A14: BT GROUP PLC | B14: Communications | C14: BT.A | E14: Đỗ Minh | F14: Hoàng
... A36: PRIMARY HEALTH PROPERTIES PLC | B36: Property Services | C36: PHP | E36: Nguyễn Thị Hà | F36: Vy
A37: WATCHES OF SWITZERLAND GROUP PLC | B37: Retail | C37: WOSG
A38: EMPIRIC STUDENT PROPERTY PLC | B38: Property Services | C38: ESP
A39: TRAVIS PERKINS PLC | B39: Retail | C39: TPK
A40: THG PLC | B40: Retail | C40: THG
A41: WATCHES OF SWITZERLAND GROUP PLC | B41: Retail | C41: WOSG
A42: WICKES GROUP PLC | B42: Retail | C42: WIX
A43: BAE SYSTEMS PLC | B43: Transport Manufacturing | C43: BA.
A44: CARNIVAL PLC | B44: Transport, Freight & Storage | C44: CCL
A45: FIRSTGROUP PLC | B45: Transport, Freight & Storage | C45: FGP
A46: WIZZ AIR HOLDINGS PLC | B46: Transport, Freight & Storage | C46: WIZZ
A47: J D WETHERSPOON PLC | B47: Travel, Personal & Leisure | C47: JDW
A48: CONVATEC GROUP PLC | B48: Travel, Personal & Leisure | C48: CTEC
... A51: ME GROUP INTERNATIONAL PLC | B51: Travel, Personal & Leisure | C51: MEGP

Sheet FTSE Data
D1: Notes: Please use this data for comparison purposes, wherever applicable
A3: Last Price (£)
A5: Start Date | B5: 44562
A6: End Date | B6: 45657
B8: FTSE 100 Index | C8: FTSE-All Shares | D8: FTSE 350 Index
A9: Dates | B9: UKX Index | C9: ASX Index | D9: NMX Index
A10: 44564 | B10: 7384.54 | C10: 4208.02 | D10: 4228.67
A11: 44565 | B11: 7505.15 | C11: 4276.18 | D11: 4298.76
A12: 44566 | B12: 7516.87 | C12: 4277.51 | D12: 4300.35
A13: 44567 | B13: 7450.37 | C13: 4235.63 | D13: 4257.77
A14: 44568 | B14: 7485.28 | C14: 4249.43 | D14: 4272.27
A15: 44571 | B15: 7445.25 | C15: 4219.71 | D15: 4242.3
A16: 44572 | B16: 7491.37 | C16: 4241.88 | D16: 4264.93
A17: 44573 | B17: 7551.72 | C17: 4270.79 | D17: 4294.04
A18: 44574 | B18: 7563.85 | C18: 4273.23 | D18: 4296.99
A19: 44575 | B19: 7542.95 | C19: 4256.59 | D19: 4280.34
A20: 44578 | B20: 7611.23 | C20: 4292.58 | D20: 4316.64
A21: 44579 | B21: 7563.55 | C21: 4263.04 | D21: 4287.22
... A791: 45657 | B791: 8173.02 | C791: 4467.8 | D791: 4510.61

Sheet BT_GROUP_PLC
A1: Daily pricing series
A2: All figures have been adjusted based on the stock split ratio
B3: Open (£) | C3: High (£) | D3: Low (£) | E3: Close (£) | F3: Volume (shares) | G3: Shares outstanding | H3: Market cap (m £)
A4: 45989 | B4: 1.805 | C4: 1.8145 | D4: 1.786 | E4: 1.8095 | F4: 11775721 | G4: 9967572370 | H4: 18036.322
A5: 45988 | B5: 1.8155 | C5: 1.817 | D5: 1.7895 | E5: 1.806 | F5: 8611085 | G5: 9967572370 | H5: 18001.437
A6: 45987 | B6: 1.773 | C6: 1.8165 | D6: 1.771 | E6: 1.8135 | F6: 27528737 | G6: 9967572370 | H6: 18076.193
A7: 45986 | B7: 1.743 | C7: 1.787 | D7: 1.73 | E7: 1.7805 | F7: 15892389 | G7: 9967572370 | H7: 17747.263
A8: 45985 | B8: 1.7715 | C8: 1.7735 | D8: 1.7425 | E8: 1.7515 | F8: 19331302 | G8: 9967572370 | H8: 17458.202
A9: 45982 | B9: 1.753 | C9: 1.779 | D9: 1.748 | E9: 1.7665 | F9: 24907516 | G9: 9967572370 | H9: 17607.717
A10: 45981 | B10: 1.757 | C10: 1.7625 | D10: 1.744 | E10: 1.7625 | F10: 37631852 | G10: 9967572370 | H10: 17567.847
A11: 45980 | B11: 1.7735 | C11: 1.7785 | D11: 1.746 | E11: 1.746 | F11: 8820614 | G11: 9967572370 | H11: 17403.382
A12: 45979 | B12: 1.776 | C12: 1.7785 | D12: 1.76 | E12: 1.77 | F12: 32634124 | G12: 9967572370 | H12: 17642.603
A13: 45978 | B13: 1.772 | C13: 1.7885 | D13: 1.755 | E13: 1.787 | F13: 11001799 | G13: 9967572370 | H13: 17812.051
A14: 45975 | B14: 1.7915 | C14: 1.7915 | D14: 1.75 | E14: 1.765 | F14: 14282956 | G14: 9967572370 | H14: 17592.765
A15: 45974 | B15: 1.7825 | C15: 1.8065 | D15: 1.782 | E15: 1.7945 | F15: 7640854 | G15: 9967572370 | H15: 17886.809
... A6019: 37258 | B6019: 0 | C6019: 0 | D6019: 0 | E6019: 2.495 | F6019: 0 | G6019: 8670033956 | H6019: 21631.734

Sheet TELECOM_PLUS_PLC
A1: Daily pricing series
A2: All figures have been adjusted based on the stock split ratio
B3: Open (£) | C3: High (£) | D3: Low (£) | E3: Close (£) | F3: Volume (shares) | G3: Shares outstanding | H3: Market cap (m £)
A4: 45989 | B4: 16.040001 | C4: 16.08 | D4: 15.82 | E4: 15.82 | F4: 271630 | G4: 80081517 | H4: 1266.8896
A5: 45988 | B5: 16.48 | C5: 16.48 | D5: 15.94 | E5: 15.98 | F5: 132080 | G5: 80080823 | H5: 1279.6915
A6: 45987 | B6: 16.4 | C6: 16.5 | D6: 15.94 | E6: 16.16 | F6: 248721 | G6: 80080823 | H6: 1294.1061
A7: 45986 | B7: 17.48 | C7: 17.48 | D7: 16.42 | E7: 16.42 | F7: 319783 | G7: 80080823 | H7: 1314.9271
A8: 45985 | B8: 17.360001 | C8: 17.719999 | D8: 17.32 | E8: 17.42 | F8: 187097 | G8: 80080823 | H8: 1395.0079
A9: 45982 | B9: 17.24 | C9: 17.860001 | D9: 16.98 | E9: 17.700001 | F9: 428406 | G9: 80080823 | H9: 1417.4306
A10: 45981 | B10: 16.959999 | C10: 16.98 | D10: 16.76 | E10: 16.860001 | F10: 126734 | G10: 80080823 | H10: 1350.1627
A11: 45980 | B11: 16.780001 | C11: 17.040001 | D11: 16.74 | E11: 16.860001 | F11: 273994 | G11: 80080823 | H11: 1350.1627
A12: 45979 | B12: 16.9 | C12: 17.040001 | D12: 16.82 | E12: 16.98 | F12: 146673 | G12: 80080823 | H12: 1359.7723
A13: 45978 | B13: 16.82 | C13: 17.16 | D13: 16.82 | E13: 17.1 | F13: 140647 | G13: 80080823 | H13: 1369.3821
A14: 45975 | B14: 17.120001 | C14: 17.24 | D14: 16.719999 | E14: 17.120001 | F14: 101308 | G14: 80080823 | H14: 1370.9838
A15: 45974 | B15: 17.18 | C15: 17.18 | D15: 16.9 | E15: 16.9 | F15: 166516 | G15: 80080823 | H15: 1353.3659
... A5107: 38583 | B5107: 0 | C5107: 0 | D5107: 0 | E5107: 1.505 | F5107: 0 | G5107: 68140720 | H5107: 102.55178

Sheet My Data
B1: FTSEAS | C1: MOTR | D1: COMPETITOR
A2: Date | B2: Close | C2: Close | G2: This data shown here is just for illustration purpsoes, please replace with your allocated company, choosen competitor and choosen index
A3: 44564 | B3: 4228.67 | C3: 15.86 | D3: 1.6955
A4: 44565 | B4: 4298.76 | C4: 16.120001 | D4: 1.7265
A5: 44566 | B5: 4300.35 | C5: 15.84 | D5: 1.7575
A6: 44567 | B6: 4257.77 | C6: 15.38 | D6: 1.7555
A7: 44568 | B7: 4272.27 | C7: 15.42 | D7: 1.7605
A8: 44571 | B8: 4242.3 | C8: 15.34 | D8: 1.778
A9: 44572 | B9: 4264.93 | C9: 15.28 | D9: 1.7715
A10: 44573 | B10: 4294.04 | C10: 15.34 | D10: 1.7465
A11: 44574 | B11: 4296.99 | C11: 15.34 | D11: 1.7815
A12: 44575 | B12: 4280.34 | C12: 15.36 | D12: 1.796
A13: 44578 | B13: 4316.64 | C13: 15.12 | D13: 1.8105
A14: 44579 | B14: 4287.22 | C14: 15.08 | D14: 1.866
... A784: 45657 | B784: 4510.61 | C784: 17.18 | D784: 1.4405

Sheet Report
A1: Code | B1: MOTR
A2: Name | B2: Motorpoint Group PLC
A3: Sector
A6: Chart 1 | B6: Title
A20: Chart 2 | B20: Title
A27: Chart 4 | B27: Title
A34: Chart 5 | B34: Title
A41: Chart 6 | B41: Title
A48: Chart 7 | B48: Title
A55: Chart 8 | B55: Title
D85: Company | E85: Competitor
B86: Beta (3Y) | D86: 0.83 | E86: 0.81
B87: PE ratio (TTM) | C87: 2022 | D87: 29.87 | E87: 13.30
C88: 2023 | D88: 23.22 | E88: 8.01
C89: 2024 | D89: 18.77 | E89: 15.31

Sheet Ret_data
A1: Date | B1: MOTR | C1: COMPETITOR | D1: FTSEAS
A2: ='My Data'!A3 -> 44564 | B2: 0 | C2: 0 | D2: 0 | J2: Formula for Daily returns = Ln (Pt/Pt-1)
A3: ='My Data'!A4 -> 44565 | B3: =LN('My Data'!#REF!/'My Data'!#REF!) -> #REF! | C3: =LN('My Data'!#REF!/'My Data'!D3) -> #REF! | D3: =LN('My Data'!B3/'My Data'!B4) -> -0.016439086
A4: ='My Data'!A5 -> 44566 | B4: =LN('My Data'!#REF!/'My Data'!#REF!) -> #REF! | C4: =LN('My Data'!#REF!/'My Data'!#REF!) -> #REF! | D4: =LN('My Data'!B4/'My Data'!B5) -> -0.00036980572 | M4: natural log = (current price / previous price)
A5: ='My Data'!A6 -> 44567 | B5: =LN('My Data'!#REF!/'My Data'!#REF!) -> #REF! | C5: =LN('My Data'!#REF!/'My Data'!#REF!) -> #REF! | D5: =LN('My Data'!B5/'My Data'!B6) -> 0.0099508657
A6: ='My Data'!A7 -> 44568 | B6: =LN('My Data'!#REF!/'My Data'!#REF!) -> #REF! | C6: =LN('My Data'!#REF!/'My Data'!#REF!) -> #REF! | D6: =LN('My Data'!B6/'My Data'!B7) -> -0.0033997529
A7: ='My Data'!A8 -> 44571 | B7: =LN('My Data'!#REF!/'My Data'!#REF!) -> #REF! | C7: =LN('My Data'!#REF!/'My Data'!#REF!) -> #REF! | D7: =LN('My Data'!B7/'My Data'!B8) -> 0.0070397269
A8: ='My Data'!A9 -> 44572 | B8: =LN('My Data'!#REF!/'My Data'!#REF!) -> #REF! | C8: =LN('My Data'!#REF!/'My Data'!#REF!) -> #REF! | D8: =LN('My Data'!B8/'My Data'!B9) -> -0.0053201931
A9: ='My Data'!A10 -> 44573 | B9: =LN('My Data'!#REF!/'My Data'!#REF!) -> #REF! | C9: =LN('My Data'!#REF!/'My Data'!#REF!) -> #REF! | D9: =LN('My Data'!B9/'My Data'!B10) -> -0.0068022466
A10: ='My Data'!A11 -> 44574 | B10: =LN('My Data'!#REF!/'My Data'!#REF!) -> #REF! | C10: =LN('My Data'!#REF!/'My Data'!#REF!) -> #REF! | D10: =LN('My Data'!B10/'My Data'!B11) -> -0.00068676285
A11: ='My Data'!A12 -> 44575 | B11: =LN('My Data'!#REF!/'My Data'!#REF!) -> #REF! | C11: =LN('My Data'!#REF!/'My Data'!#REF!) -> #REF! | D11: =LN('My Data'!B11/'My Data'!B12) -> 0.0038823319
A12: ='My Data'!A13 -> 44578 | B12: =LN('My Data'!#REF!/'My Data'!#REF!) -> #REF! | C12: =LN('My Data'!#REF!/'My Data'!#REF!) -> #REF! | D12: =LN('My Data'!B12/'My Data'!B13) -> -0.0084448762
A13: ='My Data'!A14 -> 44579 | B13: =LN('My Data'!#REF!/'My Data'!#REF!) -> #REF! | C13: =LN('My Data'!#REF!/'My Data'!#REF!) -> #REF! | D13: =LN('My Data'!B13/'My Data'!B14) -> 0.0068388176
A14: ='My Data'!A15 -> 44580 | B14: =LN('My Data'!#REF!/'My Data'!#REF!) -> #REF! | C14: =LN('My Data'!#REF!/'My Data'!#REF!) -> #REF! | D14: =LN('My Data'!B14/'My Data'!B15) -> -0.0028904682
A15: ='My Data'!A16 -> 44581 | B15: =LN('My Data'!#REF!/'My Data'!#REF!) -> #REF! | C15: =LN('My Data'!#REF!/'My Data'!#REF!) -> #REF! | D15: =LN('My Data'!B15/'My Data'!B16) -> 7.2101826e-05
A16: ='My Data'!A17 -> 44582 | B16: =LN('My Data'!#REF!/'My Data'!#REF!) -> #REF! | C16: =LN('My Data'!#REF!/'My Data'!#REF!) -> #REF! | D16: =LN('My Data'!B16/'My Data'!B17) -> 0.013384297
... A783: ='My Data'!A784 -> 45657 | B783: =LN('My Data'!#REF!/'My Data'!#REF!) -> #REF! | C783: =LN('My Data'!#REF!/'My Data'!#REF!) -> #REF! | D783: =LN('My Data'!B783/'My Data'!B784) -> -0.0069388256
A784: ='My Data'!A785 -> 0
A785: ='My Data'!A786 -> 0
A786: ='My Data'!A787 -> 0
A787: ='My Data'!A788 -> 0
A788: ='My Data'!A789 -> 0
A789: ='My Data'!A790 -> 0
A790: ='My Data'!A791 -> 0
A791: ='My Data'!A792 -> 0
A792: ='My Data'!A793 -> 0
A793: ='My Data'!A794 -> 0
A794: ='My Data'!A795 -> 0
A795: ='My Data'!A796 -> 0
... A1263: ='My Data'!A1264 -> 0

Sheet FTSE All-Share Historical 
A1: Date | B1: Price
A2: 43832 | B2: 4285.97
A3: 43833 | B3: 4290.29
A4: 43836 | B4: 4260.71
A5: 43837 | B5: 4262.43
A6: 43838 | B6: 4256.79
A7: 43839 | B7: 4267.27
A8: 43840 | B8: 4259.91
A9: 43843 | B9: 4278.83
A10: 43844 | B10: 4282.37
A11: 43845 | B11: 4290.42
A12: 43846 | B12: 4275.36
A13: 43847 | B13: 4311.06
... A1262: 45656 | B1262: 4479.42

Sheet IS data
A1: PASTE 3 YEARS OF INCOME STATEMENT DATA HERE | I1: 45747 | J1: 45016 | K1: 44651 | L1: 44286
I2: th GBP | J2: th GBP | K2: th GBP | L2: th GBP
B3: 2024 | C3: 2023 | D3: 2022 | J3: 2024 | K3: 2023 | L3: 2022
B4: th GBP | C4: th GBP | D4: th GBP | J4: th GBP | K4: th GBP | L4: th GBP
A5: ∟ Turnover | B5: 2039131 | C5: 2475160 | D5: 967.433 | I5: ∟ Turnover | J5: 20797000 | K5: 20681000 | L5: 20850000
A6: ∟ National Turnover | B6: 2039131 | C6: 2475160 | D6: 967.433 | I6: ∟ National Turnover
A7: ∟ Overseas Turnover | I7: ∟ Overseas Turnover
A8: ∟ Cost of Sales | B8: -1683921 | C8: -2168964 | D8: -778.958 | I8: ∟ Cost of Sales
A9: ∟ Exceptional Items pre GP | I9: ∟ Exceptional Items pre GP
A10: ∟ Other Income pre GP | I10: ∟ Other Income pre GP
A11: ∟ Gross Profit | B11: 355.21 | C11: 306.196 | D11: 188.475 | I11: ∟ Gross Profit
A12: ∟ Administration Expenses | B12: -250.337 | C12: -221.458 | D12: -139.399 | I12: ∟ Administration Expenses | J12: -17634000 | K12: -17494000 | L12: -17673000
A13: ∟ Other Operating Income/Costs pre OP | B13: 1.377 | C13: 1.156 | D13: 1.844 | I13: ∟ Other Operating Income/Costs pre OP
A14: ∟ Exceptional Items pre OP | I14: ∟ Exceptional Items pre OP | J14: -949 | K14: -568 | L14: -292
A15: ∟ Operating Profit | B15: 106.25 | C15: 85.894 | D15: 50.92 | I15: ∟ Operating Profit | J15: 2214000 | K15: 2619000 | L15: 2885000
A16: ∟ Other Income | C16: 3.595 | D16: -1.139 | I16: ∟ Other Income | J16: -21 | K16: -59
A17: ∟ Total Other Income & Int. Received | B17: 3.482 | C17: 4.611 | D17: -1.003 | I17: ∟ Total Other Income & Int. Received | J17: 160 | K17: 4 | L17: 12
A18: ∟ Exceptional Items | I18: ∟ Exceptional Items
A19: ∟ Profit (Loss) on Sale of Operations | I19: ∟ Profit (Loss) on Sale of Operations
A20: ∟ Costs of Reorganisation | I20: ∟ Costs of Reorganisation
A21: ∟ Profit (Loss) on Disposal | I21: ∟ Profit (Loss) on Disposal
A22: ∟ Other Exceptional Items | I22: ∟ Other Exceptional Items
A23: ∟ Profit (Loss) before Interest paid | B23: 109.732 | C23: 90.505 | D23: 49.917 | I23: ∟ Profit (Loss) before Interest paid | J23: 2374000 | K23: 2623000 | L23: 2897000
A24: ∟ Interest Received | B24: 3.482 | C24: 1.016 | D24: 136 | I24: ∟ Interest Received | J24: 181 | K24: 63 | L24: 12
A25: ∟ Interest Paid | B25: -9.255 | C25: -5.051 | D25: -2.709 | I25: ∟ Interest Paid | J25: -1188000 | K25: -894 | L25: -934
A26: ∟ Paid to Bank | B26: -9.229 | C26: -5.032 | D26: -2.187 | I26: ∟ Paid to Bank
A27: ∟ Paid on Hire Purchase | I27: ∟ Paid on Hire Purchase
A28: ∟ Paid on Leasing | B28: -26 | C28: -17 | D28: -238 | I28: ∟ Paid on Leasing | J28: -134 | K28: -133 | L28: -133
A29: ∟ Other Interest Paid | C29: -2 | D29: -284 | I29: ∟ Other Interest Paid | J29: -1054000 | K29: -761 | L29: -801
A30: ∟ Net Interest | B30: -5.773 | C30: -4.035 | D30: -2.573 | I30: ∟ Net Interest | J30: -1007000 | K30: -831 | L30: -922
A31: ∟ Profit (Loss) before Tax | B31: 100.477 | C31: 85.454 | D31: 47.208 | I31: ∟ Profit (Loss) before Tax | J31: 1186000 | K31: 1729000 | L31: 1963000
A32: ∟ Taxation | B32: -29.44 | C32: -17.293 | D32: -12.205 | I32: ∟ Taxation | J32: -331 | K32: 176 | L32: -689
A33: ∟ Profit (Loss) after Tax | B33: 71.037 | C33: 68.161 | D33: 35.003 | I33: ∟ Profit (Loss) after Tax | J33: 855 | K33: 1905000 | L33: 1274000
A34: ∟ Extraordinary Items | I34: ∟ Extraordinary Items
A35: ∟ Minority Interests | C35: 265 | I35: ∟ Minority Interests
A36: ∟ Profit (Loss) for period [=Net income] | B36: 71.037 | C36: 68.426 | D36: 35.003 | I36: ∟ Profit (Loss) for period [=Net income] | J36: 855 | K36: 1905000 | L36: 1274000
A37: ∟ Dividends (Distributable profit) | B37: -64.982 | C37: -50.601 | D37: -44.787 | I37: ∟ Dividends (Distributable profit) | J37: -757 | K37: -751 | L37: -228
A38: ∟ Retained Profit(Loss) | B38: 6.055 | C38: 17.825 | D38: -9.784 | I38: ∟ Retained Profit(Loss) | J38: 98 | K38: 1154000 | L38: 1046000
A40: ∟ Depreciation | B40: 21.618 | C40: 3.968 | D40: 4.558 | I40: ∟ Depreciation | J40: 3000000 | K40: 3653000 | L40: 3357000
A41: ∟ Depreciation Owned Assets | B41: 21.358 | C41: 3.968 | D41: 4.558 | I41: ∟ Depreciation Owned Assets | J41: 2892000 | K41: 2878000 | L41: 2669000
A42: ∟ Depreciation Other Assets | B42: 260 | I42: ∟ Depreciation Other Assets | K42: 689 | L42: 688
A43: ∟ Impairment of Tangible Assets | I43: ∟ Impairment of Tangible Assets | J43: 108 | K43: 86
A44: ∟ Audit Fee | B44: 726 | C44: 495 | D44: 314 | I44: ∟ Audit Fee | J44: 20.767 | K44: 19.832 | L44: 17.409
A45: ∟ Audit Non-fee expenses | B45: 57 | C45: 35 | D45: 31 | I45: ∟ Audit Non-fee expenses | J45: 2.52 | K45: 2.608 | L45: 3.296
A46: ∟ Tax Advice | I46: ∟ Tax Advice
A47: ∟ Non-Tax Advisory Services | B47: 57 | C47: 35 | D47: 31 | I47: ∟ Non-Tax Advisory Services | J47: 2.52 | K47: 2.608 | L47: 3.296
A48: ∟ Other Auditors Services | I48: ∟ Other Auditors Services
A49: ∟ Non-Audit Fees paid to Other Auditors | I49: ∟ Non-Audit Fees paid to Other Auditors
A50: ∟ Total Amortization and Impairment | B50: 18.057 | C50: 17.407 | D50: 15.786 | I50: ∟ Total Amortization and Impairment | J50: 2398000 | K50: 1165000 | L50: 1048000
A51: ∟ Amortisation | B51: 18.057 | C51: 17.407 | D51: 15.786 | I51: ∟ Amortisation | J51: 1900000 | K51: 1165000 | L51: 1048000
A52: ∟ Impairment | I52: ∟ Impairment | J52: 498
A53: ∟ Total Operating Lease Rentals | I53: ∟ Total Operating Lease Rentals
A54: ∟ Hire of Plant & Machinery | I54: ∟ Hire of Plant & Machinery
A55: ∟ Land & Building or Property Rents & Other | I55: ∟ Land & Building or Property Rents & Other
A56: ∟ Research & Development | I56: ∟ Research & Development | J56: 726 | K56: 683 | L56: 604
A57: ∟ Foreign Exchange Gains/Losses | I57: ∟ Foreign Exchange Gains/Losses | J57: 2 | K57: 9 | L57: -3
A58: ∟ Remuneration | B58: 124.558 | C58: 95.651 | D58: 86.48 | I58: ∟ Remuneration | J58: 3489000 | K58: 3588000 | L58: 3856000
A59: ∟ Wages & Salaries | B59: 106.106 | C59: 80.495 | D59: 75.294 | I59: ∟ Wages & Salaries | J59: 3843000 | K59: 3858000 | L59: 3746000
A60: ∟ Social Security Costs | B60: 9.729 | C60: 9.853 | D60: 7.649 | I60: ∟ Social Security Costs | J60: 425 | K60: 424 | L60: 400
A61: ∟ Pension Costs | B61: 3.563 | C61: 2.454 | D61: 2.577 | I61: ∟ Pension Costs | J61: 582 | K61: 590 | L61: 591
A62: ∟ Other Staff Costs | B62: 5.16 | C62: 2.849 | D62: 960 | I62: ∟ Other Staff Costs | J62: 71 | K62: 80 | L62: 108
A63: ∟ Directors' Remuneration | B63: 4.554 | C63: 4.554 | D63: 3.652 | I63: ∟ Directors' Remuneration | J63: 8.434 | K63: 6.837 | L63: 6.986
A64: ∟ Directors' Fees | B64: 1.799 | C64: 1.799 | D64: 2.102 | I64: ∟ Directors' Fees | J64: 1.979 | K64: 1.848 | L64: 1.835
A65: ∟ Pension Contribution | B65: 12 | C65: 12 | D65: 12 | I65: ∟ Pension Contribution | J65: 187 | K65: 185 | L65: 257
A66: ∟ Other Emoluments | B66: 2.743 | C66: 2.743 | D66: 1.538 | I66: ∟ Other Emoluments | J66: 6.268 | K66: 4.804 | L66: 4.894
A67: ∟ Highest Paid Director | B67: 1.52 | C67: 1.52 | D67: 1.214 | I67: ∟ Highest Paid Director | J67: 3.719 | K67: 3.089 | L67: 3.46
A68: ∟ EBITDA | B68: 145.925 | C68: 107.269 | D68: 71.264 | I68: ∟ EBITDA | J68: 7612000 | K68: 7437000 | L68: 7290000
A69: ∟ Number of employees | B69: 2.493 | C69: 2.078 | D69: 1.987 | I69: ∟ Number of employees | J69: 94.9 | K69: 98.8 | L69: 99
B71: 45382 | C71: 45016 | D71: 44651
B72: th GBP | C72: th GBP | D72: th GBP

Sheet SoFP data
A1: PASTE 3 YEARS OF STATEMENT OF FINANCIAL POSITION DATA HERE | J1: 45382 | K1: 45016 | L1: 44651
J2: th GBP | K2: th GBP | L2: th GBP
A3: Original documents | B3: 2024 | C3: 2023 | D3: 2022 | I3: Original documents | J3: 2024 | K3: 2023 | L3: 2022
B4: th GBP | C4: th GBP | D4: th GBP | J4: th GBP | K4: th GBP | L4: th GBP
A5: Fixed Assets | I5: Fixed Assets
A6: Tangible Assets | B6: 26.773 | C6: 34.087 | D6: 34.525 | I6: Tangible Assets | J6: 22562000 | K6: 25648000 | L6: 25028000
A7: ∟ Land & Buildings | B7: 23.39 | C7: 29.002 | D7: 30.216 | I7: ∟ Land & Buildings | J7: 20514000 | K7: 23252000 | L7: 22641000
A8: ∟ Freehold Land | I8: ∟ Freehold Land
A9: ∟ Leasehold Land | I9: ∟ Leasehold Land
A10: ∟ Fixtures & Fittings | I10: ∟ Fixtures & Fittings
A11: ∟ Plant & Vehicles | B11: 534 | C11: 549 | D11: 635 | I11: ∟ Plant & Vehicles | K11: 385 | L11: 369
A12: ∟ Plant | B12: 365 | C12: 375 | D12: 409 | I12: ∟ Plant
A13: ∟ Vehicles | B13: 169 | C13: 174 | D13: 226 | I13: ∟ Vehicles | K13: 385 | L13: 369
A14: ∟ Other Fixed Assets | B14: 2.849 | C14: 4.536 | D14: 3.674 | I14: ∟ Other Fixed Assets | J14: 2048000 | K14: 2011000 | L14: 2018000
A15: Intangible Assets | B15: 139.527 | C15: 146.233 | D15: 156.16 | I15: Intangible Assets | J15: 16562000 | K15: 13687000 | L15: 13809000
A16: Investments & other fixed assets | B16: 63.941 | C16: 47.529 | D16: 32.855 | I16: Investments & other fixed assets | J16: 3896000 | K16: 3960000 | L16: 2029000
A17: ∟ Fixed Assets | B17: 230.241 | C17: 227.849 | D17: 223.54 | I17: ∟ Fixed Assets | J17: 43020000 | K17: 43295000 | L17: 40866000
A19: Current Assets | I19: Current Assets
A20: Stock & W.I.P. | B20: 3.749 | C20: 5.698 | D20: 4.152 | I20: Stock & W.I.P. | J20: 409 | K20: 349 | L20: 610
A21: ∟ Stock | I21: ∟ Stock
A22: ∟ W.I.P. | I22: ∟ W.I.P.
A23: ∟ Finished Goods | I23: ∟ Finished Goods
A24: Trade Debtors | B24: 86.606 | C24: 50.241 | D24: 46.254 | I24: Trade Debtors | J24: 3309000 | K24: 2960000 | L24: 3229000
A25: Bank & Deposits | B25: 57.829 | C25: 193.804 | D25: 29.647 | I25: Bank & Deposits | J25: 414 | K25: 392 | L25: 777
A26: Other Current Assets | B26: 271.72 | C26: 316.02 | D26: 156.998 | I26: Other Current Assets | J26: 2058000 | K26: 2063000 | L26: 1442000
A27: ∟ Group Loans (asset) | I27: ∟ Group Loans (asset) | J27: 163 | K27: 268
A28: ∟ Directors Loans (asset) | I28: ∟ Directors Loans (asset)
A29: ∟ Other Debtors | B29: 39.625 | C29: 28.407 | D29: 18.004 | I29: ∟ Other Debtors | J29: 724 | K29: 665 | L29: 273
A30: ∟ Prepayments | B30: 231.994 | C30: 284.53 | D30: 138.994 | I30: ∟ Prepayments | J30: 748 | K30: 703 | L30: 673
A31: ∟ Deferred Taxation | B31: 101 | C31: 3.083 | I31: ∟ Deferred Taxation | J31: 423 | K31: 427 | L31: 496
A32: Investments & other current assets | B32: 1.246 | C32: 1.127 | D32: 5.194 | I32: Investments & other current assets | J32: 2529000 | K32: 3693000 | L32: 2850000
A33: ∟ Current Assets | B33: 421.15 | C33: 566.89 | D33: 242.245 | I33: ∟ Current Assets | J33: 8719000 | K33: 9457000 | L33: 8908000
A35: Current Liabilities | I35: Current Liabilities
A36: Trade Creditors | B36: -100.974 | C36: -38.83 | D36: -28.644 | I36: Trade Creditors | J36: -5025000 | K36: -4196000 | L36: -4143000
A37: Short Term Loans & Overdrafts | I37: Short Term Loans & Overdrafts | J37: -1395000 | K37: -2572000 | L37: -1668000
A38: ∟ Bank Overdrafts | I38: ∟ Bank Overdrafts
A39: ∟ Group Loans (short t.) | I39: ∟ Group Loans (short t.)
A40: ∟ Director Loans (short t.) | I40: ∟ Director Loans (short t.)
A41: ∟ Hire Purch. & Leas. (short t.) | I41: ∟ Hire Purch. & Leas. (short t.) | K41: -800 | L41: -795
A42: ∟ Hire Purchase (short t.) | I42: ∟ Hire Purchase (short t.)
A43: ∟ Leasing (short t.) | I43: ∟ Leasing (short t.) | K43: -800 | L43: -795
A44: ∟ Other Short Term Loans | I44: ∟ Other Short Term Loans | J44: -1395000 | K44: -1772000 | L44: -873
A45: Total Other Current Liabilities | B45: -136.35 | C45: -433.92 | D45: -130.509 | I45: Total Other Current Liabilities | J45: -3398000 | K45: -3624000 | L45: -3235000
A46: ∟ Corporation Tax | D46: -8 | I46: ∟ Corporation Tax | J46: -92 | K46: -78 | L46: -90
A47: ∟ Dividends payable | I47: ∟ Dividends payable
A48: ∟ Accruals & Def. Inc. (short t.) | B48: -113.723 | C48: -417.354 | D48: -113.493 | I48: ∟ Accruals & Def. Inc. (short t.) | J48: -898 | K48: -990 | L48: -894
A49: ∟ Social Securities & V.A.T. | B49: -11.449 | C49: -16.566 | D49: -9.457 | I49: ∟ Social Securities & V.A.T. | J49: -544 | K49: -581 | L49: -573
A50: ∟ Other Current Liabilities | B50: -11.178 | D50: -7.551 | I50: ∟ Other Current Liabilities | J50: -1864000 | K50: -1975000 | L50: -1678000
A51: ∟ Current Liabilities | B51: -237.324 | C51: -472.75 | D51: -159.153 | I51: ∟ Current Liabilities | J51: -9818000 | K51: -10392000 | L51: -9046000
A53: ∟ Net Current Assets | B53: 183.826 | C53: 94.14 | D53: 83.092 | I53: ∟ Net Current Assets | J53: -1099000 | K53: -935 | L53: -138
A54: ∟ Net Tangible Assets | B54: 274.54 | C54: 175.756 | D54: 150.472 | I54: ∟ Net Tangible Assets | J54: 25359000 | K54: 28673000 | L54: 26919000
A55: ∟ Working Capital | B55: -10.619 | C55: 17.109 | D55: 21.762 | I55: ∟ Working Capital | J55: -1307000 | K55: -887 | L55: -304
A56: ∟ Total Assets | B56: 651.391 | C56: 794.739 | D56: 465.785 | I56: ∟ Total Assets | J56: 51739000 | K56: 52752000 | L56: 49774000
A57: ∟ Total Assets minus Current Liabilities | B57: 414.067 | C57: 321.989 | D57: 306.632 | I57: ∟ Total Assets minus Current Liabilities | J57: 41921000 | K57: 42360000 | L57: 40728000
A59: Long Term Liabilities | I59: Long Term Liabilities
A60: Long Term Debt | B60: -176.509 | C60: -90.38 | D60: -99.981 | I60: Long Term Debt | J60: -17131000 | K60: -21308000 | L60: -20277000
A61: ∟ Group Loans (long t.) | I61: ∟ Group Loans (long t.)
A62: ∟ Director Loans (long t.) | I62: ∟ Director Loans (long t.)
A63: ∟ Hire Purchase & Lease (LT) | C63: -659 | D63: -766 | I63: ∟ Hire Purchase & Lease (LT) | K63: -4559000 | L63: -4965000
A64: ∟ Hire Purchase (long t.) | I64: ∟ Hire Purchase (long t.)
A65: ∟ Leasing (long t.) | C65: -659 | D65: -766 | I65: ∟ Leasing (long t.) | K65: -4559000 | L65: -4965000
A66: ∟ Preference Shares (part of Liabilities) | I66: ∟ Preference Shares (part of Liabilities)
A67: ∟ Other Long Term Loans | B67: -176.509 | C67: -89.721 | D67: -99.215 | I67: ∟ Other Long Term Loans | J67: -17131000 | K67: -16749000 | L67: -15312000
A68: Total Other Long Term Liab. | B68: -3.821 | I68: Total Other Long Term Liab. | J68: -5446000 | K68: -1410000 | L68: -1613000
A69: ∟ Accruals & Def. Inc. (long t.) | I69: ∟ Accruals & Def. Inc. (long t.) | J69: -342 | K69: -403
A70: ∟ Other Long Term Liab. | B70: -3.821 | I70: ∟ Other Long Term Liab. | J70: -5104000 | K70: -1007000 | L70: -1613000
A71: Provisions for Other Liab. | B71: -1.106 | C71: -901 | D71: -1.078 | I71: Provisions for Other Liab. | J71: -1944000 | K71: -1989000 | L71: -2399000
A72: ∟ Deferred Tax | B72: -1.106 | C72: -901 | D72: -1.078 | I72: ∟ Deferred Tax | J72: -1533000 | K72: -1620000 | L72: -1960000
A73: ∟ Other Provisions | I73: ∟ Other Provisions | J73: -411 | K73: -369 | L73: -439
A74: Pension Liabilities | I74: Pension Liabilities | J74: -4882000 | K74: -3139000 | L74: -1143000
A75: ∟ Long Term Liabilities | B75: -181.436 | C75: -91.281 | D75: -101.059 | I75: ∟ Long Term Liabilities | J75: -29403000 | K75: -27846000 | L75: -25432000
A77: ∟ Net assets | B77: 232.631 | C77: 230.708 | D77: 205.573 | I77: ∟ Net assets | J77: 12518000 | K77: 14514000 | L77: 15296000
A79: Shareholders Funds | I79: Shareholders Funds
A80: Issued Capital | B80: 4.007 | C80: 4.003 | D80: 3.982 | I80: Issued Capital | J80: 499 | K80: 499 | L80: 499
A81: ∟ Ordinary Shares | I81: ∟ Ordinary Shares
A82: ∟ Preference Shares (part of Equity) | I82: ∟ Preference Shares (part of Equity)
A83: ∟ Other Shares | I83: ∟ Other Shares
A84: Total Reserves | B84: 228.624 | C84: 226.705 | D84: 202.502 | I84: Total Reserves | J84: 12019000 | K84: 14015000 | L84: 14797000
A85: ∟ Share Premium Account | B85: 151.553 | C85: 150.652 | D85: 147.112 | I85: ∟ Share Premium Account | J85: 1051000 | K85: 1051000 | L85: 1051000
A86: ∟ Revaluation Reserves | I86: ∟ Revaluation Reserves
A87: ∟ Profit (Loss) Account | B87: 93.802 | C87: 82.598 | D87: 61.935 | I87: ∟ Profit (Loss) Account | J87: 9565000 | K87: 11431000 | L87: 12403000
A88: ∟ Other Reserves | B88: -16.731 | C88: -6.545 | D88: -6.545 | I88: ∟ Other Reserves | J88: 1403000 | K88: 1533000 | L88: 1343000
A89: Balance sheet Minorities | B89: n.a. | C89: n.a. | D89: -911 | I89: Balance sheet Minorities | J89: n.a. | K89: n.a. | L89: n.a.
A90: ∟ Shareholders Funds | B90: 232.631 | C90: 230.708 | D90: 205.573 | I90: ∟ Shareholders Funds | J90: 12518000 | K90: 14514000 | L90: 15296000

Sheet Custom data
A1: PASTE 3 YEARS OF DATA FROM CHOOSEN DATA SOURCE WITH KEY RATIOS FOR OWN COMPANY AND COMPETITOR. ANALYSE AND CREATE CHARTS.
A3: Profitability Ratios: Profit margin (%) | E3: Efficiency Ratios: Net Assets Turnover (x) | I3: Gearing ratios: Gearing (%) | M3: Equity Ratios: | Q3: Liquidity ratios:
B4: Company | C4: Competitor/Industry Average | F4: Company | G4: Competitor/Industry Average | J4: Company | K4: Competitor/Industry Average | N4: Company | O4: Competitor/Industry Average | R4: Company | S4: Competitor/Industry Average
A5: 2022 | B5: 4.88 | C5: 9.41 | E5: 2022 | F5: 3.16 | G5: 0.51 | I5: 2022 | J5: 49.16 | K5: 177.17 | M5: 2022 | N5: 22.96 | O5: 12.83 | Q5: 2022 | R5: 1.52 | S5: 0.98
A6: 2023 | B6: 3.45 | C6: 8.36 | E6: 2023 | F6: 7.69 | G6: 0.49 | I6: 2023 | J6: 39.57 | K6: 209.58 | M6: 2023 | N6: 37.04 | O6: 11.91 | Q6: 2023 | R6: 1.2 | S6: 0.91
A7: 2024 | B7: 4.93 | C7: 5.7 | E7: 2024 | F7: 4.92 | G7: 0.5 | I7: 2024 | J7: 77.99 | K7: 246.03 | M7: 2024 | N7: 43.19 | O7: 9.47 | Q7: 2024 | R7: 1.77 | S7: 0.89

Sheet Mkt_calc
B1: Equity Return and Risk
C2: Company | D2: FTSEAS | E2: Competitor
B3: Average Daily Return | C3: =AVERAGE(Ret_data!B2:B783) -> #REF! | D3: =AVERAGE(Ret_data!D2:D783) -> -8.2538205e-05 | E3: =AVERAGE(Ret_data!C2:C783) -> #REF!
B4: Volatility (Standard deviation) | C4: =STDEV(Ret_data!B2:B783) -> #REF! | D4: =STDEV(Ret_data!D2:D783) -> 0.0079590321 | E4: =STDEV(Ret_data!C2:C783) -> #REF!
B5: 3 year return | C5: =C3*252*3 -> #REF! | D5: =D3*252*3 -> -0.062398883 | E5: =E3*252*3 -> #REF!
A6: Annual return | B6: 2022 | C6: =AVERAGE(Ret_data!B2:B261)*252 -> #REF! | D6: =AVERAGE(Ret_data!D2:D261)*252 -> 0.026697664 | E6: =AVERAGE(Ret_data!C2:C261)*252 -> #REF!
B7: 2023 | C7: =AVERAGE(Ret_data!B262:B521)*252 -> #REF! | D7: =AVERAGE(Ret_data!D262:D521)*252 -> -0.036859854 | E7: =AVERAGE(Ret_data!C262:C521)*252 -> #REF!
B8: 2024 | C8: =AVERAGE(Ret_data!B522:B783)*252 -> #REF! | D8: =AVERAGE(Ret_data!D522:D783)*252 -> -0.051996716 | E8: =AVERAGE(Ret_data!C522:C783)*252 -> #REF!
A9: Annual volatility | B9: 2022 | C9: =STDEV(Ret_data!B2:B261)*SQRT(252) -> #REF! | D9: =STDEV(Ret_data!D2:D261)*SQRT(252) -> 0.16267515 | E9: =STDEV(Ret_data!C2:C261)*SQRT(252) -> #REF!
B10: 2023 | C10: =STDEV(Ret_data!B262:B521)*SQRT(252) -> #REF! | D10: =STDEV(Ret_data!D262:D521)*SQRT(252) -> 0.11455636 | E10: =STDEV(Ret_data!C262:C521)*SQRT(252) -> #REF!
B11: 2024 | C11: =STDEV(Ret_data!B522:B783)*SQRT(252) -> #REF! | D11: =STDEV(Ret_data!D522:D783)*SQRT(252) -> 0.092035658 | E11: =STDEV(Ret_data!C522:C783)*SQRT(252) -> #REF!
A13: FROM FAME
D14: Company | E14: Competitor
B15: Beta (3Y) | D15: 0.83 | E15: 0.81
B16: PE ratio (TTM) | C16: 2022 | D16: 29.87 | E16: 13.30
C17: 2023 | D17: 23.22 | E17: 8.01
C18: 2024 | D18: 18.77 | E18: 15.31

Sheet Fin_calc
A1: THIS IS YOUR SPACE TO CALCULATE THE RATIOS, PERFORM FINANCIAL ANALYSIS ON THE INCOME STATEMENT AND THE SoFP, AND CREATE THE CHARTS/TABLES FOR THE REPORT PAGE.
A3: Profitability Ratios: Profit margin (%) | E3: Efficiency Ratios: Net Assets Turnover (x) | I3: Gearing ratios: Gearing (%) | M3: Equity Ratios: Return on Shareholder Funds (%) | Q3: Liquidity ratios: Current Ratio
B4: Company | C4: Competitor/Industry Average | F4: Company | G4: Competitor/Industry Average | J4: Company | K4: Competitor/Industry Average | N4: Company | O4: Competitor/Industry Average | R4: Company | S4: Competitor/Industry Average
A5: 2022 | B5: =('IS data'!D15/'IS data'!D5) -> 0.052634136 | C5: =('IS data'!L15/'IS data'!L5) -> 0.1383693 | E5: 2022 | F5: =('IS data'!D5/'SoFP data'!D57) -> 3.1550295 | G5: =('IS data'!L5/'SoFP data'!L57) -> 0.51193282 | I5: 2022 | J5: =ABS('SoFP data'!D75) / (ABS('SoFP data'!D75) + ABS('SoFP data'!D90)) -> 0.32957747 | K5: =ABS('SoFP data'!L75) / (ABS('SoFP data'!L75) + ABS('SoFP data'!L90)) -> 0.62443528 | M5: 2022 | N5: =('IS data'!D31/'SoFP data'!D90) -> 0.22964105 | O5: =('IS data'!L31/'SoFP data'!L90) -> 0.12833421 | Q5: 2022 | R5: ='SoFP data'!D33/ABS('SoFP data'!D51) -> 1.5220888 | S5: ='SoFP data'!L33/ABS('SoFP data'!L51) -> 0.98474464
A6: 2023 | B6: =('IS data'!C15/'IS data'!C5) -> 3.4702403e-05 | C6: =('IS data'!K15/'IS data'!K5) -> 0.12663798 | E6: 2023 | F6: =('IS data'!C5 / 'SoFP data'!C57) -> 7687.0949 | G6: =('IS data'!K5/'SoFP data'!K57) -> 0.48822002 | I6: 2023 | J6: =ABS('SoFP data'!C75) / (ABS('SoFP data'!C75) + ABS('SoFP data'!C90)) -> 0.28349105 | K6: =ABS('SoFP data'!K75) / (ABS('SoFP data'!K75) + ABS('SoFP data'!K90)) -> 0.65736544 | M6: 2023 | N6: =('IS data'!C31/'SoFP data'!C90) -> 0.37039895 | O6: =('IS data'!K31/'SoFP data'!K90) -> 0.11912636 | Q6: 2023 | R6: ='SoFP data'!C33/ABS('SoFP data'!C51) -> 1.1991327 | S6: ='SoFP data'!K33/ABS('SoFP data'!K51) -> 0.91002694
A7: 2024 | B7: =('IS data'!B15/'IS data'!B5) -> 5.2105529e-05 | C7: =('IS data'!J15/'IS data'!J5) -> 0.10645766 | E7: 2024 | F7: =('IS data'!B5 / 'SoFP data'!B57) -> 4924.6402 | G7: =('IS data'!J5/'SoFP data'!J57) -> 0.49609981 | I7: 2024 | J7: =ABS('SoFP data'!B75) / (ABS('SoFP data'!B75) + ABS('SoFP data'!B90)) -> 0.43818029 | K7: =ABS('SoFP data'!J75) / (ABS('SoFP data'!J75) + ABS('SoFP data'!J90)) -> 0.70139071 | M7: 2024 | N7: =('IS data'!B31/'SoFP data'!B90) -> 0.43191578 | O7: =('IS data'!J31/'SoFP data'!J90) -> 0.094743569 | Q7: 2024 | R7: ='SoFP data'!B33/ABS('SoFP data'!B51) -> 1.7745782 | S7: ='SoFP data'!J33/ABS('SoFP data'!J51) -> 0.88806274

Sheet All stock Data
C1: XLON:FSTA | D1: XLON:GFRD | E1: XLON:HFD | F1: XLON:BOOT | G1: XLON:HSW | H1: XLON:KMR | I1: XLON:MARS | J1: XLON:MOTR | K1: XLON:NXR | L1: XLON:OTB | M1: XLON:OXB | N1: XLON:MAB | O1: XLON:YNGA | P1: XLON:MGNS | Q1: XLON:KIE | R1: XLON:COST | S1: XLON:VTU | T1: XLON:VCP | U1: XLON:JHD | V1: XLON:WJG | W1: XLON:RIO | X1: XLON:AAL | Y1: XLON:CAML | Z1: XLON:JDW | AA1: XLON:CKN | AB1: XLON:BAB | AC1: XLON:OCN | AD1: XLON:FERG | AE1: XLON:JET2 | AF1: XLON:HIK | AG1: XLON:SNG
A2: Date | C2: Close | D2: Close | E2: Close | F2: Close | G2: Close | H2: Close | I2: Close | J2: Close | K2: Close | L2: Close | M2: Close | N2: Close | O2: Close | P2: Close | Q2: Close | R2: Close | S2: Close | T2: Close | U2: Close | V2: Close | W2: Close | X2: Close | Y2: Close | Z2: Close | AA2: Close | AB2: Close | AC2: Close | AD2: Close | AE2: Close | AF2: Close | AG2: Close
A3: 43832 | B3: =VLOOKUP(A3,'FTSE All-Share Historical '!A:B,2,FALSE) -> 4285.97 | C3: 960 | D3: 886 | E3: 170.3 | F3: 330 | G3: 128.8 | H3: 239 | I3: 129.6 | J3: 289 | K3: 278 | L3: 489.2 | M3: 673 | N3: 456.5 | O3: 1627.5 | P3: 1620 | Q3: 94.75 | R3: 165 | S3: 38.3 | T3: 432.5 | U3: 270.5 | V3: 244 | W3: 4526.5 | X3: 2193.1259 | Y3: 223 | Z3: 1678 | AA3: 3030 | AB3: 631 | AC3: 990 | AD3: 6978 | AE3: 1723 | AF3: 1985 | AG3: 4.2439
A4: 43833 | B4: =VLOOKUP(A4,'FTSE All-Share Historical '!A:B,2,FALSE) -> 4290.29 | C4: 940 | D4: 165.86 | E4: 167.8 | F4: 322 | G4: 128.8 | H4: 239 | I4: 128.2 | J4: 294 | K4: 276 | L4: 490 | M4: 670 | N4: 456.5 | O4: 1650 | P4: 1610 | Q4: 91.7 | R4: 166.6 | S4: 37 | T4: 434 | U4: 266 | V4: 246 | W4: 4504 | X4: 2177.6884 | Y4: 221 | Z4: 1676 | AA4: 2995 | AB4: 613 | AC4: 990 | AD4: 7006 | AE4: 1675 | AF4: 1986 | AG4: 4.6051
A5: 43836 | B5: =VLOOKUP(A5,'FTSE All-Share Historical '!A:B,2,FALSE) -> 4260.71 | C5: 950 | D5: 163 | E5: 162.3 | F5: 330 | G5: 127.8 | H5: 241 | I5: 125.7 | J5: 290 | K5: 280 | L5: 478 | M5: 675 | N5: 443 | O5: 1660 | P5: 1580 | Q5: 90.5 | R5: 164.2 | S5: 36.4 | T5: 432.5 | U5: 269 | V5: 244 | W5: 4430 | X5: 2136.3557 | Y5: 216 | Z5: 1644 | AA5: 2935 | AB5: 628.4 | AC5: 995 | AD5: 6906 | AE5: 1674 | AF5: 1912 | AG5: 4.4245
A6: 43837 | B6: =VLOOKUP(A6,'FTSE All-Share Historical '!A:B,2,FALSE) -> 4262.43 | C6: 966 | D6: 136.42 | E6: 159.9 | F6: 330 | G6: 130.4 | H6: 245 | I6: 125 | J6: 288 | K6: 280 | L6: 481.8 | M6: 670 | N6: 439.5 | O6: 1637.5 | P6: 1616 | Q6: 89.5 | R6: 167 | S6: 37.1 | T6: 435 | U6: 273 | V6: 244 | W6: 4440 | X6: 2151.2952 | Y6: 215.5 | Z6: 1626 | AA6: 2955 | AB6: 646.6 | AC6: 995 | AD6: 6948 | AE6: 1670 | AF6: 1882.5 | AG6: 4.3703
A7: 43838 | B7: =VLOOKUP(A7,'FTSE All-Share Historical '!A:B,2,FALSE) -> 4256.79 | C7: 958 | D7: 144.08 | E7: 158 | F7: 320 | G7: 130 | H7: 240.5 | I7: 122.7 | J7: 290 | K7: 280 | L7: 468.4 | M7: 665 | N7: 421.5 | O7: 1605 | P7: 1640 | Q7: 87.05 | R7: 166.6 | S7: 36.9 | T7: 438 | U7: 268 | V7: 242.5 | W7: 4500 | X7: 2144.3234 | Y7: 217 | Z7: 1625 | AA7: 2945 | AB7: 641 | AC7: 990 | AD7: 6980 | AE7: 1675 | AF7: 1874.5 | AG7: 4.6954
A8: 43839 | B8: =VLOOKUP(A8,'FTSE All-Share Historical '!A:B,2,FALSE) -> 4267.27 | C8: 956 | D8: 151.5 | E8: 154.1 | F8: 315 | G8: 133 | H8: 235 | I8: 123.1 | J8: 278 | K8: 283.5 | L8: 461 | M8: 675 | N8: 433 | O8: 1650 | P8: 1652 | Q8: 83.1 | R8: 162.6 | S8: 37.35 | T8: 437.5 | U8: 270 | V8: 242 | W8: 4451 | X8: 2135.3597 | Y8: 224.5 | Z8: 1622 | AA8: 2925 | AB8: 643.2 | AC8: 980 | AD8: 7146 | AE8: 1705 | AF8: 1902 | AG8: 4.6051
A9: 43840 | B9: =VLOOKUP(A9,'FTSE All-Share Historical '!A:B,2,FALSE) -> 4259.91 | C9: 962 | D9: 158.4 | E9: 142 | F9: 313 | G9: 136 | H9: 233 | I9: 121.2 | J9: 277 | K9: 283 | L9: 461 | M9: 690 | N9: 433 | O9: 1630 | P9: 1664 | Q9: 82.5 | R9: 166 | S9: 37.25 | T9: 432 | U9: 270 | V9: 242 | W9: 4488 | X9: 2156.2751 | Y9: 222 | Z9: 1605 | AA9: 2925 | AB9: 636 | AC9: 980 | AD9: 7078 | AE9: 1817 | AF9: 1906.5 | AG9: 4.4606
A10: 43843 | B10: =VLOOKUP(A10,'FTSE All-Share Historical '!A:B,2,FALSE) -> 4278.83 | C10: 978 | D10: 157.7 | E10: 146 | F10: 313 | G10: 144 | H10: 240 | I10: 118.4 | J10: 286 | K10: 289 | L10: 464 | M10: 700 | N10: 420.5 | O10: 1622.5 | P10: 1648 | Q10: 83.8 | R10: 168.6 | S10: 37 | T10: 440 | U10: 278 | V10: 241.5 | W10: 4555 | X10: 2176.6924 | Y10: 228 | Z10: 1600 | AA10: 2925 | AB10: 638.4 | AC10: 975 | AD10: 7166 | AE10: 1806 | AF10: 1928 | AG10: 4.4606
A11: 43844 | B11: =VLOOKUP(A11,'FTSE All-Share Historical '!A:B,2,FALSE) -> 4282.37 | C11: 961 | D11: 158.26 | E11: 146 | F11: 325 | G11: 143.6 | H11: 235 | I11: 120.8 | J11: 295 | K11: 290 | L11: 450.2 | M11: 695 | N11: 425 | O11: 1620 | P11: 1646 | Q11: 81.95 | R11: 170.2 | S11: 36.7 | T11: 440 | U11: 275 | V11: 248 | W11: 4545 | X11: 2163.7448 | Y11: 230 | Z11: 1599 | AA11: 2905 | AB11: 632.6 | AC11: 980 | AD11: 7216 | AE11: 1803 | AF11: 1944.5 | AG11: 4.9121
A12: 43845 | B12: =VLOOKUP(A12,'FTSE All-Share Historical '!A:B,2,FALSE) -> 4290.42 | C12: 970 | D12: 151.86 | E12: 145.5 | F12: 335 | G12: 149.8 | H12: 236 | I12: 122.3 | J12: 294 | K12: 285 | L12: 457 | M12: 700 | N12: 417 | O12: 1610 | P12: 1680 | Q12: 77.5 | R12: 165.2 | S12: 36.1 | T12: 437.5 | U12: 281 | V12: 248.5 | W12: 4523 | X12: 2152.7892 | Y12: 228 | Z12: 1600 | AA12: 2950 | AB12: 618.8 | AC12: 1000 | AD12: 7176 | AE12: 1820 | AF12: 1975 | AG12: 5.0927
A13: 43846 | B13: =VLOOKUP(A13,'FTSE All-Share Historical '!A:B,2,FALSE) -> 4275.36 | C13: 970 | D13: 145.98 | E13: 153.5 | F13: 328 | G13: 149.4 | H13: 235 | I13: 123.4 | J13: 300 | K13: 281 | L13: 455.8 | M13: 671 | N13: 412.5 | O13: 1630 | P13: 1716 | Q13: 78 | R13: 170.4 | S13: 36.8 | T13: 437.5 | U13: 281 | V13: 250 | W13: 4526.5 | X13: 2166.7327 | Y13: 220.5 | Z13: 1600 | AA13: 3010 | AB13: 609.8 | AC13: 1025 | AD13: 7170 | AE13: 1777 | AF13: 1910.5 | AG13: 5.9596
A14: 43847 | B14: =VLOOKUP(A14,'FTSE All-Share Historical '!A:B,2,FALSE) -> 4311.06 | C14: 970 | D14: 142.88 | E14: 152 | F14: 342 | G14: 153.2 | H14: 237 | I14: 121.3 | J14: 304 | K14: 290 | L14: 437 | M14: 679 | N14: 411 | O14: 1625 | P14: 1696 | Q14: 78.4 | R14: 175.6 | S14: 38.15 | T14: 440 | U14: 279 | V14: 255 | W14: 4651 | X14: 2236.4506 | Y14: 224.5 | Z14: 1623 | AA14: 3075 | AB14: 620.2 | AC14: 1025 | AD14: 7176 | AE14: 1792 | AF14: 1955.5 | AG14: 5.779
... A357: 44343 | B357: =VLOOKUP(A357,'FTSE All-Share Historical '!A:B,2,FALSE) -> 4030.8 | C357: 884 | D357: 129.3 | E357: 385.2 | F357: 283 | G357: 100.8 | H357: 441 | I357: 93.7 | J357: 280 | K357: 297 | L357: 419.5 | M357: 1152 | N357: 316.2 | O357: 1630 | P357: 2275 | Q357: 116.6 | R357: 58.6 | S357: 43 | T357: 1010 | U357: 245 | V357: 238.5 | W357: 6074 | X357: 3124.8559 | Y357: 274 | Z357: 1354 | AA357: 3075 | AB357: 305 | AC357: 1065 | AD357: 9624 | AE357: 1345.5 | AF357: 2454 | AG357: 106.0439
A358: 44344 | B358: =VLOOKUP(A358,'FTSE All-Share Historical '!A:B,2,FALSE) -> 4032.98 | C358: 842 | D358: 125.8 | E358: 381.4 | F358: #N/A | G358: 97.2 | H358: 431 | I358: 91.35 | J358: 268 | K358: 305 | L358: 408 | M358: 1140 | N358: 305 | O358: 1610 | P358: 2235 | Q358: 115 | R358: 58.1 | S358: 43.5 | T358: 1005 | U358: 250 | V358: 225 | W358: 6064 | X358: 3122.366 | Y358: 272 | Z358: 1317 | AA358: 3080 | AB358: 299.1 | AC358: 1080 | AD358: 9584 | AE358: 1350 | AF358: 2444 | AG358: 117.7463
A359: 44348 | B359: =VLOOKUP(A359,'FTSE All-Share Historical '!A:B,2,FALSE) -> 4066.34 | C359: 924 | D359: 125.4 | E359: 386.6 | F359: 285 | G359: 97.9 | H359: 449 | I359: 94.7 | J359: 287 | K359: 297 | L359: 421.5 | M359: 1132 | N359: 310.8 | O359: 1600 | P359: 2270 | Q359: 115.2 | R359: 58.8 | S359: 43.9 | T359: 1025 | U359: 249.5 | V359: 226 | W359: 6305 | X359: 3248.3562 | Y359: 277.5 | Z359: 1351 | AA359: 3110 | AB359: 298.7 | AC359: 1070 | AD359: 9632 | AE359: 1360 | AF359: 2435 | AG359: 126.9204
A360: 44349 | B360: =VLOOKUP(A360,'FTSE All-Share Historical '!A:B,2,FALSE) -> 4081.16 | C360: 900 | D360: 126 | E360: 380.8 | F360: 280 | G360: 98 | H360: 441 | I360: 94.7 | J360: 276 | K360: 309 | L360: 427.5 | M360: 1120 | N360: 312.6 | O360: 1590 | P360: 2280 | Q360: 114.8 | R360: 58.6 | S360: 44.7 | T360: 1005 | U360: 248.5 | V360: 222 | W360: 6305 | X360: 3282.2191 | Y360: 284.5 | Z360: 1338 | AA360: 3105 | AB360: 306.9 | AC360: 1070 | AD360: 9660 | AE360: 1357.5 | AF360: 2423 | AG360: 122.8029
A361: 44350 | B361: =VLOOKUP(A361,'FTSE All-Share Historical '!A:B,2,FALSE) -> 4056.42 | C361: 854 | D361: 127.9 | E361: 376.4 | F361: 277 | G361: 96 | H361: 450 | I361: 93 | J361: 279 | K361: 302.5 | L361: 428 | M361: 1128 | N361: 307.2 | O361: 1590 | P361: 2250 | Q361: 113 | R361: 57.1 | S361: 46.3 | T361: 1005 | U361: 251 | V361: 224.5 | W361: 6172 | X361: 3188.1 | Y361: 274.5 | Z361: 1315 | AA361: 3115 | AB361: 305.4 | AC361: 1070 | AD361: 9802 | AE361: 1293 | AF361: 2403 | AG361: 121.1414
A362: 44351 | B362: =VLOOKUP(A362,'FTSE All-Share Historical '!A:B,2,FALSE) -> 4059.61 | C362: 882 | D362: 128.9 | E362: 379 | F362: 280 | G362: 97 | H362: 441 | I362: 94.35 | J362: 281 | K362: 298 | L362: 418 | M362: 1140 | N362: 311.6 | O362: 1590 | P362: 2230 | Q362: 112 | R362: 57.4 | S362: 46 | T362: 1000 | U362: 252 | V362: 217 | W362: 6219 | X362: 3241.3844 | Y362: 280.5 | Z362: 1327 | AA362: 3085 | AB362: 303.1 | AC362: 1065 | AD362: 9824 | AE362: 1303 | AF362: 2409 | AG362: 115.6514
A363: 44354 | B363: =VLOOKUP(A363,'FTSE All-Share Historical '!A:B,2,FALSE) -> 4065.88 | C363: 856 | D363: 126.2 | E363: 389.2 | F363: 277 | G363: 95.8 | H363: 441 | I363: 93.2 | J363: 275 | K363: 307 | L363: 404.5 | M363: 1136 | N363: 314 | O363: 1580 | P363: 2220 | Q363: 113.4 | R363: 59 | S363: 46.5 | T363: 1005 | U363: 252 | V363: 218 | W363: 6141 | X363: 3153 | Y363: 273 | Z363: 1325 | AA363: 3120 | AB363: 308.2 | AC363: 1065 | AD363: 9862 | AE363: 1282.5 | AF363: 2425 | AG363: 112.6897
A364: 44355 | B364: =VLOOKUP(A364,'FTSE All-Share Historical '!A:B,2,FALSE) -> 4073.88 | C364: 888 | D364: 126 | E364: 397.2 | F364: 270 | G364: 96 | H364: 453 | I364: 94.2 | J364: 278 | K364: 306 | L364: 384 | M364: 1148 | N364: 315 | O364: 1600 | P364: 2200 | Q364: 113.2 | R364: 58.9 | S364: 46.2 | T364: 1015 | U364: 253 | V364: 214 | W364: 6192 | X364: 3183 | Y364: 268.5 | Z364: 1329 | AA364: 3095 | AB364: 301 | AC364: 1065 | AD364: 9880 | AE364: 1267.5 | AF364: 2418 | AG364: 104.9604
A365: 44356 | B365: =VLOOKUP(A365,'FTSE All-Share Historical '!A:B,2,FALSE) -> 4062.85 | C365: 850 | D365: 122.8 | E365: 388 | F365: 276 | G365: 97 | H365: 444 | I365: 93.15 | J365: 274.5 | K365: 319 | L365: 374 | M365: 1152 | N365: 311.2 | O365: 1605 | P365: 2185 | Q365: 112 | R365: 57.6 | S365: 46 | T365: 976 | U365: 251 | V365: 214 | W365: 6068 | X365: 3102.5 | Y365: 264 | Z365: 1330 | AA365: 3100 | AB365: 296.6 | AC365: 1065 | AD365: 9726 | AE365: 1290 | AF365: 2446 | AG365: 114.1345
A366: 44357 | B366: =VLOOKUP(A366,'FTSE All-Share Historical '!A:B,2,FALSE) -> 4061.37 | C366: 872 | D366: 125 | E366: 397.2 | F366: 279 | G366: 97.3 | H366: 443 | I366: 91 | J366: 275 | K366: 322 | L366: 379 | M366: 1208 | N366: 303.2 | O366: 1595 | P366: 2170 | Q366: 113.8 | R366: 57.2 | S366: 45.7 | T366: 1005 | U366: 250 | V366: 210 | W366: 6033 | X366: 3099.5 | Y366: 259 | Z366: 1279 | AA366: 3100 | AB366: 299 | AC366: 1065 | AD366: 9576 | AE366: 1271 | AF366: 2445 | AG366: 111.9674
A367: 44358 | B367: =VLOOKUP(A367,'FTSE All-Share Historical '!A:B,2,FALSE) -> 4086.98 | C367: 862 | D367: 125 | E367: 395 | F367: 270 | G367: 96 | H367: 444 | I367: 91.5 | J367: 275 | K367: 328 | L367: 374 | M367: 1246 | N367: 303.2 | O367: 1590 | P367: 2195 | Q367: 114.4 | R367: 57 | S367: 45.4 | T367: 998 | U367: 251 | V367: 211 | W367: 6119 | X367: 3147 | Y367: 265 | Z367: 1288 | AA367: 3100 | AB367: 303 | AC367: 1065 | AD367: 9572 | AE367: 1279 | AF367: 2447 | AG367: 110.7393
A368: 44361 | B368: =VLOOKUP(A368,'FTSE All-Share Historical '!A:B,2,FALSE) -> 4093.25 | C368: 868 | D368: 125 | E368: 394.6 | F368: 266 | G368: 96.7 | H368: 444 | I368: 89.9 | J368: 270 | K368: 330 | L368: 359 | M368: 1288 | N368: 299.4 | O368: 1580 | P368: 2215 | Q368: 117 | R368: 57.7 | S368: 46.2 | T368: 1010 | U368: 256 | V368: 214.5 | W368: 6092 | X368: 3112.5 | Y368: 269.5 | Z368: 1237 | AA368: 3105 | AB368: 299.2 | AC368: 1080 | AD368: 9622 | AE368: 1240 | AF368: 2465 | AG368: 111.3895
A369: 44362 | B369: =VLOOKUP(A369,'FTSE All-Share Historical '!A:B,2,FALSE) -> 4101.74 | C369: 850 | D369: 127.4 | E369: 398.8 | F369: 266 | G369: 98.6 | H369: 452 | I369: 90.3 | J369: 279 | K369: 336 | L369: 348.5 | M369: 1310 | N369: 297.4 | O369: 1600 | P369: 2205 | Q369: 116.4 | R369: 58 | S369: 46.4 | T369: 1030 | U369: 252 | V369: 211 | W369: 6014 | X369: 2999 | Y369: 259 | Z369: 1248 | AA369: 3095 | AB369: 291.1 | AC369: 1110 | AD369: 9818 | AE369: 1232.5 | AF369: 2486 | AG369: 126.3425
A370: 44363 | B370: =VLOOKUP(A370,'FTSE All-Share Historical '!A:B,2,FALSE) -> 4107.15 | C370: 874 | D370: 128 | E370: 405.8 | F370: 266 | G370: 99 | H370: 446 | I370: 91.2 | J370: 275 | K370: 328 | L370: 345 | M370: 1280 | N370: 293 | O370: 1590 | P370: 2220 | Q370: 118.6 | R370: 57.9 | S370: 46.5 | T370: 1020 | U370: 253 | V370: 210 | W370: 6020 | X370: 2963.5 | Y370: 254.5 | Z370: 1225 | AA370: 3140 | AB370: 296.7 | AC370: 1130 | AD370: 9914 | AE370: 1225 | AF370: 2512 | AG370: 126.1258
... A421: 44434 | B421: =VLOOKUP(A421,'FTSE All-Share Historical '!A:B,2,FALSE) -> 4121.23 | C421: 820 | D421: 174.1 | E421: 369 | F421: 275 | G421: 87 | H421: 421 | I421: 85.45 | J421: 337.5 | K421: 287 | L421: 360 | M421: 1450 | N421: 287.2 | O421: 1605 | P421: 2545 | Q421: 130.8 | R421: 61.7 | S421: 52.4 | T421: 1045 | U421: 283 | V421: 236 | W421: 5316 | X421: 2994 | Y421: 233.5 | Z421: 1115 | AA421: 3750 | AB421: 372.8 | AC421: 1030 | AD421: 10230 | AE421: 1174 | AF421: 2525 | AG421: 114.1345
A422: 44435 | B422: =VLOOKUP(A422,'FTSE All-Share Historical '!A:B,2,FALSE) -> 4135.49 | C422: 787 | D422: 169.2 | E422: 367 | F422: #N/A | G422: 84 | H422: 420 | I422: 85.45 | J422: 337 | K422: 295 | L422: 365.5 | M422: 1472 | N422: 289.8 | O422: 1615 | P422: 2580 | Q422: 128.6 | R422: 59.9 | S422: 52.4 | T422: 1045 | U422: 285 | V422: 241 | W422: 5404 | X422: 3084 | Y422: 241.5 | Z422: 1112 | AA422: 3795 | AB422: 369.5 | AC422: 1020 | AD422: 10225 | AE422: 1161.5 | AF422: 2524 | AG422: 111.9674
A423: 44439 | B423: =VLOOKUP(A423,'FTSE All-Share Historical '!A:B,2,FALSE) -> 4123.45 | C423: 774 | D423: 170.1 | E423: 363.6 | F423: 286 | G423: 86.4 | H423: 427 | I423: 86.35 | J423: 338.5 | K423: 298 | L423: 352.5 | M423: 1482 | N423: 294.6 | O423: 1605 | P423: 2570 | Q423: 128.6 | R423: 59 | S423: 54 | T423: 1115 | U423: 287 | V423: 238 | W423: 5382 | X423: 3069 | Y423: 250 | Z423: 1113 | AA423: 3820 | AB423: 363.1 | AC423: 1025 | AD423: 10505 | AE423: 1154 | AF423: 2538 | AG423: 110.3781
A424: 44440 | B424: =VLOOKUP(A424,'FTSE All-Share Historical '!A:B,2,FALSE) -> 4142.37 | C424: 770 | D424: 168.5 | E424: 356.6 | F424: 273 | G424: 86.4 | H424: 425 | I424: 87 | J424: 355 | K424: 302 | L424: 357.5 | M424: 1490 | N424: 295 | O424: 1610 | P424: 2635 | Q424: 127.4 | R424: 61.4 | S424: 54.8 | T424: 1095 | U424: 287 | V424: 237 | W424: 5332 | X424: 3067.5 | Y424: 242 | Z424: 1118 | AA424: 3910 | AB424: 365.4 | AC424: 1030 | AD424: 10565 | AE424: 1193 | AF424: 2560 | AG424: 110.8838
A425: 44441 | B425: =VLOOKUP(A425,'FTSE All-Share Historical '!A:B,2,FALSE) -> 4148.24 | C425: 744 | D425: 171.5 | E425: 355 | F425: 276 | G425: 88.6 | H425: 425 | I425: 85.85 | J425: 345 | K425: 316 | L425: 361 | M425: 1502 | N425: 292.6 | O425: 1630 | P425: 2645 | Q425: 127.8 | R425: 60.4 | S425: 56 | T425: 1050 | U425: 283 | V425: 237 | W425: 5406 | X425: 3074.5 | Y425: 242.5 | Z425: 1120 | AA425: 3900 | AB425: 357.2 | AC425: 1030 | AD425: 10645 | AE425: 1191 | AF425: 2565 | AG425: 111.1727
A426: 44442 | B426: =VLOOKUP(A426,'FTSE All-Share Historical '!A:B,2,FALSE) -> 4135.18 | C426: 726 | D426: 167.9 | E426: 355.8 | F426: 279 | G426: 87.6 | H426: 420 | I426: 84.5 | J426: 337 | K426: 299 | L426: 354 | M426: 1514 | N426: 285.4 | O426: 1620 | P426: 2685 | Q426: 129.8 | R426: 58.6 | S426: 59.6 | T426: 1060 | U426: 278 | V426: 239.5 | W426: 5408 | X426: 3091 | Y426: 237 | Z426: 1097 | AA426: 3935 | AB426: 351.3 | AC426: 1030 | AD426: 10610 | AE426: 1159.5 | AF426: 2572 | AG426: 111.1727
A427: 44445 | B427: =VLOOKUP(A427,'FTSE All-Share Historical '!A:B,2,FALSE) -> 4159.94 | C427: 726 | D427: 169.3 | E427: 351 | F427: 270 | G427: 85 | H427: 420 | I427: 84.35 | J427: 333 | K427: 300 | L427: 353 | M427: 1506 | N427: 285.2 | O427: 1590 | P427: 2610 | Q427: 129.2 | R427: 59.8 | S427: 56.2 | T427: 1050 | U427: 281 | V427: 249 | W427: 5337 | X427: 3078.5 | Y427: 239.5 | Z427: 1099 | AA427: 3965 | AB427: 349.9 | AC427: 1025 | AD427: 10765 | AE427: 1173 | AF427: 2603 | AG427: 110.5226
A428: 44446 | B428: =VLOOKUP(A428,'FTSE All-Share Historical '!A:B,2,FALSE) -> 4137.32 | C428: 730 | D428: 171 | E428: 351.4 | F428: 273 | G428: 87.9 | H428: 425 | I428: 82.25 | J428: 333 | K428: 299 | L428: 347 | M428: 1486 | N428: 283.4 | O428: 1595 | P428: 2570 | Q428: 128 | R428: 60.3 | S428: 55.4 | T428: 1045 | U428: 281.5 | V428: 247 | W428: 5360 | X428: 3096 | Y428: 239 | Z428: 1082 | AA428: 4010 | AB428: 347.2 | AC428: 1025 | AD428: 10700 | AE428: 1150.5 | AF428: 2576 | AG428: 111.245
A429: 44447 | B429: =VLOOKUP(A429,'FTSE All-Share Historical '!A:B,2,FALSE) -> 4104.05 | C429: 730 | D429: 170 | E429: 342.8 | F429: 279 | G429: 86.8 | H429: 425 | I429: 80.4 | J429: 331 | K429: 302 | L429: 338.5 | M429: 1476 | N429: 281 | O429: 1620 | P429: 2560 | Q429: 125 | R429: 58.7 | S429: 54.4 | T429: 1055 | U429: 277 | V429: 241 | W429: 5305 | X429: 3047.5 | Y429: 235 | Z429: 1056 | AA429: 4000 | AB429: 339.8 | AC429: 1025 | AD429: 10555 | AE429: 1135.5 | AF429: 2525 | AG429: 108.5
A430: 44448 | B430: =VLOOKUP(A430,'FTSE All-Share Historical '!A:B,2,FALSE) -> 4068.81 | C430: 750 | D430: 170.3 | E430: 330.4 | F430: 287 | G430: 86.4 | H430: 427 | I430: 81.15 | J430: 331 | K430: 305 | L430: 341 | M430: 1446 | N430: 271.4 | O430: 1620 | P430: 2590 | Q430: 125 | R430: 60.4 | S430: 54.2 | T430: 1040 | U430: 278 | V430: 243 | W430: 5163 | X430: 3028 | Y430: 231 | Z430: 1060 | AA430: 3910 | AB430: 340.5 | AC430: 1025 | AD430: 10575 | AE430: 1102.5 | AF430: 2520 | AG430: 112.8342
A431: 44449 | B431: =VLOOKUP(A431,'FTSE All-Share Historical '!A:B,2,FALSE) -> 4069.07 | C431: 768 | D431: 166.9 | E431: 309 | F431: 288 | G431: 86 | H431: 434 | I431: 80.7 | J431: 335 | K431: 302 | L431: 346 | M431: 1454 | N431: 268 | O431: 1590 | P431: 2580 | Q431: 124 | R431: 60.4 | S431: 54.6 | T431: 1015 | U431: 276.5 | V431: 243 | W431: 5264 | X431: 3071.5 | Y431: 233.5 | Z431: 1056 | AA431: 3870 | AB431: 340.2 | AC431: 1025 | AD431: 10570 | AE431: 1070 | AF431: 2531 | AG431: 126.8482
A432: 44452 | B432: =VLOOKUP(A432,'FTSE All-Share Historical '!A:B,2,FALSE) -> 4088.93 | C432: 740 | D432: 170.3 | E432: 301.8 | F432: 280 | G432: 83.6 | H432: 438 | I432: 82.8 | J432: 336 | K432: 303 | L432: 358 | M432: 1478 | N432: 270.8 | O432: 1590 | P432: 2550 | Q432: 124 | R432: 61.3 | S432: 53.6 | T432: 1020 | U432: 273 | V432: 250 | W432: 5287 | X432: 3093 | Y432: 232.5 | Z432: 1060 | AA432: 3845 | AB432: 355.4 | AC432: 1020 | AD432: 10640 | AE432: 1130.5 | AF432: 2500 | AG432: 125.6924
A433: 44453 | B433: =VLOOKUP(A433,'FTSE All-Share Historical '!A:B,2,FALSE) -> 4069.91 | C433: 734 | D433: 170 | E433: 300 | F433: 278 | G433: 85 | H433: 436 | I433: 80.3 | J433: 343 | K433: 305 | L433: 326.5 | M433: 1460 | N433: 265 | O433: 1550 | P433: 2560 | Q433: 123 | R433: 59.8 | S433: 54.2 | T433: 1010 | U433: 270.5 | V433: 248 | W433: 5179 | X433: 2996.5 | Y433: 232 | Z433: 1046 | AA433: 3815 | AB433: 360.2 | AC433: 1020 | AD433: 10575 | AE433: 1117.5 | AF433: 2485 | AG433: 119.1911
A434: 44454 | B434: =VLOOKUP(A434,'FTSE All-Share Historical '!A:B,2,FALSE) -> 4053.58 | C434: 692 | D434: 171.6 | E434: 295.2 | F434: 275 | G434: 78 | H434: 435 | I434: 78.45 | J434: 338 | K434: 307 | L434: 310 | M434: 1478 | N434: 257.8 | O434: 1525 | P434: 2515 | Q434: 125.2 | R434: 59.8 | S434: 53 | T434: 1015 | U434: 269 | V434: 250 | W434: 5219 | X434: 2953.5 | Y434: 247.5 | Z434: 1005 | AA434: 3745 | AB434: 356.2 | AC434: 1020 | AD434: 10495 | AE434: 1115.5 | AF434: 2449 | AG434: 117.0239
... A505: 44553 | B505: =VLOOKUP(A505,'FTSE All-Share Historical '!A:B,2,FALSE) -> 4216.65 | C505: 710 | D505: 186.7 | E505: 344.4 | F505: 278 | G505: 68.6 | H505: 459 | I505: 74.35 | J505: 325 | K505: 318 | L505: 260 | M505: 1220 | N505: 246.6 | O505: 1545 | P505: 2475 | Q505: 108.4 | R505: 51.6 | S505: 69 | T505: 1200 | U505: 284 | V505: 256 | W505: 4864.5 | X505: 3010.5 | Y505: 246 | Z505: 918 | AA505: 3750 | AB505: 318.7 | AC505: 932.5 | AD505: 13050 | AE505: 1049.5 | AF505: 2186 | AG505: 151.6977
A506: 44554 | B506: =VLOOKUP(A506,'FTSE All-Share Historical '!A:B,2,FALSE) -> 4216.17 | C506: 714 | D506: 182.8 | E506: 341.8 | F506: #N/A | G506: 68.6 | H506: 448 | I506: 74.95 | J506: 322.5 | K506: 313 | L506: 270.5 | M506: 1200 | N506: 246.6 | O506: 1525 | P506: 2465 | Q506: 108.4 | R506: 52.6 | S506: 68.4 | T506: 1190 | U506: 278.5 | V506: 260.5 | W506: 4866.5 | X506: 3040.5 | Y506: 245 | Z506: 929.5 | AA506: 3750 | AB506: 318.4 | AC506: 932.5 | AD506: 13100 | AE506: 1042.5 | AF506: 2189 | AG506: 150.9753
A507: 44559 | B507: =VLOOKUP(A507,'FTSE All-Share Historical '!A:B,2,FALSE) -> 4246.9 | C507: 696 | D507: 183.9 | E507: 347.6 | F507: 280 | G507: 68.5 | H507: 459 | I507: 74.45 | J507: 327 | K507: 310 | L507: 274.5 | M507: 1202 | N507: 247.8 | O507: 1535 | P507: 2505 | Q507: 110.8 | R507: 51 | S507: 67.4 | T507: 1165 | U507: 285 | V507: 264 | W507: 4846 | X507: 3028 | Y507: 250 | Z507: 933 | AA507: 3840 | AB507: 324.5 | AC507: 932.5 | AD507: 13275 | AE507: 1071.5 | AF507: 2228 | AG507: 145.9187
A508: 44560 | B508: =VLOOKUP(A508,'FTSE All-Share Historical '!A:B,2,FALSE) -> 4239.25 | C508: 682 | D508: 187.2 | E508: 345 | F508: 284 | G508: 69.2 | H508: 453 | I508: 75.75 | J508: 337.5 | K508: 315 | L508: 275.5 | M508: 1198 | N508: 250.6 | O508: 1535 | P508: 2500 | Q508: 110 | R508: 53 | S508: 68 | T508: 1200 | U508: 288 | V508: 263.5 | W508: 4900.5 | X508: 3019.5 | Y508: 250.5 | Z508: 944 | AA508: 3855 | AB508: 319 | AC508: 932.5 | AD508: 13220 | AE508: 1061 | AF508: 2220 | AG508: 149.5306
A509: 44561 | B509: =VLOOKUP(A509,'FTSE All-Share Historical '!A:B,2,FALSE) -> 4228.67 | C509: 714 | D509: 179.8 | E509: 345.4 | F509: #N/A | G509: 68.5 | H509: 464 | I509: 77 | J509: 350 | K509: 313 | L509: 285 | M509: 1230 | N509: 256 | O509: 1560 | P509: 2520 | Q509: 110 | R509: 53.4 | S509: 68.8 | T509: 1200 | U509: 287 | V509: 261.5 | W509: 4892 | X509: 3016 | Y509: 259 | Z509: 961 | AA509: 3880 | AB509: 318.6 | AC509: 932.5 | AD509: 13105 | AE509: 1115 | AF509: 2219 | AG509: 150.253
A510: 44565 | B510: =VLOOKUP(A510,'FTSE All-Share Historical '!A:B,2,FALSE) -> 4298.76 | C510: 754 | D510: 177.9 | E510: 358.6 | F510: 281 | G510: 71.7 | H510: 465 | I510: 78 | J510: 335 | K510: 321 | L510: 296.5 | M510: 1210 | N510: 263.6 | O510: 1660 | P510: 2530 | Q510: 109.8 | R510: 54 | S510: 73 | T510: 1200 | U510: 281 | V510: 267 | W510: 4938.5 | X510: 3096.5 | Y510: 255 | Z510: 964.5 | AA510: 3965 | AB510: 328.6 | AC510: 935 | AD510: 13305 | AE510: 1181 | AF510: 2189 | AG510: 144.474
A511: 44566 | B511: =VLOOKUP(A511,'FTSE All-Share Historical '!A:B,2,FALSE) -> 4300.35 | C511: 742 | D511: 181.2 | E511: 359 | F511: 279 | G511: 71.2 | H511: 488 | I511: 78.5 | J511: 324 | K511: 325 | L511: 300.5 | M511: 1202 | N511: 259.8 | O511: 1610 | P511: 2490 | Q511: 111 | R511: 54 | S511: 72 | T511: 1210 | U511: 282 | V511: 269.5 | W511: 5035 | X511: 3182 | Y511: 251 | Z511: 973 | AA511: 3870 | AB511: 327.1 | AC511: 935 | AD511: 13290 | AE511: 1185 | AF511: 2191 | AG511: 138.0449
A512: 44567 | B512: =VLOOKUP(A512,'FTSE All-Share Historical '!A:B,2,FALSE) -> 4257.77 | C512: 722 | D512: 178.5 | E512: 357.4 | F512: 275 | G512: 70 | H512: 475 | I512: 78.85 | J512: 334 | K512: 322 | L512: 290 | M512: 1152 | N512: 258.6 | O512: 1590 | P512: 2470 | Q512: 110.4 | R512: 53.1 | S512: 69.2 | T512: 1190 | U512: 284 | V512: 269.5 | W512: 5078 | X512: 3164 | Y512: 232 | Z512: 970.5 | AA512: 3820 | AB512: 341.3 | AC512: 935 | AD512: 12965 | AE512: 1199.5 | AF512: 2125 | AG512: 145.1964
A513: 44568 | B513: =VLOOKUP(A513,'FTSE All-Share Historical '!A:B,2,FALSE) -> 4272.27 | C513: 750 | D513: 176.7 | E513: 359.4 | F513: 278 | G513: 69 | H513: 470 | I513: 78.5 | J513: 331 | K513: 325 | L513: 293.5 | M513: 1136 | N513: 257.6 | O513: 1565 | P513: 2455 | Q513: 108.8 | R513: 53.2 | S513: 68.2 | T513: 1195 | U513: 280 | V513: 263.5 | W513: 5212 | X513: 3257 | Y513: 226.5 | Z513: 961 | AA513: 3975 | AB513: 341.3 | AC513: 935 | AD513: 12840 | AE513: 1237.5 | AF513: 2134 | AG513: 143.7516
A514: 44571 | B514: =VLOOKUP(A514,'FTSE All-Share Historical '!A:B,2,FALSE) -> 4242.3 | C514: 730 | D514: 173 | E514: 356.2 | F514: 275 | G514: 71.2 | H514: 480 | I514: 78 | J514: 334 | K514: 320 | L514: 297 | M514: 1100 | N514: 263 | O514: 1600 | P514: 2365 | Q514: 105.4 | R514: 56 | S514: 70.4 | T514: 1190 | U514: 275 | V514: 256 | W514: 5202 | X514: 3242 | Y514: 228 | Z514: 969 | AA514: 3830 | AB514: 346.4 | AC514: 935 | AD514: 12355 | AE514: 1264 | AF514: 2103 | AG514: 144.474
A515: 44572 | B515: =VLOOKUP(A515,'FTSE All-Share Historical '!A:B,2,FALSE) -> 4264.93 | C515: 740 | D515: 175 | E515: 360 | F515: 285 | G515: 69.2 | H515: 476 | I515: 79.6 | J515: 327.5 | K515: 314 | L515: 293 | M515: 1092 | N515: 263.4 | O515: 1565 | P515: 2325 | Q515: 105.4 | R515: 52.6 | S515: 70.8 | T515: 1175 | U515: 283 | V515: 259.5 | W515: 5301 | X515: 3239 | Y515: 223 | Z515: 958.5 | AA515: 3780 | AB515: 344.4 | AC515: 935 | AD515: 12450 | AE515: 1250.5 | AF515: 2098 | AG515: 138.984
A516: 44573 | B516: =VLOOKUP(A516,'FTSE All-Share Historical '!A:B,2,FALSE) -> 4294.04 | C516: 738 | D516: 175 | E516: 362 | F516: 285 | G516: 70 | H516: 470 | I516: 80 | J516: 318 | K516: 316 | L516: 293 | M516: 1062 | N516: 257.6 | O516: 1600 | P516: 2310 | Q516: 108 | R516: 53.6 | S516: 72.4 | T516: 1200 | U516: 290 | V516: 257.5 | W516: 5452 | X516: 3364.5 | Y516: 237.5 | Z516: 917.5 | AA516: 3810 | AB516: 331.7 | AC516: 935 | AD516: 12715 | AE516: 1249 | AF516: 2080 | AG516: 139.4896
A517: 44574 | B517: =VLOOKUP(A517,'FTSE All-Share Historical '!A:B,2,FALSE) -> 4296.99 | C517: 726 | D517: 175 | E517: 364 | F517: 283 | G517: 70 | H517: 453 | I517: 82.65 | J517: 322 | K517: 324 | L517: 295.5 | M517: 1026 | N517: 260 | O517: 1540 | P517: 2370 | Q517: 107.2 | R517: 53 | S517: 72 | T517: 1200 | U517: 289 | V517: 263 | W517: 5463 | X517: 3355 | Y517: 235 | Z517: 927 | AA517: 3860 | AB517: 339.2 | AC517: 935 | AD517: 12800 | AE517: 1273 | AF517: 2061 | AG517: 139.6341
A518: 44575 | B518: =VLOOKUP(A518,'FTSE All-Share Historical '!A:B,2,FALSE) -> 4280.34 | C518: 718 | D518: 174.8 | E518: 357 | F518: 279.5 | G518: 75 | H518: 459 | I518: 83.25 | J518: 308 | K518: 322 | L518: 297 | M518: 1016 | N518: 262 | O518: 1565 | P518: 2340 | Q518: 106.4 | R518: 52.6 | S518: 74.8 | T518: 1200 | U518: 298 | V518: 263.5 | W518: 5392 | X518: 3306 | Y518: 227 | Z518: 925.5 | AA518: 3800 | AB518: 342.8 | AC518: 935 | AD518: 12455 | AE518: 1257.5 | AF518: 2056 | AG518: 137.6837
A519: 44578 | B519: =VLOOKUP(A519,'FTSE All-Share Historical '!A:B,2,FALSE) -> 4316.64 | C519: 742 | D519: 176 | E519: 358 | F519: 293 | G519: 80.6 | H519: 458 | I519: 81.95 | J519: 317 | K519: 325 | L519: 292.5 | M519: 994 | N519: 264 | O519: 1540 | P519: 2330 | Q519: 106.6 | R519: 51 | S519: 75 | T519: 1175 | U519: 290 | V519: 264.5 | W519: 5393 | X519: 3371.5 | Y519: 230 | Z519: 921 | AA519: 3840 | AB519: 345.1 | AC519: 935 | AD519: 12530 | AE519: 1267 | AF519: 2069 | AG519: 140.8621
A520: 44579 | B520: =VLOOKUP(A520,'FTSE All-Share Historical '!A:B,2,FALSE) -> 4287.22 | C520: 740 | D520: 178.8 | E520: 346 | F520: 287 | G520: 77.4 | H520: 450 | I520: 82.5 | J520: 309 | K520: 321 | L520: 285.5 | M520: 975 | N520: 264.4 | O520: 1540 | P520: 2310 | Q520: 109.6 | R520: 50 | S520: 71.6 | T520: 1150 | U520: 290 | V520: 267 | W520: 5443 | X520: 3376 | Y520: 229.5 | Z520: 903.5 | AA520: 3825 | AB520: 343.6 | AC520: 935 | AD520: 12125 | AE520: 1247 | AF520: 2029 | AG520: 150.9753
A521: 44580 | B521: =VLOOKUP(A521,'FTSE All-Share Historical '!A:B,2,FALSE) -> 4299.63 | C521: 712 | D521: 176.7 | E521: 347 | F521: 295 | G521: 75.5 | H521: 450 | I521: 83.65 | J521: 309 | K521: 320 | L521: 288.5 | M521: 973 | N521: 261 | O521: 1575 | P521: 2310 | Q521: 108.6 | R521: 48.3 | S521: 68.6 | T521: 1075 | U521: 288.5 | V521: 270 | W521: 5654 | X521: 3517.5 | Y521: 237 | Z521: 919.5 | AA521: 3715 | AB521: 344.2 | AC521: 935 | AD521: 11905 | AE521: 1233 | AF521: 2020 | AG521: 148.2303
... A590: 44679 | B590: =VLOOKUP(A590,'FTSE All-Share Historical '!A:B,2,FALSE) -> 4197.13 | C590: 596 | D590: 175 | E590: 224.8 | F590: 324 | G590: 84 | H590: 491 | I590: 76.05 | J590: 248 | K590: 243 | L590: 222 | M590: 545 | N590: 225.8 | O590: 1440 | P590: 2190 | Q590: 77.2 | R590: 40 | S590: 50.8 | T590: 610 | U590: 240 | V590: 248 | W590: 5628 | X590: 3453.5 | Y590: 270 | Z590: 730 | AA590: 3700 | AB590: 304.6 | AC590: 975 | AD590: 10080 | AE590: 1237.5 | AF590: 2029 | AG590: 17.1491
A591: 44680 | B591: =VLOOKUP(A591,'FTSE All-Share Historical '!A:B,2,FALSE) -> 4216.64 | C591: 596 | D591: 175 | E591: 226.4 | F591: #N/A | G591: 84.6 | H591: 472.5 | I591: 75.05 | J591: 242 | K591: 240 | L591: 230 | M591: 570 | N591: 228 | O591: 1386 | P591: 2175 | Q591: 79.3 | R591: 40 | S591: 51.8 | T591: 640 | U591: 248 | V591: 247.5 | W591: 5706 | X591: 3586 | Y591: 268 | Z591: 735.5 | AA591: 3690 | AB591: 306.4 | AC591: 965 | AD591: 10140 | AE591: 1240.5 | AF591: 1883.5 | AG591: 19.2295
A592: 44684 | B592: =VLOOKUP(A592,'FTSE All-Share Historical '!A:B,2,FALSE) -> 4218.6 | C592: 602 | D592: 175.6 | E592: 226 | F592: 323 | G592: 84.4 | H592: 487 | I592: 73.1 | J592: 244 | K592: 232 | L592: 218 | M592: 525 | N592: 227.8 | O592: 1416 | P592: 2125 | Q592: 78.5 | R592: 42.35 | S592: 52.7 | T592: 660 | U592: 240 | V592: 245.5 | W592: 5645 | X592: 3580 | Y592: 278 | Z592: 741 | AA592: 3660 | AB592: 313.2 | AC592: 995 | AD592: 9938 | AE592: 1236 | AF592: 1890 | AG592: 17.6258
A593: 44685 | B593: =VLOOKUP(A593,'FTSE All-Share Historical '!A:B,2,FALSE) -> 4177.02 | C593: 608 | D593: 171 | E593: 222.8 | F593: 321 | G593: 83.6 | H593: 493 | I593: 71.45 | J593: 254 | K593: 226 | L593: 221 | M593: 521 | N593: 228.2 | O593: 1394 | P593: 2080 | Q593: 77.6 | R593: 42 | S593: 51 | T593: 690 | U593: 240 | V593: 242 | W593: 5492 | X593: 3507.5 | Y593: 269 | Z593: 730 | AA593: 3650 | AB593: 312.4 | AC593: 990 | AD593: 9758 | AE593: 1183 | AF593: 1852.5 | AG593: 17.8859
A594: 44686 | B594: =VLOOKUP(A594,'FTSE All-Share Historical '!A:B,2,FALSE) -> 4177.55 | C594: 608 | D594: 170 | E594: 221.2 | F594: 316 | G594: 84.7 | H594: 479.5 | I594: 69.1 | J594: 244 | K594: 228 | L594: 224.5 | M594: 515 | N594: 214.2 | O594: 1394 | P594: 2030 | Q594: 78 | R594: 42 | S594: 50.1 | T594: 600 | U594: 236 | V594: 242.5 | W594: 5481 | X594: 3521 | Y594: 255 | Z594: 718 | AA594: 3555 | AB594: 304.8 | AC594: 1000 | AD594: 9764 | AE594: 1169.5 | AF594: 1685.5 | AG594: 18.4638
A595: 44687 | B595: =VLOOKUP(A595,'FTSE All-Share Historical '!A:B,2,FALSE) -> 4114.56 | C595: 584 | D595: 169 | E595: 221.4 | F595: 315 | G595: 82.7 | H595: 476 | I595: 67.65 | J595: 245 | K595: 226 | L595: 219 | M595: 497.5 | N595: 210 | O595: 1400 | P595: 2030 | Q595: 76.5 | R595: 42.4 | S595: 49 | T595: 552 | U595: 222 | V595: 234.5 | W595: 5440 | X595: 3488.5 | Y595: 255 | Z595: 718.5 | AA595: 3545 | AB595: 306 | AC595: 990 | AD595: 9332 | AE595: 1123 | AF595: 1735 | AG595: 19.1428
A596: 44690 | B596: =VLOOKUP(A596,'FTSE All-Share Historical '!A:B,2,FALSE) -> 4017.43 | C596: 601 | D596: 167 | E596: 223.8 | F596: 315 | G596: 82.8 | H596: 463.5 | I596: 64.65 | J596: 238 | K596: 218 | L596: 208 | M596: 485 | N596: 209.4 | O596: 1352 | P596: 1960 | Q596: 74.5 | R596: 40 | S596: 47 | T596: 588 | U596: 216 | V596: 232.5 | W596: 5188 | X596: 3300 | Y596: 233 | Z596: 705 | AA596: 3400 | AB596: 304.8 | AC596: 985 | AD596: 9110 | AE596: 1071.5 | AF596: 1697 | AG596: 17.727
A597: 44691 | B597: =VLOOKUP(A597,'FTSE All-Share Historical '!A:B,2,FALSE) -> 4032.49 | C597: 584 | D597: 167 | E597: 223.8 | F597: 332 | G597: 81 | H597: 457 | I597: 63.45 | J597: 240 | K597: 222 | L597: 210.5 | M597: 485 | N597: 208 | O597: 1360 | P597: 1958 | Q597: 74.5 | R597: 39.55 | S597: 48 | T597: 600 | U597: 222 | V597: 225 | W597: 5163 | X597: 3286 | Y597: 228 | Z597: 700 | AA597: 3385 | AB597: 301.4 | AC597: 1020 | AD597: 9174 | AE597: 1074 | AF597: 1741 | AG597: 17.6981
A598: 44692 | B598: =VLOOKUP(A598,'FTSE All-Share Historical '!A:B,2,FALSE) -> 4090.08 | C598: 590 | D598: 170 | E598: 226 | F598: 320 | G598: 84.9 | H598: 457 | I598: 61.85 | J598: 241 | K598: 230 | L598: 218.5 | M598: 486 | N598: 205.8 | O598: 1350 | P598: 1974 | Q598: 76.1 | R598: 39.5 | S598: 52.2 | T598: 552 | U598: 222 | V598: 225.5 | W598: 5357 | X598: 3397.5 | Y598: 235.5 | Z598: 721 | AA598: 3370 | AB598: 307.6 | AC598: 1020 | AD598: 9402 | AE598: 1112.5 | AF598: 1729.5 | AG598: 17.8714
A599: 44693 | B599: =VLOOKUP(A599,'FTSE All-Share Historical '!A:B,2,FALSE) -> 4030.88 | C599: 582 | D599: 170.8 | E599: 227.8 | F599: 325 | G599: 83.8 | H599: 445 | I599: 60.35 | J599: 237 | K599: 220 | L599: 214.5 | M599: 473.5 | N599: 204.6 | O599: 1330 | P599: 1936 | Q599: 75.3 | R599: 39.5 | S599: 48.6 | T599: 554 | U599: 220 | V599: 224 | W599: 5203 | X599: 3242.5 | Y599: 228.5 | Z599: 705 | AA599: 3225 | AB599: 304.8 | AC599: 975 | AD599: 9634 | AE599: 1112.5 | AF599: 1697 | AG599: 16.8601
A600: 44694 | B600: =VLOOKUP(A600,'FTSE All-Share Historical '!A:B,2,FALSE) -> 4132.07 | C600: 588 | D600: 172.4 | E600: 227.8 | F600: 325 | G600: 87.9 | H600: 441 | I600: 63 | J600: 238.5 | K600: 240 | L600: 217.5 | M600: 500 | N600: 215.8 | O600: 1340 | P600: 2005 | Q600: 76.7 | R600: 39 | S600: 51.8 | T600: 570 | U600: 226 | V600: 230.5 | W600: 5320 | X600: 3304.5 | Y600: 234.5 | Z600: 730.5 | AA600: 3300 | AB600: 310.4 | AC600: 1010 | AD600: 9874 | AE600: 1138 | AF600: 1724 | AG600: 19.2873
A601: 44697 | B601: =VLOOKUP(A601,'FTSE All-Share Historical '!A:B,2,FALSE) -> 4154.12 | C601: 574 | D601: 175.2 | E601: 223 | F601: 316 | G601: 86.6 | H601: 447.5 | I601: 62.5 | J601: 239 | K601: 244 | L601: 219 | M601: 503 | N601: 212 | O601: 1338 | P601: 1956 | Q601: 75.6 | R601: 39 | S601: 54.3 | T601: 596 | U601: 226 | V601: 231 | W601: 5339 | X601: 3348.5 | Y601: 236 | Z601: 730 | AA601: 3250 | AB601: 311 | AC601: 1010 | AD601: 9696 | AE601: 1131.5 | AF601: 1711 | AG601: 25.283
A602: 44698 | B602: =VLOOKUP(A602,'FTSE All-Share Historical '!A:B,2,FALSE) -> 4183.88 | C602: 574 | D602: 175 | E602: 220.4 | F602: 326 | G602: 87.1 | H602: 460 | I602: 62.5 | J602: 238 | K602: 242 | L602: 220 | M602: 507 | N602: 214 | O602: 1338 | P602: 1968 | Q602: 75.4 | R602: 39.65 | S602: 54.6 | T602: 600 | U602: 230 | V602: 237 | W602: 5470 | X602: 3498.5 | Y602: 233 | Z602: 736.5 | AA602: 3280 | AB602: 311 | AC602: 995 | AD602: 9936 | AE602: 1139 | AF602: 1726.5 | AG602: 22.4079
A603: 44699 | B603: =VLOOKUP(A603,'FTSE All-Share Historical '!A:B,2,FALSE) -> 4142.34 | C603: 586 | D603: 175 | E603: 217.6 | F603: 324 | G603: 89 | H603: 459 | I603: 58 | J603: 238 | K603: 250 | L603: 228.5 | M603: 487.5 | N603: 211 | O603: 1332 | P603: 1940 | Q603: 76 | R603: 40.85 | S603: 54.8 | T603: 660 | U603: 223 | V603: 228 | W603: 5372 | X603: 3413 | Y603: 232.5 | Z603: 706.5 | AA603: 3200 | AB603: 316.8 | AC603: 985 | AD603: 9604 | AE603: 1141 | AF603: 1678.5 | AG603: 22.1045
... A612: 44712 | B612: =VLOOKUP(A612,'FTSE All-Share Historical '!A:B,2,FALSE) -> 4237.22 | C612: 552 | D612: 175 | E612: 224.2 | F612: 345 | G612: 100 | H612: 495 | I612: 54.55 | J612: 230 | K612: 237 | L612: 202.5 | M612: 511 | N612: 207.6 | O612: 1300 | P612: 2080 | Q612: 78.5 | R612: 39 | S612: 58.6 | T612: 514 | U612: 229 | V612: 232 | W612: 5750 | X612: 3887 | Y612: 258 | Z612: 746.5 | AA612: 3100 | AB612: 337.6 | AC612: 965 | AD612: 9532 | AE612: 1168 | AF612: 1698.5 | AG612: 18.7816
A613: 44713 | B613: =VLOOKUP(A613,'FTSE All-Share Historical '!A:B,2,FALSE) -> 4197.38 | C613: 564 | D613: 175 | E613: 223.6 | F613: #N/A | G613: 104.4 | H613: 484.5 | I613: 54.95 | J613: 232 | K613: 238 | L613: 196.8 | M613: 490.5 | N613: 208 | O613: 1290 | P613: 2080 | Q613: 76.8 | R613: 39.4 | S613: 59.1 | T613: 556 | U613: 232 | V613: 232 | W613: 5758 | X613: 3850 | Y613: 257.5 | Z613: 739 | AA613: 3140 | AB613: 350 | AC613: 967.5 | AD613: 9312 | AE613: 1130 | AF613: 1673 | AG613: 19.0561
A614: 44718 | B614: =VLOOKUP(A614,'FTSE All-Share Historical '!A:B,2,FALSE) -> 4240.32 | C614: 568 | D614: 175 | E614: 224.6 | F614: 336 | G614: 103 | H614: 486 | I614: 55.2 | J614: 234 | K614: 245 | L614: 200.5 | M614: 499 | N614: 206 | O614: 1300 | P614: 2100 | Q614: 78.5 | R614: 39.975 | S614: 56.4 | T614: 548 | U614: 231 | V614: 228.5 | W614: 5956 | X614: 3966.5 | Y614: 264 | Z614: 743 | AA614: 3205 | AB614: 358.8 | AC614: 980 | AD614: 9580 | AE614: 1130.5 | AF614: 1675 | AG614: 18.8105
A615: 44719 | B615: =VLOOKUP(A615,'FTSE All-Share Historical '!A:B,2,FALSE) -> 4232.51 | C615: 564 | D615: 176 | E615: 219 | F615: 329 | G615: 104 | H615: 486 | I615: 56.2 | J615: 232 | K615: 245 | L615: 198.2 | M615: 502 | N615: 203.8 | O615: 1284 | P615: 2100 | Q615: 78.1 | R615: 39.25 | S615: 57.6 | T615: 550 | U615: 230 | V615: 231.5 | W615: 6091 | X615: 4017.5 | Y615: 263 | Z615: 750 | AA615: 3145 | AB615: 362.4 | AC615: 962.5 | AD615: 9494 | AE615: 1102.5 | AF615: 1661.5 | AG615: 19.3884
A616: 44720 | B616: =VLOOKUP(A616,'FTSE All-Share Historical '!A:B,2,FALSE) -> 4226.89 | C616: 570 | D616: 180.4 | E616: 220 | F616: 330 | G616: 106.4 | H616: 487.5 | I616: 58 | J616: 219 | K616: 240 | L616: 197.6 | M616: 514 | N616: 208.4 | O616: 1270 | P616: 2095 | Q616: 77.4 | R616: 39.2 | S616: 58.2 | T616: 530 | U616: 225 | V616: 230 | W616: 6065 | X616: 4007 | Y616: 263 | Z616: 759 | AA616: 3200 | AB616: 363 | AC616: 960 | AD616: 9500 | AE616: 1078.5 | AF616: 1646.5 | AG616: 19.504
A617: 44721 | B617: =VLOOKUP(A617,'FTSE All-Share Historical '!A:B,2,FALSE) -> 4164.27 | C617: 570 | D617: 185.2 | E617: 214 | F617: 324 | G617: 103 | H617: 488 | I617: 58.8 | J617: 226.5 | K617: 249 | L617: 199 | M617: 509 | N617: 207.6 | O617: 1264 | P617: 2065 | Q617: 75.9 | R617: 41 | S617: 58 | T617: 489 | U617: 234 | V617: 228 | W617: 5900 | X617: 3904.5 | Y617: 263 | Z617: 763.5 | AA617: 3200 | AB617: 367.6 | AC617: 970 | AD617: 9310 | AE617: 1047.5 | AF617: 1611 | AG617: 19.3884
A618: 44722 | B618: =VLOOKUP(A618,'FTSE All-Share Historical '!A:B,2,FALSE) -> 4076.7 | C618: 576 | D618: 183 | E618: 208.6 | F618: 323 | G618: 101 | H618: 485 | I618: 58 | J618: 226.5 | K618: 240 | L618: 187.8 | M618: 486 | N618: 203.4 | O618: 1230 | P618: 2040 | Q618: 72.8 | R618: 39.6 | S618: 56.5 | T618: 466 | U618: 230 | V618: 224 | W618: 5690 | X618: 3613 | Y618: 257 | Z618: 741 | AA618: 3200 | AB618: 366.2 | AC618: 962.5 | AD618: 9146 | AE618: 1003 | AF618: 1583.5 | AG618: 18.7816
A619: 44725 | B619: =VLOOKUP(A619,'FTSE All-Share Historical '!A:B,2,FALSE) -> 4007.68 | C619: 576 | D619: 182.6 | E619: 204.4 | F619: 319 | G619: 99.5 | H619: 465 | I619: 56.15 | J619: 228 | K619: 240 | L619: 173.2 | M619: 451 | N619: 201 | O619: 1224 | P619: 1976 | Q619: 70.2 | R619: 39 | S619: 54.8 | T619: 426 | U619: 229 | V619: 214.5 | W619: 5580 | X619: 3518.5 | Y619: 250 | Z619: 730 | AA619: 3175 | AB619: 359.8 | AC619: 962.5 | AD619: 8952 | AE619: 960.2 | AF619: 1537.5 | AG619: 19.504
A620: 44726 | B620: =VLOOKUP(A620,'FTSE All-Share Historical '!A:B,2,FALSE) -> 3995.35 | C620: 580 | D620: 181.8 | E620: 201.2 | F620: 320 | G620: 102.6 | H620: 466 | I620: 56.15 | J620: 225.5 | K620: 235 | L620: 170.4 | M620: 429.5 | N620: 200.2 | O620: 1226 | P620: 1912 | Q620: 70.5 | R620: 39.475 | S620: 55.3 | T620: 455 | U620: 220 | V620: 217 | W620: 5555 | X620: 3455 | Y620: 248 | Z620: 719.5 | AA620: 3160 | AB620: 360 | AC620: 947.5 | AD620: 9186 | AE620: 950.8 | AF620: 1509.5 | AG620: 19.504
A621: 44727 | B621: =VLOOKUP(A621,'FTSE All-Share Historical '!A:B,2,FALSE) -> 4044.51 | C621: 606 | D621: 176 | E621: 197.5 | F621: 320 | G621: 102.4 | H621: 470 | I621: 57.1 | J621: 213 | K621: 233 | L621: 170 | M621: 439.5 | N621: 207.2 | O621: 1200 | P621: 1918 | Q621: 69.9 | R621: 39 | S621: 53.5 | T621: 476 | U621: 224 | V621: 210.5 | W621: 5635 | X621: 3551 | Y621: 251.5 | Z621: 723 | AA621: 3110 | AB621: 349.8 | AC621: 960 | AD621: 9130 | AE621: 993 | AF621: 1518 | AG621: 19.504
A622: 44728 | B622: =VLOOKUP(A622,'FTSE All-Share Historical '!A:B,2,FALSE) -> 3918.07 | C622: 630 | D622: 175 | E622: 142.8 | F622: 320 | G622: 106.8 | H622: 435.5 | I622: 54.9 | J622: 203 | K622: 235 | L622: 162.8 | M622: 419.5 | N622: 196.9 | O622: 1212 | P622: 1822 | Q622: 68 | R622: 38 | S622: 53 | T622: 438 | U622: 215 | V622: 206 | W622: 5444 | X622: 3447 | Y622: 241 | Z622: 690.5 | AA622: 2975 | AB622: 328 | AC622: 975 | AD622: 8680 | AE622: 939.8 | AF622: 1485 | AG622: 19.5762
A623: 44729 | B623: =VLOOKUP(A623,'FTSE All-Share Historical '!A:B,2,FALSE) -> 3910.86 | C623: 624 | D623: 174 | E623: 156.8 | F623: 312 | G623: 106.4 | H623: 439.5 | I623: 54.2 | J623: 210 | K623: 240 | L623: 163 | M623: 415 | N623: 199.8 | O623: 1206 | P623: 1858 | Q623: 67.9 | R623: 36 | S623: 52 | T623: 440 | U623: 216 | V623: 206 | W623: 5177 | X623: 3344.5 | Y623: 234 | Z623: 700.5 | AA623: 2915 | AB623: 329.6 | AC623: 1050 | AD623: 8950 | AE623: 985.6 | AF623: 1496.5 | AG623: 21.5411
A624: 44732 | B624: =VLOOKUP(A624,'FTSE All-Share Historical '!A:B,2,FALSE) -> 3963.31 | C624: 618 | D624: 173.6 | E624: 153.4 | F624: 312 | G624: 101.6 | H624: 439 | I624: 55.15 | J624: 215 | K624: 235 | L624: 169.2 | M624: 454 | N624: 206.4 | O624: 1218 | P624: 1798 | Q624: 69.8 | R624: 35.5 | S624: 52.4 | T624: 462 | U624: 211 | V624: 205.5 | W624: 5125 | X624: 3353.5 | Y624: 233.5 | Z624: 700 | AA624: 2945 | AB624: 331 | AC624: 990 | AD624: 8962 | AE624: 1029.5 | AF624: 1500 | AG624: 25.283
A625: 44733 | B625: =VLOOKUP(A625,'FTSE All-Share Historical '!A:B,2,FALSE) -> 3975.58 | C625: 610 | D625: 176 | E625: 148.8 | F625: 314 | G625: 100 | H625: 436 | I625: 54.25 | J625: 210 | K625: 237 | L625: 161 | M625: 459 | N625: 201.8 | O625: 1190 | P625: 1776 | Q625: 70.6 | R625: 35 | S625: 53.1 | T625: 475 | U625: 210 | V625: 208 | W625: 5250 | X625: 3374 | Y625: 237.5 | Z625: 688 | AA625: 2950 | AB625: 329.6 | AC625: 970 | AD625: 9018 | AE625: 987.6 | AF625: 1482 | AG625: 23.5637
... A672: 44798 | B672: =VLOOKUP(A672,'FTSE All-Share Historical '!A:B,2,FALSE) -> 4139.86 | C672: 614 | D672: 161 | E672: 127.8 | F672: 283 | G672: 83 | H672: 447 | I672: 37.5 | J672: 199 | K672: 210 | L672: 127 | M672: 447 | N672: 160.4 | O672: 1218 | P672: 1774 | Q672: 70 | R672: 40.5 | S672: 51 | T672: 361 | U672: 200.5 | V672: 205 | W672: 4951 | X672: 2919.5 | Y672: 231.5 | Z672: 499.6 | AA672: 3050 | AB672: 322.6 | AC672: 890 | AD672: 10235 | AE672: 873.6 | AF672: 1354 | AG672: 15.7477
A673: 44799 | B673: =VLOOKUP(A673,'FTSE All-Share Historical '!A:B,2,FALSE) -> 4112.34 | C673: 620 | D673: 160.4 | E673: 124.7 | F673: #N/A | G673: 85.15 | H673: 443 | I673: 36.66 | J673: 195.75 | K673: 204 | L673: 120.4 | M673: 435.5 | N673: 157.5 | O673: 1218 | P673: 1730 | Q673: 70.4 | R673: 41 | S673: 50.3 | T673: 364 | U673: 198 | V673: 198 | W673: 4980 | X673: 2922.5 | Y673: 232 | Z673: 492 | AA673: 3060 | AB673: 321.2 | AC673: 875 | AD673: 10085 | AE673: 854.2 | AF673: 1336 | AG673: 15.8921
A674: 44803 | B674: =VLOOKUP(A674,'FTSE All-Share Historical '!A:B,2,FALSE) -> 4080.77 | C674: 590 | D674: 158.4 | E674: 127.4 | F674: 280 | G674: 83 | H674: 443.5 | I674: 36.04 | J674: 195.75 | K674: 205 | L674: 123.4 | M674: 438 | N674: 155.6 | O674: 1198 | P674: 1744 | Q674: 72.1 | R674: 40 | S674: 49.7 | T674: 350 | U674: 201 | V674: 192.4 | W674: 4815 | X674: 2786.5 | Y674: 225.5 | Z674: 490.8 | AA674: 3025 | AB674: 326.8 | AC674: 870 | AD674: 10025 | AE674: 848.6 | AF674: 1319.5 | AG674: 15.1698
A675: 44804 | B675: =VLOOKUP(A675,'FTSE All-Share Historical '!A:B,2,FALSE) -> 4041.53 | C675: 572 | D675: 157.6 | E675: 130.6 | F675: 281 | G675: 83 | H675: 444.5 | I675: 36.36 | J675: 197.5 | K675: 212 | L675: 128 | M675: 457 | N675: 154.5 | O675: 1176 | P675: 1726 | Q675: 71.6 | R675: 40 | S675: 48.65 | T675: 344 | U675: 205 | V675: 189.4 | W675: 4771 | X675: 2783 | Y675: 230 | Z675: 482 | AA675: 3015 | AB675: 329 | AC675: 850 | AD675: 9986 | AE675: 854.4 | AF675: 1313 | AG675: 15.8921
A676: 44805 | B676: =VLOOKUP(A676,'FTSE All-Share Historical '!A:B,2,FALSE) -> 3959.37 | C676: 566 | D676: 159 | E676: 130.2 | F676: 279 | G676: 83 | H676: 438.5 | I676: 36.32 | J676: 195 | K676: 210 | L676: 127.8 | M676: 420.5 | N676: 149.1 | O676: 1160 | P676: 1646 | Q676: 70.4 | R676: 38.45 | S676: 48 | T676: 362 | U676: 200 | V676: 185.2 | W676: 4607.5 | X676: 2678 | Y676: 216 | Z676: 471.8 | AA676: 2770 | AB676: 316.4 | AC676: 857.5 | AD676: 9788 | AE676: 866 | AF676: 1289.5 | AG676: 15.2709
A677: 44806 | B677: =VLOOKUP(A677,'FTSE All-Share Historical '!A:B,2,FALSE) -> 4033.38 | C677: 569 | D677: 155.8 | E677: 132.7 | F677: 279 | G677: 82 | H677: 441 | I677: 38.8 | J677: 195.25 | K677: 212 | L677: 121.2 | M677: 432.5 | N677: 153.6 | O677: 1130 | P677: 1688 | Q677: 70.7 | R677: 39.25 | S677: 47.8 | T677: 369 | U677: 200 | V677: 189 | W677: 4700.5 | X677: 2751.5 | Y677: 218.5 | Z677: 484 | AA677: 2860 | AB677: 320.6 | AC677: 845 | AD677: 9946 | AE677: 900 | AF677: 1308 | AG677: 16.1811
A678: 44809 | B678: =VLOOKUP(A678,'FTSE All-Share Historical '!A:B,2,FALSE) -> 4029.14 | C678: 546 | D678: 153.2 | E678: 134 | F678: 279 | G678: 77 | H678: 440 | I678: 39.5 | J678: 195.75 | K678: 206 | L678: 118.4 | M678: 423.5 | N678: 153.6 | O678: 1126 | P678: 1666 | Q678: 70.3 | R678: 40 | S678: 46.75 | T678: 391 | U678: 196 | V678: 184.4 | W678: 4732.5 | X678: 2769 | Y678: 218 | Z678: 488.6 | AA678: 2810 | AB678: 320.2 | AC678: 860 | AD678: 9872 | AE678: 859.8 | AF678: 1279 | AG678: 16.6217
A679: 44810 | B679: =VLOOKUP(A679,'FTSE All-Share Historical '!A:B,2,FALSE) -> 4041.41 | C679: 550 | D679: 162.2 | E679: 133.5 | F679: 279 | G679: 80 | H679: 437.5 | I679: 41.46 | J679: 198 | K679: 216 | L679: 114.8 | M679: 421.5 | N679: 164.9 | O679: 1126 | P679: 1686 | Q679: 70.9 | R679: 39.1 | S679: 46.5 | T679: 401 | U679: 202 | V679: 186 | W679: 4733.5 | X679: 2806.5 | Y679: 219.5 | Z679: 511 | AA679: 2700 | AB679: 325 | AC679: 862.5 | AD679: 9894 | AE679: 882.4 | AF679: 1292 | AG679: 15.8921
A680: 44811 | B680: =VLOOKUP(A680,'FTSE All-Share Historical '!A:B,2,FALSE) -> 4011.63 | C680: 540 | D680: 160 | E680: 154.3 | F680: 276 | G680: 81.2 | H680: 426.5 | I680: 41.56 | J680: 195 | K680: 212 | L680: 115 | M680: 426.5 | N680: 156.6 | O680: 1130 | P680: 1672 | Q680: 70.8 | R680: 40 | S680: 46.25 | T680: 454 | U680: 203 | V680: 183.8 | W680: 4632 | X680: 2744 | Y680: 219 | Z680: 505 | AA680: 2690 | AB680: 320.2 | AC680: 845 | AD680: 9882 | AE680: 894.2 | AF680: 1282 | AG680: 17.3369
A681: 44812 | B681: =VLOOKUP(A681,'FTSE All-Share Historical '!A:B,2,FALSE) -> 4025.18 | C681: 538 | D681: 158.6 | E681: 150 | F681: 275 | G681: 85.3 | H681: 429 | I681: 45.24 | J681: 195 | K681: 209 | L681: 116.2 | M681: 437.5 | N681: 162.3 | O681: 1132 | P681: 1630 | Q681: 71.7 | R681: 42 | S681: 46 | T681: 449 | U681: 203 | V681: 177.4 | W681: 4725.5 | X681: 2794.5 | Y681: 222 | Z681: 513.5 | AA681: 2665 | AB681: 323 | AC681: 890 | AD681: 10030 | AE681: 873.4 | AF681: 1266.5 | AG681: 15.8921
A682: 44813 | B682: =VLOOKUP(A682,'FTSE All-Share Historical '!A:B,2,FALSE) -> 4077.03 | C682: 510 | D682: 155 | E682: 154.7 | F682: 276 | G682: 81.8 | H682: 432.5 | I682: 46.14 | J682: 192.5 | K682: 215 | L682: 124.2 | M682: 451 | N682: 165.4 | O682: 1090 | P682: 1670 | Q682: 73 | R682: 41.3 | S682: 45.5 | T682: 480 | U682: 209 | V682: 184 | W682: 4860 | X682: 2926.5 | Y682: 232 | Z682: 521 | AA682: 2725 | AB682: 320.4 | AC682: 845 | AD682: 10135 | AE682: 875.6 | AF682: 1285.5 | AG682: 15.6176
A683: 44816 | B683: =VLOOKUP(A683,'FTSE All-Share Historical '!A:B,2,FALSE) -> 4144.91 | C683: 510 | D683: 157 | E683: 160.3 | F683: 274 | G683: 82.2 | H683: 440 | I683: 45.4 | J683: 194 | K683: 216 | L683: 135 | M683: 455 | N683: 172.2 | O683: 1138 | P683: 1730 | Q683: 75.5 | R683: 42.25 | S683: 44.6 | T683: 578 | U683: 203 | V683: 181.8 | W683: 4944.5 | X683: 2990.5 | Y683: 240.5 | Z683: 538.5 | AA683: 2770 | AB683: 324.6 | AC683: 850 | AD683: 10260 | AE683: 879.8 | AF683: 1316 | AG683: 14.8086
A684: 44817 | B684: =VLOOKUP(A684,'FTSE All-Share Historical '!A:B,2,FALSE) -> 4092.77 | C684: 500 | D684: 159.4 | E684: 154.1 | F684: 274 | G684: 79 | H684: 445 | I684: 43.46 | J684: 192.5 | K684: 217 | L684: 128.2 | M684: 453 | N684: 169 | O684: 1140 | P684: 1660 | Q684: 75.1 | R684: 42.8 | S684: 46 | T684: 578 | U684: 205 | V684: 176 | W684: 4909 | X684: 2920.5 | Y684: 240 | Z684: 523 | AA684: 2720 | AB684: 324 | AC684: 850 | AD684: 10150 | AE684: 862.2 | AF684: 1266.5 | AG684: 14.628
...
