Workbook
Name alloc_stu_grp: [1]stu_alloc!$B$2:$B$54
Name c_date: Report!$C$11
Name co_idx: [1]Report!$B$2
Name co_idx: Report!$B$2
Name co_idx: Report!$B$2
Name end_date: [1]Params!$B$7
Name Ex_code: Report!$B$4
Name Ex_code: Report!$B$4
Name Ex_code: Report!$B$1
Name exch_code: [1]Params!$B$4
Name Master_mode: [1]hparams!#REF!
Name Setup_status: #REF!
Name st_id: #REF!
Name start_date: [1]Params!$B$8
Name stu_grp: #REF!
Name stu_grp: #REF!
Name stu_idx: [1]hparams!$B$4
Name stu_key_id: [1]hparams!$B$3

Sheet Instructions
A2: Individual Report - Excel Workbook Template | D2: Write your company name, Code and Sector here
A3: Student Number: | B3: 25062677 - 10240511
B4: WORKBOOK TABS
A5: Instructions | B5: This page guides you through much of the preparation for the assignment.
A6: Co. Names | B6: List of all companies for which we have data and allocation to student. Please delete this sheet once you found your company. | D6: Company Name | F6: OXFORD NANOPORE TECHNOLOGIES PLC
A7: FTSE Data | B7: This has the daily cloing prices for a five year period, for the FTSE 350, FTSE-All shares, FTSE 100 Index for for comparison purposes, wherever applicable. | D7: Code | F7: ONT
A8: Example Data | B8: This has the daily share prices for a five year period, for the FTSE 350 (FTSEAS) and for each company being allocated. (Example) | D8: Sector | F8: Biotechnology and Life Sciences
A9: Report | B9: In this worksheet you will build your summary of the company analysis (for use in your word report).
A10: Ret_data | B10: You will calculate the daily returns on this sheet.
A11: IS data | B11: This is where you will paste 3 years of Income Statements .
A12: SoFP data | B12: This is where you will paste 3 years of Statements of Financial Position (Balance Sheets)
A13: Custom Data | B13: Get 3 years of ratios for your assigned company and its competitor.
A14: Mkt_calc | B14: This is where you will put all of your market analysis calculations (risk and return in relation to share price).
A15: Fin_Calc | B15: This is where you will put all of your financial analysis calculations (based on the data in the financial statements) and create relevant charts or tables .
B17: INSTRUCTIONS
A18: 1 | B18: In this tab input your student number.
A19: 2 | B19: In tab 'Report' for the company you have been allocated, insert the company code (that the exchange uses) the official company name, and the sector in which it operates.
A20: 3 | B20: In tab 'Ret_data' calculate the daily returns (%) from the historical daily prices (found in the 'Data' tab) for your company the FTSE All-Shares or FTSE350 and/or competitor. Time period is 01/01/2022 to 31/12/2024 (3 years)
A21: 4 | B21: Extract the Income statement (IS) data and Statements of financial position (SoFP) data for each year ending 2022-2025 (3 years of data). Paste the data into the tabs 'IS data' and 'SoFP data' respectively.
A22: 5 | B22: Extract the various ratios for your company and a competitor for the same time period. Paste the data into the 'Custom data' tab and analyse the data creating useful charts/tables.
A23: 6 | B23: In tab 'Mkt_calc' calculate; the daily volatility and average returns, the annual returns and the volatility in each year. Then calculate the overall returns for the whole five years. In this tab you should include the Beta and PE ratio (collected from Yahoo finance ). You will need this for section 3 of your word report ' Market report'.
A24: 7 | B24: In tab 'Fin_calc' perform the analysis - ratio analysis over time and in comparison . Create the charts and tables in this tab. You will need this for section 2 of your word report ' Financial report'.
A25: 8 | B25: In tab 'Report' put all charts and tables that you will be utilising in your word report, these will be duplicates of the charts and tables in 'Fin_calc' and 'Mkt_calc'. Make sure that you number them so that you can cross reference to your report.
A26: 9 | B26: Tidy up the workbook and make it presentable/professional.
A28: REMEMBER: | B28: Regularly save copies of the workbook adding a version number on each save.
B29: Look up the company on FAME, Hargreaves Lansdown and Yahoo finance, to find information about the company and the sector it operates in.

Sheet Sheet1

Sheet Co. Names
A1: Company name | B1: BvD sector | C1: Ticker symbol | E1: Students Allocation
A2: LEGAL & GENERAL GROUP PLC | B2: Banking, Insurance & Financial Services | C2: LGEN | E2: Phan Hoàng | F2: An | J2: Once you identified your company please delete this sheet
A3: ADMIRAL GROUP PLC | B3: Banking, Insurance & Financial Services | C3: ADM | E3: Trương Bùi Thành | F3: An
A4: INVESTEC PLC | B4: Banking, Insurance & Financial Services | C4: INVP | E4: Lê Nguyễn Vân | F4: Anh
A5: CMC MARKETS PLC | B5: Banking, Insurance & Financial Services | C5: CMCX | E5: Nguyễn Phương | F5: Anh
A6: GENUS PLC | B6: Biotechnology and Life Sciences | C6: GNS | E6: Trần Duy | F6: Bảo
A7: OXFORD NANOPORE TECHNOLOGIES PLC | B7: Biotechnology and Life Sciences | C7: ONT | E7: Nguyễn Thanh | F7: Bình
A8: CURRYS PLC | B8: Business Services | C8: CURY | E8: Đậu Minh | F8: Châu
A9: EASYJET PLC | B9: Business Services | C9: EZJ | E9: Hoàng Đức | F9: Cường
A10: MITIE GROUP PLC | B10: Business Services | C10: MTO | E10: Trần Minh | F10: Đăng
A11: ITV PLC | B11: Business Services | C11: ITV | E11: Lê Ngân | F11: Hà
A12: SEVERN TRENT PLC | B12: Business Services | C12: SVT | E12: Tăng Thu | F12: Hằng
A13: VODAFONE GROUP PUBLIC LIMITED COMPANY | B13: Communications | C13: VOD | E13: Nguyễn Xuân | F13: Hậu
A14: BT GROUP PLC | B14: Communications | C14: BT.A | E14: Đỗ Minh | F14: Hoàng
... A36: PRIMARY HEALTH PROPERTIES PLC | B36: Property Services | C36: PHP | E36: Nguyễn Thị Hà | F36: Vy
A37: WATCHES OF SWITZERLAND GROUP PLC | B37: Retail | C37: WOSG
A38: EMPIRIC STUDENT PROPERTY PLC | B38: Property Services | C38: ESP
A39: TRAVIS PERKINS PLC | B39: Retail | C39: TPK
A40: THG PLC | B40: Retail | C40: THG
A41: WATCHES OF SWITZERLAND GROUP PLC | B41: Retail | C41: WOSG
A42: WICKES GROUP PLC | B42: Retail | C42: WIX
A43: BAE SYSTEMS PLC | B43: Transport Manufacturing | C43: BA.
A44: CARNIVAL PLC | B44: Transport, Freight & Storage | C44: CCL
A45: FIRSTGROUP PLC | B45: Transport, Freight & Storage | C45: FGP
A46: WIZZ AIR HOLDINGS PLC | B46: Transport, Freight & Storage | C46: WIZZ
A47: J D WETHERSPOON PLC | B47: Travel, Personal & Leisure | C47: JDW
A48: CONVATEC GROUP PLC | B48: Travel, Personal & Leisure | C48: CTEC
... A51: ME GROUP INTERNATIONAL PLC | B51: Travel, Personal & Leisure | C51: MEGP

Sheet FTSE Data
D1: Notes: Please use this data for comparison purposes, wherever applicable
A3: Last Price (£)
A5: Start Date | B5: 44562
A6: End Date | B6: 45657
B8: FTSE 100 Index | C8: FTSE-All Shares | D8: FTSE 350 Index
A9: Dates | B9: UKX Index | C9: ASX Index | D9: NMX Index
A10: 44564 | B10: 7384.54 | C10: 4208.02 | D10: 4228.67
A11: 44565 | B11: 7505.15 | C11: 4276.18 | D11: 4298.76
A12: 44566 | B12: 7516.87 | C12: 4277.51 | D12: 4300.35
A13: 44567 | B13: 7450.37 | C13: 4235.63 | D13: 4257.77
A14: 44568 | B14: 7485.28 | C14: 4249.43 | D14: 4272.27
A15: 44571 | B15: 7445.25 | C15: 4219.71 | D15: 4242.3
A16: 44572 | B16: 7491.37 | C16: 4241.88 | D16: 4264.93
A17: 44573 | B17: 7551.72 | C17: 4270.79 | D17: 4294.04
A18: 44574 | B18: 7563.85 | C18: 4273.23 | D18: 4296.99
A19: 44575 | B19: 7542.95 | C19: 4256.59 | D19: 4280.34
A20: 44578 | B20: 7611.23 | C20: 4292.58 | D20: 4316.64
A21: 44579 | B21: 7563.55 | C21: 4263.04 | D21: 4287.22
... A791: 45657 | B791: 8173.02 | C791: 4467.8 | D791: 4510.61

Sheet My Data
B1: FTSE 350 Index | C1: ONT | D1: GNS
A2: Date | B2: Close | C2: Close | D2: Close
A3: 44564 | B3: 4228.67 | C3: ='Processed closing data'!K1 -> 6.98 | D3: ='Processed closing data'!L1 -> 49.38
A4: 44565 | B4: 4298.76 | C4: ='Processed closing data'!K2 -> 6.71 | D4: ='Processed closing data'!L2 -> 48.76
A5: 44566 | B5: 4300.35 | C5: ='Processed closing data'!K3 -> 6.33 | D5: ='Processed closing data'!L3 -> 48.14
A6: 44567 | B6: 4257.77 | C6: ='Processed closing data'!K4 -> 6.05 | D6: ='Processed closing data'!L4 -> 46.62
A7: 44568 | B7: 4272.27 | C7: ='Processed closing data'!K5 -> 6.05 | D7: ='Processed closing data'!L5 -> 46
A8: 44571 | B8: 4242.3 | C8: ='Processed closing data'!K6 -> 5.65 | D8: ='Processed closing data'!L6 -> 44.5
A9: 44572 | B9: 4264.93 | C9: ='Processed closing data'!K7 -> 5.31 | D9: ='Processed closing data'!L7 -> 44.32
A10: 44573 | B10: 4294.04 | C10: ='Processed closing data'!K8 -> 5.54 | D10: ='Processed closing data'!L8 -> 43.86
A11: 44574 | B11: 4296.99 | C11: ='Processed closing data'!K9 -> 5.51 | D11: ='Processed closing data'!L9 -> 41.92
A12: 44575 | B12: 4280.34 | C12: ='Processed closing data'!K10 -> 5.39 | D12: ='Processed closing data'!L10 -> 41.22
A13: 44578 | B13: 4316.64 | C13: ='Processed closing data'!K11 -> 5.48 | D13: ='Processed closing data'!L11 -> 41.74
A14: 44579 | B14: 4287.22 | C14: ='Processed closing data'!K12 -> 5.16 | D14: ='Processed closing data'!L12 -> 41.12
... A782: 45653 | B782: 4495.62 | C782: ='Processed closing data'!K780 -> 1.27 | D782: ='Processed closing data'!L780 -> 15.2
A783: 45656 | B783: 4479.42 | C783: 1.25 | D783: ='Processed closing data'!L781 -> 15.32
A784: 45657 | B784: 4510.61 | C784: 1.29 | D784: ='Processed closing data'!L782 -> 15.5

Sheet Processed closing data
A1: 44564 | B1: 4228.67 | C1: FTSE-350-Index | D1: 44565 | E1: 6.71 | F1: My Company | I1: =A1 -> 44564 | J1: =B1 -> 4228.67 | K1: 6.98 | L1: 49.38 | O1: 44565 | P1: 48.76 | Q1: Competitor
A2: 44565 | B2: 4298.76 | D2: 44566 | E2: 6.33 | I2: =A2 -> 44565 | J2: =B2 -> 4298.76 | K2: =_xlfn.XLOOKUP(VALUE(I2), 'Processed closing data'!D$1:D$750, 'Processed closing data'!E$1:E$750, "") -> 6.71 | L2: =_xlfn.XLOOKUP(VALUE(I2), 'Processed closing data'!O$1:O$750, 'Processed closing data'!P$1:P$750, "") -> 48.76 | O2: 44566 | P2: 48.14
A3: 44566 | B3: 4300.35 | D3: 44567 | E3: 6.05 | I3: =A3 -> 44566 | J3: =B3 -> 4300.35 | K3: =_xlfn.XLOOKUP(VALUE(I3), 'Processed closing data'!D$1:D$750, 'Processed closing data'!E$1:E$750, "") -> 6.33 | L3: =_xlfn.XLOOKUP(VALUE(I3), 'Processed closing data'!O$1:O$750, 'Processed closing data'!P$1:P$750, "") -> 48.14 | O3: 44567 | P3: 46.62
A4: 44567 | B4: 4257.77 | D4: 44568 | E4: 6.05 | I4: =A4 -> 44567 | J4: =B4 -> 4257.77 | K4: =_xlfn.XLOOKUP(VALUE(I4), 'Processed closing data'!D$1:D$750, 'Processed closing data'!E$1:E$750, "") -> 6.05 | L4: =_xlfn.XLOOKUP(VALUE(I4), 'Processed closing data'!O$1:O$750, 'Processed closing data'!P$1:P$750, "") -> 46.62 | O4: 44568 | P4: 46
A5: 44568 | B5: 4272.27 | D5: 44571 | E5: 5.65 | I5: =A5 -> 44568 | J5: =B5 -> 4272.27 | K5: =_xlfn.XLOOKUP(VALUE(I5), 'Processed closing data'!D$1:D$750, 'Processed closing data'!E$1:E$750, "") -> 6.05 | L5: =_xlfn.XLOOKUP(VALUE(I5), 'Processed closing data'!O$1:O$750, 'Processed closing data'!P$1:P$750, "") -> 46 | O5: 44571 | P5: 44.5
A6: 44571 | B6: 4242.3 | D6: 44572 | E6: 5.31 | I6: =A6 -> 44571 | J6: =B6 -> 4242.3 | K6: =_xlfn.XLOOKUP(VALUE(I6), 'Processed closing data'!D$1:D$750, 'Processed closing data'!E$1:E$750, "") -> 5.65 | L6: =_xlfn.XLOOKUP(VALUE(I6), 'Processed closing data'!O$1:O$750, 'Processed closing data'!P$1:P$750, "") -> 44.5 | O6: 44572 | P6: 44.32
A7: 44572 | B7: 4264.93 | D7: 44573 | E7: 5.54 | I7: =A7 -> 44572 | J7: =B7 -> 4264.93 | K7: =_xlfn.XLOOKUP(VALUE(I7), 'Processed closing data'!D$1:D$750, 'Processed closing data'!E$1:E$750, "") -> 5.31 | L7: =_xlfn.XLOOKUP(VALUE(I7), 'Processed closing data'!O$1:O$750, 'Processed closing data'!P$1:P$750, "") -> 44.32 | O7: 44573 | P7: 43.86
A8: 44573 | B8: 4294.04 | D8: 44574 | E8: 5.51 | I8: =A8 -> 44573 | J8: =B8 -> 4294.04 | K8: =_xlfn.XLOOKUP(VALUE(I8), 'Processed closing data'!D$1:D$750, 'Processed closing data'!E$1:E$750, "") -> 5.54 | L8: =_xlfn.XLOOKUP(VALUE(I8), 'Processed closing data'!O$1:O$750, 'Processed closing data'!P$1:P$750, "") -> 43.86 | O8: 44574 | P8: 41.92
A9: 44574 | B9: 4296.99 | D9: 44575 | E9: 5.39 | I9: =A9 -> 44574 | J9: =B9 -> 4296.99 | K9: =_xlfn.XLOOKUP(VALUE(I9), 'Processed closing data'!D$1:D$750, 'Processed closing data'!E$1:E$750, "") -> 5.51 | L9: =_xlfn.XLOOKUP(VALUE(I9), 'Processed closing data'!O$1:O$750, 'Processed closing data'!P$1:P$750, "") -> 41.92 | O9: 44575 | P9: 41.22
A10: 44575 | B10: 4280.34 | D10: 44578 | E10: 5.48 | I10: =A10 -> 44575 | J10: =B10 -> 4280.34 | K10: =_xlfn.XLOOKUP(VALUE(I10), 'Processed closing data'!D$1:D$750, 'Processed closing data'!E$1:E$750, "") -> 5.39 | L10: =_xlfn.XLOOKUP(VALUE(I10), 'Processed closing data'!O$1:O$750, 'Processed closing data'!P$1:P$750, "") -> 41.22 | O10: 44578 | P10: 41.74
A11: 44578 | B11: 4316.64 | D11: 44579 | E11: 5.16 | I11: =A11 -> 44578 | J11: =B11 -> 4316.64 | K11: =_xlfn.XLOOKUP(VALUE(I11), 'Processed closing data'!D$1:D$750, 'Processed closing data'!E$1:E$750, "") -> 5.48 | L11: =_xlfn.XLOOKUP(VALUE(I11), 'Processed closing data'!O$1:O$750, 'Processed closing data'!P$1:P$750, "") -> 41.74 | O11: 44579 | P11: 41.12
A12: 44579 | B12: 4287.22 | D12: 44580 | E12: 5.22 | I12: =A12 -> 44579 | J12: =B12 -> 4287.22 | K12: =_xlfn.XLOOKUP(VALUE(I12), 'Processed closing data'!D$1:D$750, 'Processed closing data'!E$1:E$750, "") -> 5.16 | L12: =_xlfn.XLOOKUP(VALUE(I12), 'Processed closing data'!O$1:O$750, 'Processed closing data'!P$1:P$750, "") -> 41.12 | O12: 44580 | P12: 40.92
A13: 44580 | B13: 4299.63 | D13: 44581 | E13: 5.46 | I13: =A13 -> 44580 | J13: =B13 -> 4299.63 | K13: =_xlfn.XLOOKUP(VALUE(I13), 'Processed closing data'!D$1:D$750, 'Processed closing data'!E$1:E$750, "") -> 5.22 | L13: =_xlfn.XLOOKUP(VALUE(I13), 'Processed closing data'!O$1:O$750, 'Processed closing data'!P$1:P$750, "") -> 40.92 | O13: 44581 | P13: 40.26
... A74: 44665 | B74: 4263.64 | D74: 44670 | E74: 3.44 | I74: =A74 -> 44665 | J74: =B74 -> 4263.64 | K74: =_xlfn.XLOOKUP(VALUE(I74), 'Processed closing data'!D$1:D$750, 'Processed closing data'!E$1:E$750, "") -> 3.54 | L74: =_xlfn.XLOOKUP(VALUE(I74), 'Processed closing data'!O$1:O$750, 'Processed closing data'!P$1:P$750, "") -> 26.54 | O74: 44670 | P74: 26.5
A75: 44666 | B75: 4263.64 | D75: 44671 | E75: 3.44 | I75: =A75 -> 44666 | J75: =B75 -> 4263.64 | K75: 3.54 | L75: 26.54 | O75: 44671 | P75: 26.46
A76: 44669 | B76: 4263.64 | D76: 44672 | E76: 3.56 | I76: =A76 -> 44669 | J76: =B76 -> 4263.64 | K76: 3.54 | L76: 26.54 | O76: 44672 | P76: 26.38
A77: 44670 | B77: 4251.45 | D77: 44673 | E77: 3.49 | I77: =A77 -> 44670 | J77: =B77 -> 4251.45 | K77: =_xlfn.XLOOKUP(VALUE(I77), 'Processed closing data'!D$1:D$750, 'Processed closing data'!E$1:E$750, "") -> 3.44 | L77: =_xlfn.XLOOKUP(VALUE(I77), 'Processed closing data'!O$1:O$750, 'Processed closing data'!P$1:P$750, "") -> 26.5 | O77: 44673 | P77: 26.58
A78: 44671 | B78: 4268.5 | D78: 44676 | E78: 3.19 | I78: =A78 -> 44671 | J78: =B78 -> 4268.5 | K78: =_xlfn.XLOOKUP(VALUE(I78), 'Processed closing data'!D$1:D$750, 'Processed closing data'!E$1:E$750, "") -> 3.44 | L78: =_xlfn.XLOOKUP(VALUE(I78), 'Processed closing data'!O$1:O$750, 'Processed closing data'!P$1:P$750, "") -> 26.46 | O78: 44676 | P78: 26.6
A79: 44672 | B79: 4270.31 | D79: 44677 | E79: 3.14 | I79: =A79 -> 44672 | J79: =B79 -> 4270.31 | K79: =_xlfn.XLOOKUP(VALUE(I79), 'Processed closing data'!D$1:D$750, 'Processed closing data'!E$1:E$750, "") -> 3.56 | L79: =_xlfn.XLOOKUP(VALUE(I79), 'Processed closing data'!O$1:O$750, 'Processed closing data'!P$1:P$750, "") -> 26.38 | O79: 44677 | P79: 26.3
A80: 44673 | B80: 4211.35 | D80: 44678 | E80: 3.18 | I80: =A80 -> 44673 | J80: =B80 -> 4211.35 | K80: =_xlfn.XLOOKUP(VALUE(I80), 'Processed closing data'!D$1:D$750, 'Processed closing data'!E$1:E$750, "") -> 3.49 | L80: =_xlfn.XLOOKUP(VALUE(I80), 'Processed closing data'!O$1:O$750, 'Processed closing data'!P$1:P$750, "") -> 26.58 | O80: 44678 | P80: 25.18
A81: 44676 | B81: 4135.79 | D81: 44679 | E81: 3.2 | I81: =A81 -> 44676 | J81: =B81 -> 4135.79 | K81: =_xlfn.XLOOKUP(VALUE(I81), 'Processed closing data'!D$1:D$750, 'Processed closing data'!E$1:E$750, "") -> 3.19 | L81: =_xlfn.XLOOKUP(VALUE(I81), 'Processed closing data'!O$1:O$750, 'Processed closing data'!P$1:P$750, "") -> 26.6 | O81: 44679 | P81: 25.4
A82: 44677 | B82: 4135.06 | D82: 44680 | E82: 3.07 | I82: =A82 -> 44677 | J82: =B82 -> 4135.06 | K82: =_xlfn.XLOOKUP(VALUE(I82), 'Processed closing data'!D$1:D$750, 'Processed closing data'!E$1:E$750, "") -> 3.14 | L82: =_xlfn.XLOOKUP(VALUE(I82), 'Processed closing data'!O$1:O$750, 'Processed closing data'!P$1:P$750, "") -> 26.3 | O82: 44680 | P82: 25.16
A83: 44678 | B83: 4151.93 | D83: 44684 | E83: 2.94 | I83: =A83 -> 44678 | J83: =B83 -> 4151.93 | K83: =_xlfn.XLOOKUP(VALUE(I83), 'Processed closing data'!D$1:D$750, 'Processed closing data'!E$1:E$750, "") -> 3.18 | L83: =_xlfn.XLOOKUP(VALUE(I83), 'Processed closing data'!O$1:O$750, 'Processed closing data'!P$1:P$750, "") -> 25.18 | O83: 44684 | P83: 24.46
A84: 44679 | B84: 4197.13 | D84: 44685 | E84: 2.8 | I84: =A84 -> 44679 | J84: =B84 -> 4197.13 | K84: =_xlfn.XLOOKUP(VALUE(I84), 'Processed closing data'!D$1:D$750, 'Processed closing data'!E$1:E$750, "") -> 3.2 | L84: =_xlfn.XLOOKUP(VALUE(I84), 'Processed closing data'!O$1:O$750, 'Processed closing data'!P$1:P$750, "") -> 25.4 | O84: 44685 | P84: 24
A85: 44680 | B85: 4216.64 | D85: 44686 | E85: 2.86 | I85: =A85 -> 44680 | J85: =B85 -> 4216.64 | K85: =_xlfn.XLOOKUP(VALUE(I85), 'Processed closing data'!D$1:D$750, 'Processed closing data'!E$1:E$750, "") -> 3.07 | L85: =_xlfn.XLOOKUP(VALUE(I85), 'Processed closing data'!O$1:O$750, 'Processed closing data'!P$1:P$750, "") -> 25.16 | O85: 44686 | P85: 23.98
A86: 44683 | B86: 4216.64 | D86: 44687 | E86: 2.71 | I86: =A86 -> 44683 | J86: =B86 -> 4216.64 | K86: 3.07 | L86: 25.16 | O86: 44687 | P86: 22.76
A87: 44684 | B87: 4218.6 | D87: 44690 | E87: 2.58 | I87: =A87 -> 44684 | J87: =B87 -> 4218.6 | K87: =_xlfn.XLOOKUP(VALUE(I87), 'Processed closing data'!D$1:D$750, 'Processed closing data'!E$1:E$750, "") -> 2.94 | L87: =_xlfn.XLOOKUP(VALUE(I87), 'Processed closing data'!O$1:O$750, 'Processed closing data'!P$1:P$750, "") -> 24.46 | O87: 44690 | P87: 22.34
A88: 44685 | B88: 4177.02 | D88: 44691 | E88: 2.55 | I88: =A88 -> 44685 | J88: =B88 -> 4177.02 | K88: =_xlfn.XLOOKUP(VALUE(I88), 'Processed closing data'!D$1:D$750, 'Processed closing data'!E$1:E$750, "") -> 2.8 | L88: =_xlfn.XLOOKUP(VALUE(I88), 'Processed closing data'!O$1:O$750, 'Processed closing data'!P$1:P$750, "") -> 24 | O88: 44691 | P88: 23.66
A89: 44686 | B89: 4177.55 | D89: 44692 | E89: 2.62 | I89: =A89 -> 44686 | J89: =B89 -> 4177.55 | K89: =_xlfn.XLOOKUP(VALUE(I89), 'Processed closing data'!D$1:D$750, 'Processed closing data'!E$1:E$750, "") -> 2.86 | L89: =_xlfn.XLOOKUP(VALUE(I89), 'Processed closing data'!O$1:O$750, 'Processed closing data'!P$1:P$750, "") -> 23.98 | O89: 44692 | P89: 24.38
A90: 44687 | B90: 4114.56 | D90: 44693 | E90: 2.55 | I90: =A90 -> 44687 | J90: =B90 -> 4114.56 | K90: =_xlfn.XLOOKUP(VALUE(I90), 'Processed closing data'!D$1:D$750, 'Processed closing data'!E$1:E$750, "") -> 2.71 | L90: =_xlfn.XLOOKUP(VALUE(I90), 'Processed closing data'!O$1:O$750, 'Processed closing data'!P$1:P$750, "") -> 22.76 | O90: 44693 | P90: 24.56
A91: 44690 | B91: 4017.43 | D91: 44694 | E91: 2.85 | I91: =A91 -> 44690 | J91: =B91 -> 4017.43 | K91: =_xlfn.XLOOKUP(VALUE(I91), 'Processed closing data'!D$1:D$750, 'Processed closing data'!E$1:E$750, "") -> 2.58 | L91: =_xlfn.XLOOKUP(VALUE(I91), 'Processed closing data'!O$1:O$750, 'Processed closing data'!P$1:P$750, "") -> 22.34 | O91: 44694 | P91: 25.44
A92: 44691 | B92: 4032.49 | D92: 44697 | E92: 2.9 | I92: =A92 -> 44691 | J92: =B92 -> 4032.49 | K92: =_xlfn.XLOOKUP(VALUE(I92), 'Processed closing data'!D$1:D$750, 'Processed closing data'!E$1:E$750, "") -> 2.55 | L92: =_xlfn.XLOOKUP(VALUE(I92), 'Processed closing data'!O$1:O$750, 'Processed closing data'!P$1:P$750, "") -> 23.66 | O92: 44697 | P92: 25.66
A93: 44692 | B93: 4090.08 | D93: 44698 | E93: 2.94 | I93: =A93 -> 44692 | J93: =B93 -> 4090.08 | K93: =_xlfn.XLOOKUP(VALUE(I93), 'Processed closing data'!D$1:D$750, 'Processed closing data'!E$1:E$750, "") -> 2.62 | L93: =_xlfn.XLOOKUP(VALUE(I93), 'Processed closing data'!O$1:O$750, 'Processed closing data'!P$1:P$750, "") -> 24.38 | O93: 44698 | P93: 25.44
A94: 44693 | B94: 4030.88 | D94: 44699 | E94: 2.8 | I94: =A94 -> 44693 | J94: =B94 -> 4030.88 | K94: =_xlfn.XLOOKUP(VALUE(I94), 'Processed closing data'!D$1:D$750, 'Processed closing data'!E$1:E$750, "") -> 2.55 | L94: =_xlfn.XLOOKUP(VALUE(I94), 'Processed closing data'!O$1:O$750, 'Processed closing data'!P$1:P$750, "") -> 24.56 | O94: 44699 | P94: 25.64
A95: 44694 | B95: 4132.07 | D95: 44700 | E95: 2.95 | I95: =A95 -> 44694 | J95: =B95 -> 4132.07 | K95: =_xlfn.XLOOKUP(VALUE(I95), 'Processed closing data'!D$1:D$750, 'Processed closing data'!E$1:E$750, "") -> 2.85 | L95: =_xlfn.XLOOKUP(VALUE(I95), 'Processed closing data'!O$1:O$750, 'Processed closing data'!P$1:P$750, "") -> 25.44 | O95: 44700 | P95: 25.8
A96: 44697 | B96: 4154.12 | D96: 44701 | E96: 3.23 | I96: =A96 -> 44697 | J96: =B96 -> 4154.12 | K96: =_xlfn.XLOOKUP(VALUE(I96), 'Processed closing data'!D$1:D$750, 'Processed closing data'!E$1:E$750, "") -> 2.9 | L96: =_xlfn.XLOOKUP(VALUE(I96), 'Processed closing data'!O$1:O$750, 'Processed closing data'!P$1:P$750, "") -> 25.66 | O96: 44701 | P96: 26.84
A97: 44698 | B97: 4183.88 | D97: 44704 | E97: 3.12 | I97: =A97 -> 44698 | J97: =B97 -> 4183.88 | K97: =_xlfn.XLOOKUP(VALUE(I97), 'Processed closing data'!D$1:D$750, 'Processed closing data'!E$1:E$750, "") -> 2.94 | L97: =_xlfn.XLOOKUP(VALUE(I97), 'Processed closing data'!O$1:O$750, 'Processed closing data'!P$1:P$750, "") -> 25.44 | O97: 44704 | P97: 26.78
A98: 44699 | B98: 4142.34 | D98: 44705 | E98: 3.17 | I98: =A98 -> 44699 | J98: =B98 -> 4142.34 | K98: =_xlfn.XLOOKUP(VALUE(I98), 'Processed closing data'!D$1:D$750, 'Processed closing data'!E$1:E$750, "") -> 2.8 | L98: =_xlfn.XLOOKUP(VALUE(I98), 'Processed closing data'!O$1:O$750, 'Processed closing data'!P$1:P$750, "") -> 25.64 | O98: 44705 | P98: 26.72
... A108: 44713 | B108: 4197.38 | D108: 44721 | E108: 3.57 | I108: =A108 -> 44713 | J108: =B108 -> 4197.38 | K108: =_xlfn.XLOOKUP(VALUE(I108), 'Processed closing data'!D$1:D$750, 'Processed closing data'!E$1:E$750, "") -> 3.08 | L108: =_xlfn.XLOOKUP(VALUE(I108), 'Processed closing data'!O$1:O$750, 'Processed closing data'!P$1:P$750, "") -> 26.74 | O108: 44721 | P108: 24.78
A109: 44714 | B109: 4197.38 | D109: 44722 | E109: 3.32 | I109: =A109 -> 44714 | J109: =B109 -> 4197.38 | K109: 3.08 | L109: 26.74 | O109: 44722 | P109: 24.74
A110: 44715 | B110: 4197.38 | D110: 44725 | E110: 3.2 | I110: =A110 -> 44715 | J110: =B110 -> 4197.38 | K110: 3.08 | L110: 26.74 | O110: 44725 | P110: 24.3
A111: 44718 | B111: 4240.32 | D111: 44726 | E111: 3.18 | I111: =A111 -> 44718 | J111: =B111 -> 4240.32 | K111: =_xlfn.XLOOKUP(VALUE(I111), 'Processed closing data'!D$1:D$750, 'Processed closing data'!E$1:E$750, "") -> 3.35 | L111: =_xlfn.XLOOKUP(VALUE(I111), 'Processed closing data'!O$1:O$750, 'Processed closing data'!P$1:P$750, "") -> 27.22 | O111: 44726 | P111: 24.06
A112: 44719 | B112: 4232.51 | D112: 44727 | E112: 3.36 | I112: =A112 -> 44719 | J112: =B112 -> 4232.51 | K112: =_xlfn.XLOOKUP(VALUE(I112), 'Processed closing data'!D$1:D$750, 'Processed closing data'!E$1:E$750, "") -> 3.4 | L112: =_xlfn.XLOOKUP(VALUE(I112), 'Processed closing data'!O$1:O$750, 'Processed closing data'!P$1:P$750, "") -> 26.08 | O112: 44727 | P112: 24.86
A113: 44720 | B113: 4226.89 | D113: 44728 | E113: 3.18 | I113: =A113 -> 44720 | J113: =B113 -> 4226.89 | K113: =_xlfn.XLOOKUP(VALUE(I113), 'Processed closing data'!D$1:D$750, 'Processed closing data'!E$1:E$750, "") -> 3.63 | L113: =_xlfn.XLOOKUP(VALUE(I113), 'Processed closing data'!O$1:O$750, 'Processed closing data'!P$1:P$750, "") -> 25.86 | O113: 44728 | P113: 24.3
A114: 44721 | B114: 4164.27 | D114: 44729 | E114: 3.25 | I114: =A114 -> 44721 | J114: =B114 -> 4164.27 | K114: =_xlfn.XLOOKUP(VALUE(I114), 'Processed closing data'!D$1:D$750, 'Processed closing data'!E$1:E$750, "") -> 3.57 | L114: =_xlfn.XLOOKUP(VALUE(I114), 'Processed closing data'!O$1:O$750, 'Processed closing data'!P$1:P$750, "") -> 24.78 | O114: 44729 | P114: 25.12
A115: 44722 | B115: 4076.7 | D115: 44733 | E115: 3.3 | I115: =A115 -> 44722 | J115: =B115 -> 4076.7 | K115: =_xlfn.XLOOKUP(VALUE(I115), 'Processed closing data'!D$1:D$750, 'Processed closing data'!E$1:E$750, "") -> 3.32 | L115: =_xlfn.XLOOKUP(VALUE(I115), 'Processed closing data'!O$1:O$750, 'Processed closing data'!P$1:P$750, "") -> 24.74 | O115: 44733 | P115: 24.84
A116: 44725 | B116: 4007.68 | D116: 44734 | E116: 3.18 | I116: =A116 -> 44725 | J116: =B116 -> 4007.68 | K116: =_xlfn.XLOOKUP(VALUE(I116), 'Processed closing data'!D$1:D$750, 'Processed closing data'!E$1:E$750, "") -> 3.2 | L116: =_xlfn.XLOOKUP(VALUE(I116), 'Processed closing data'!O$1:O$750, 'Processed closing data'!P$1:P$750, "") -> 24.3 | O116: 44734 | P116: 24.92
A117: 44726 | B117: 3995.35 | D117: 44735 | E117: 3.1 | I117: =A117 -> 44726 | J117: =B117 -> 3995.35 | K117: =_xlfn.XLOOKUP(VALUE(I117), 'Processed closing data'!D$1:D$750, 'Processed closing data'!E$1:E$750, "") -> 3.18 | L117: =_xlfn.XLOOKUP(VALUE(I117), 'Processed closing data'!O$1:O$750, 'Processed closing data'!P$1:P$750, "") -> 24.06 | O117: 44735 | P117: 24.76
A118: 44727 | B118: 4044.51 | D118: 44736 | E118: 3.23 | I118: =A118 -> 44727 | J118: =B118 -> 4044.51 | K118: =_xlfn.XLOOKUP(VALUE(I118), 'Processed closing data'!D$1:D$750, 'Processed closing data'!E$1:E$750, "") -> 3.36 | L118: =_xlfn.XLOOKUP(VALUE(I118), 'Processed closing data'!O$1:O$750, 'Processed closing data'!P$1:P$750, "") -> 24.86 | O118: 44736 | P118: 25.04
A119: 44728 | B119: 3918.07 | D119: 44739 | E119: 3.19 | I119: =A119 -> 44728 | J119: =B119 -> 3918.07 | K119: =_xlfn.XLOOKUP(VALUE(I119), 'Processed closing data'!D$1:D$750, 'Processed closing data'!E$1:E$750, "") -> 3.18 | L119: =_xlfn.XLOOKUP(VALUE(I119), 'Processed closing data'!O$1:O$750, 'Processed closing data'!P$1:P$750, "") -> 24.3 | O119: 44739 | P119: 25.32
A120: 44729 | B120: 3910.86 | D120: 44740 | E120: 3.05 | I120: =A120 -> 44729 | J120: =B120 -> 3910.86 | K120: =_xlfn.XLOOKUP(VALUE(I120), 'Processed closing data'!D$1:D$750, 'Processed closing data'!E$1:E$750, "") -> 3.25 | L120: =_xlfn.XLOOKUP(VALUE(I120), 'Processed closing data'!O$1:O$750, 'Processed closing data'!P$1:P$750, "") -> 25.12 | O120: 44740 | P120: 25
A121: 44732 | B121: 3963.31 | D121: 44741 | E121: 2.94 | I121: =A121 -> 44732 | J121: =B121 -> 3963.31 | K121: 3.25 | L121: 25.12 | O121: 44741 | P121: 24.4
A122: 44733 | B122: 3975.58 | D122: 44742 | E122: 2.77 | I122: =A122 -> 44733 | J122: =B122 -> 3975.58 | K122: =_xlfn.XLOOKUP(VALUE(I122), 'Processed closing data'!D$1:D$750, 'Processed closing data'!E$1:E$750, "") -> 3.3 | L122: =_xlfn.XLOOKUP(VALUE(I122), 'Processed closing data'!O$1:O$750, 'Processed closing data'!P$1:P$750, "") -> 24.84 | O122: 44742 | P122: 25.08
A123: 44734 | B123: 3944.13 | D123: 44743 | E123: 2.66 | I123: =A123 -> 44734 | J123: =B123 -> 3944.13 | K123: =_xlfn.XLOOKUP(VALUE(I123), 'Processed closing data'!D$1:D$750, 'Processed closing data'!E$1:E$750, "") -> 3.18 | L123: =_xlfn.XLOOKUP(VALUE(I123), 'Processed closing data'!O$1:O$750, 'Processed closing data'!P$1:P$750, "") -> 24.92 | O123: 44743 | P123: 25.54
A124: 44735 | B124: 3905.39 | D124: 44746 | E124: 2.67 | I124: =A124 -> 44735 | J124: =B124 -> 3905.39 | K124: =_xlfn.XLOOKUP(VALUE(I124), 'Processed closing data'!D$1:D$750, 'Processed closing data'!E$1:E$750, "") -> 3.1 | L124: =_xlfn.XLOOKUP(VALUE(I124), 'Processed closing data'!O$1:O$750, 'Processed closing data'!P$1:P$750, "") -> 24.76 | O124: 44746 | P124: 25.4
A125: 44736 | B125: 4007.91 | D125: 44747 | E125: 2.75 | I125: =A125 -> 44736 | J125: =B125 -> 4007.91 | K125: =_xlfn.XLOOKUP(VALUE(I125), 'Processed closing data'!D$1:D$750, 'Processed closing data'!E$1:E$750, "") -> 3.23 | L125: =_xlfn.XLOOKUP(VALUE(I125), 'Processed closing data'!O$1:O$750, 'Processed closing data'!P$1:P$750, "") -> 25.04 | O125: 44747 | P125: 25.82
A126: 44739 | B126: 4037.48 | D126: 44748 | E126: 3.1 | I126: =A126 -> 44739 | J126: =B126 -> 4037.48 | K126: =_xlfn.XLOOKUP(VALUE(I126), 'Processed closing data'!D$1:D$750, 'Processed closing data'!E$1:E$750, "") -> 3.19 | L126: =_xlfn.XLOOKUP(VALUE(I126), 'Processed closing data'!O$1:O$750, 'Processed closing data'!P$1:P$750, "") -> 25.32 | O126: 44748 | P126: 26.56
A127: 44740 | B127: 4069.18 | D127: 44749 | E127: 3.19 | I127: =A127 -> 44740 | J127: =B127 -> 4069.18 | K127: =_xlfn.XLOOKUP(VALUE(I127), 'Processed closing data'!D$1:D$750, 'Processed closing data'!E$1:E$750, "") -> 3.05 | L127: =_xlfn.XLOOKUP(VALUE(I127), 'Processed closing data'!O$1:O$750, 'Processed closing data'!P$1:P$750, "") -> 25 | O127: 44749 | P127: 26.6
A128: 44741 | B128: 4053.98 | D128: 44750 | E128: 3.21 | I128: =A128 -> 44741 | J128: =B128 -> 4053.98 | K128: =_xlfn.XLOOKUP(VALUE(I128), 'Processed closing data'!D$1:D$750, 'Processed closing data'!E$1:E$750, "") -> 2.94 | L128: =_xlfn.XLOOKUP(VALUE(I128), 'Processed closing data'!O$1:O$750, 'Processed closing data'!P$1:P$750, "") -> 24.4 | O128: 44750 | P128: 26.08
A129: 44742 | B129: 3974.68 | D129: 44753 | E129: 3.12 | I129: =A129 -> 44742 | J129: =B129 -> 3974.68 | K129: =_xlfn.XLOOKUP(VALUE(I129), 'Processed closing data'!D$1:D$750, 'Processed closing data'!E$1:E$750, "") -> 2.77 | L129: =_xlfn.XLOOKUP(VALUE(I129), 'Processed closing data'!O$1:O$750, 'Processed closing data'!P$1:P$750, "") -> 25.08 | O129: 44753 | P129: 25.28
A130: 44743 | B130: 3973.44 | D130: 44754 | E130: 2.95 | I130: =A130 -> 44743 | J130: =B130 -> 3973.44 | K130: =_xlfn.XLOOKUP(VALUE(I130), 'Processed closing data'!D$1:D$750, 'Processed closing data'!E$1:E$750, "") -> 2.66 | L130: =_xlfn.XLOOKUP(VALUE(I130), 'Processed closing data'!O$1:O$750, 'Processed closing data'!P$1:P$750, "") -> 25.54 | O130: 44754 | P130: 24.26
A131: 44746 | B131: 4002.19 | D131: 44755 | E131: 2.92 | I131: =A131 -> 44746 | J131: =B131 -> 4002.19 | K131: =_xlfn.XLOOKUP(VALUE(I131), 'Processed closing data'!D$1:D$750, 'Processed closing data'!E$1:E$750, "") -> 2.67 | L131: =_xlfn.XLOOKUP(VALUE(I131), 'Processed closing data'!O$1:O$750, 'Processed closing data'!P$1:P$750, "") -> 25.4 | O131: 44755 | P131: 23.76
A132: 44747 | B132: 3895.69 | D132: 44756 | E132: 2.69 | I132: =A132 -> 44747 | J132: =B132 -> 3895.69 | K132: =_xlfn.XLOOKUP(VALUE(I132), 'Processed closing data'!D$1:D$750, 'Processed closing data'!E$1:E$750, "") -> 2.75 | L132: =_xlfn.XLOOKUP(VALUE(I132), 'Processed closing data'!O$1:O$750, 'Processed closing data'!P$1:P$750, "") -> 25.82 | O132: 44756 | P132: 22.98
A133: 44748 | B133: 3943.39 | D133: 44757 | E133: 2.84 | I133: =A133 -> 44748 | J133: =B133 -> 3943.39 | K133: =_xlfn.XLOOKUP(VALUE(I133), 'Processed closing data'!D$1:D$750, 'Processed closing data'!E$1:E$750, "") -> 3.1 | L133: =_xlfn.XLOOKUP(VALUE(I133), 'Processed closing data'!O$1:O$750, 'Processed closing data'!P$1:P$750, "") -> 26.56 | O133: 44757 | P133: 23.34
... A149: 44770 | B149: 4095.65 | D149: 44782 | E149: 3.05 | I149: =A149 -> 44770 | J149: =B149 -> 4095.65 | K149: =_xlfn.XLOOKUP(VALUE(I149), 'Processed closing data'!D$1:D$750, 'Processed closing data'!E$1:E$750, "") -> 3.07 | L149: =_xlfn.XLOOKUP(VALUE(I149), 'Processed closing data'!O$1:O$750, 'Processed closing data'!P$1:P$750, "") -> 27.82 | O149: 44782 | P149: 26.34
A150: 44771 | B150: 4142.41 | D150: 44783 | E150: 3.15 | I150: =A150 -> 44771 | J150: =B150 -> 4142.41 | K150: 3.07 | L150: 27.82 | O150: 44783 | P150: 27.14
A151: 44774 | B151: 4134.95 | D151: 44784 | E151: 3.35 | I151: =A151 -> 44774 | J151: =B151 -> 4134.95 | K151: =_xlfn.XLOOKUP(VALUE(I151), 'Processed closing data'!D$1:D$750, 'Processed closing data'!E$1:E$750, "") -> 3.24 | L151: =_xlfn.XLOOKUP(VALUE(I151), 'Processed closing data'!O$1:O$750, 'Processed closing data'!P$1:P$750, "") -> 28.32 | O151: 44784 | P151: 27.64
A152: 44775 | B152: 4126.34 | D152: 44785 | E152: 3.15 | I152: =A152 -> 44775 | J152: =B152 -> 4126.34 | K152: =_xlfn.XLOOKUP(VALUE(I152), 'Processed closing data'!D$1:D$750, 'Processed closing data'!E$1:E$750, "") -> 3.2 | L152: =_xlfn.XLOOKUP(VALUE(I152), 'Processed closing data'!O$1:O$750, 'Processed closing data'!P$1:P$750, "") -> 27.48 | O152: 44785 | P152: 27.54
A153: 44776 | B153: 4148.2 | D153: 44788 | E153: 3.19 | I153: =A153 -> 44776 | J153: =B153 -> 4148.2 | K153: =_xlfn.XLOOKUP(VALUE(I153), 'Processed closing data'!D$1:D$750, 'Processed closing data'!E$1:E$750, "") -> 3.31 | L153: =_xlfn.XLOOKUP(VALUE(I153), 'Processed closing data'!O$1:O$750, 'Processed closing data'!P$1:P$750, "") -> 27.8 | O153: 44788 | P153: 27.88
A154: 44777 | B154: 4153.71 | D154: 44789 | E154: 3.12 | I154: =A154 -> 44777 | J154: =B154 -> 4153.71 | K154: =_xlfn.XLOOKUP(VALUE(I154), 'Processed closing data'!D$1:D$750, 'Processed closing data'!E$1:E$750, "") -> 3.11 | L154: =_xlfn.XLOOKUP(VALUE(I154), 'Processed closing data'!O$1:O$750, 'Processed closing data'!P$1:P$750, "") -> 28.34 | O154: 44789 | P154: 27.06
A155: 44778 | B155: 4146.45 | D155: 44790 | E155: 3.08 | I155: =A155 -> 44778 | J155: =B155 -> 4146.45 | K155: =_xlfn.XLOOKUP(VALUE(I155), 'Processed closing data'!D$1:D$750, 'Processed closing data'!E$1:E$750, "") -> 3.09 | L155: =_xlfn.XLOOKUP(VALUE(I155), 'Processed closing data'!O$1:O$750, 'Processed closing data'!P$1:P$750, "") -> 27.66 | O155: 44790 | P155: 26.26
A156: 44781 | B156: 4168.67 | D156: 44791 | E156: 3.11 | I156: =A156 -> 44781 | J156: =B156 -> 4168.67 | K156: =_xlfn.XLOOKUP(VALUE(I156), 'Processed closing data'!D$1:D$750, 'Processed closing data'!E$1:E$750, "") -> 3.13 | L156: =_xlfn.XLOOKUP(VALUE(I156), 'Processed closing data'!O$1:O$750, 'Processed closing data'!P$1:P$750, "") -> 27.9 | O156: 44791 | P156: 26.5
A157: 44782 | B157: 4164.79 | D157: 44792 | E157: 3.12 | I157: =A157 -> 44782 | J157: =B157 -> 4164.79 | K157: =_xlfn.XLOOKUP(VALUE(I157), 'Processed closing data'!D$1:D$750, 'Processed closing data'!E$1:E$750, "") -> 3.05 | L157: =_xlfn.XLOOKUP(VALUE(I157), 'Processed closing data'!O$1:O$750, 'Processed closing data'!P$1:P$750, "") -> 26.34 | O157: 44792 | P157: 26.52
A158: 44783 | B158: 4186.07 | D158: 44795 | E158: 2.94 | I158: =A158 -> 44783 | J158: =B158 -> 4186.07 | K158: =_xlfn.XLOOKUP(VALUE(I158), 'Processed closing data'!D$1:D$750, 'Processed closing data'!E$1:E$750, "") -> 3.15 | L158: =_xlfn.XLOOKUP(VALUE(I158), 'Processed closing data'!O$1:O$750, 'Processed closing data'!P$1:P$750, "") -> 27.14 | O158: 44795 | P158: 26
A159: 44784 | B159: 4164.99 | D159: 44796 | E159: 2.78 | I159: =A159 -> 44784 | J159: =B159 -> 4164.99 | K159: =_xlfn.XLOOKUP(VALUE(I159), 'Processed closing data'!D$1:D$750, 'Processed closing data'!E$1:E$750, "") -> 3.35 | L159: =_xlfn.XLOOKUP(VALUE(I159), 'Processed closing data'!O$1:O$750, 'Processed closing data'!P$1:P$750, "") -> 27.64 | O159: 44796 | P159: 25.12
A160: 44785 | B160: 4184.46 | D160: 44797 | E160: 2.82 | I160: =A160 -> 44785 | J160: =B160 -> 4184.46 | K160: =_xlfn.XLOOKUP(VALUE(I160), 'Processed closing data'!D$1:D$750, 'Processed closing data'!E$1:E$750, "") -> 3.15 | L160: =_xlfn.XLOOKUP(VALUE(I160), 'Processed closing data'!O$1:O$750, 'Processed closing data'!P$1:P$750, "") -> 27.54 | O160: 44797 | P160: 25.38
A161: 44788 | B161: 4189.75 | D161: 44798 | E161: 2.86 | I161: =A161 -> 44788 | J161: =B161 -> 4189.75 | K161: =_xlfn.XLOOKUP(VALUE(I161), 'Processed closing data'!D$1:D$750, 'Processed closing data'!E$1:E$750, "") -> 3.19 | L161: =_xlfn.XLOOKUP(VALUE(I161), 'Processed closing data'!O$1:O$750, 'Processed closing data'!P$1:P$750, "") -> 27.88 | O161: 44798 | P161: 25.28
A162: 44789 | B162: 4200.94 | D162: 44799 | E162: 2.77 | I162: =A162 -> 44789 | J162: =B162 -> 4200.94 | K162: =_xlfn.XLOOKUP(VALUE(I162), 'Processed closing data'!D$1:D$750, 'Processed closing data'!E$1:E$750, "") -> 3.12 | L162: =_xlfn.XLOOKUP(VALUE(I162), 'Processed closing data'!O$1:O$750, 'Processed closing data'!P$1:P$750, "") -> 27.06 | O162: 44799 | P162: 25.3
... A170: 44799 | B170: 4112.34 | D170: 44812 | E170: 2.86 | I170: =A170 -> 44799 | J170: =B170 -> 4112.34 | K170: =_xlfn.XLOOKUP(VALUE(I170), 'Processed closing data'!D$1:D$750, 'Processed closing data'!E$1:E$750, "") -> 2.77 | L170: =_xlfn.XLOOKUP(VALUE(I170), 'Processed closing data'!O$1:O$750, 'Processed closing data'!P$1:P$750, "") -> 25.3 | O170: 44812 | P170: 27.98
A171: 44802 | B171: 4112.34 | D171: 44813 | E171: 2.87 | I171: =A171 -> 44802 | J171: =B171 -> 4112.34 | K171: 2.77 | L171: 25.3 | O171: 44813 | P171: 28.6
A172: 44803 | B172: 4080.77 | D172: 44816 | E172: 2.72 | I172: =A172 -> 44803 | J172: =B172 -> 4080.77 | K172: =_xlfn.XLOOKUP(VALUE(I172), 'Processed closing data'!D$1:D$750, 'Processed closing data'!E$1:E$750, "") -> 2.85 | L172: =_xlfn.XLOOKUP(VALUE(I172), 'Processed closing data'!O$1:O$750, 'Processed closing data'!P$1:P$750, "") -> 25.28 | O172: 44816 | P172: 28.88
A173: 44804 | B173: 4041.53 | D173: 44817 | E173: 2.84 | I173: =A173 -> 44804 | J173: =B173 -> 4041.53 | K173: =_xlfn.XLOOKUP(VALUE(I173), 'Processed closing data'!D$1:D$750, 'Processed closing data'!E$1:E$750, "") -> 2.74 | L173: =_xlfn.XLOOKUP(VALUE(I173), 'Processed closing data'!O$1:O$750, 'Processed closing data'!P$1:P$750, "") -> 25.16 | O173: 44817 | P173: 27.6
A174: 44805 | B174: 3959.37 | D174: 44818 | E174: 2.95 | I174: =A174 -> 44805 | J174: =B174 -> 3959.37 | K174: =_xlfn.XLOOKUP(VALUE(I174), 'Processed closing data'!D$1:D$750, 'Processed closing data'!E$1:E$750, "") -> 2.86 | L174: =_xlfn.XLOOKUP(VALUE(I174), 'Processed closing data'!O$1:O$750, 'Processed closing data'!P$1:P$750, "") -> 23.74 | O174: 44818 | P174: 26.84
A175: 44806 | B175: 4033.38 | D175: 44819 | E175: 2.97 | I175: =A175 -> 44806 | J175: =B175 -> 4033.38 | K175: =_xlfn.XLOOKUP(VALUE(I175), 'Processed closing data'!D$1:D$750, 'Processed closing data'!E$1:E$750, "") -> 2.99 | L175: =_xlfn.XLOOKUP(VALUE(I175), 'Processed closing data'!O$1:O$750, 'Processed closing data'!P$1:P$750, "") -> 24.5 | O175: 44819 | P175: 27.62
A176: 44809 | B176: 4029.14 | D176: 44820 | E176: 2.89 | I176: =A176 -> 44809 | J176: =B176 -> 4029.14 | K176: =_xlfn.XLOOKUP(VALUE(I176), 'Processed closing data'!D$1:D$750, 'Processed closing data'!E$1:E$750, "") -> 2.94 | L176: =_xlfn.XLOOKUP(VALUE(I176), 'Processed closing data'!O$1:O$750, 'Processed closing data'!P$1:P$750, "") -> 23.42 | O176: 44820 | P176: 27.82
A177: 44810 | B177: 4041.41 | D177: 44824 | E177: 2.83 | I177: =A177 -> 44810 | J177: =B177 -> 4041.41 | K177: =_xlfn.XLOOKUP(VALUE(I177), 'Processed closing data'!D$1:D$750, 'Processed closing data'!E$1:E$750, "") -> 3.01 | L177: =_xlfn.XLOOKUP(VALUE(I177), 'Processed closing data'!O$1:O$750, 'Processed closing data'!P$1:P$750, "") -> 23.94 | O177: 44824 | P177: 27.46
A178: 44811 | B178: 4011.63 | D178: 44825 | E178: 2.84 | I178: =A178 -> 44811 | J178: =B178 -> 4011.63 | K178: =_xlfn.XLOOKUP(VALUE(I178), 'Processed closing data'!D$1:D$750, 'Processed closing data'!E$1:E$750, "") -> 2.92 | L178: =_xlfn.XLOOKUP(VALUE(I178), 'Processed closing data'!O$1:O$750, 'Processed closing data'!P$1:P$750, "") -> 23.98 | O178: 44825 | P178: 28.2
A179: 44812 | B179: 4025.18 | D179: 44826 | E179: 2.65 | I179: =A179 -> 44812 | J179: =B179 -> 4025.18 | K179: =_xlfn.XLOOKUP(VALUE(I179), 'Processed closing data'!D$1:D$750, 'Processed closing data'!E$1:E$750, "") -> 2.86 | L179: =_xlfn.XLOOKUP(VALUE(I179), 'Processed closing data'!O$1:O$750, 'Processed closing data'!P$1:P$750, "") -> 27.98 | O179: 44826 | P179: 28.16
A180: 44813 | B180: 4077.03 | D180: 44827 | E180: 2.46 | I180: =A180 -> 44813 | J180: =B180 -> 4077.03 | K180: =_xlfn.XLOOKUP(VALUE(I180), 'Processed closing data'!D$1:D$750, 'Processed closing data'!E$1:E$750, "") -> 2.87 | L180: =_xlfn.XLOOKUP(VALUE(I180), 'Processed closing data'!O$1:O$750, 'Processed closing data'!P$1:P$750, "") -> 28.6 | O180: 44827 | P180: 27.3
A181: 44816 | B181: 4144.91 | D181: 44830 | E181: 2.39 | I181: =A181 -> 44816 | J181: =B181 -> 4144.91 | K181: =_xlfn.XLOOKUP(VALUE(I181), 'Processed closing data'!D$1:D$750, 'Processed closing data'!E$1:E$750, "") -> 2.72 | L181: =_xlfn.XLOOKUP(VALUE(I181), 'Processed closing data'!O$1:O$750, 'Processed closing data'!P$1:P$750, "") -> 28.88 | O181: 44830 | P181: 26.3
A182: 44817 | B182: 4092.77 | D182: 44831 | E182: 2.38 | I182: =A182 -> 44817 | J182: =B182 -> 4092.77 | K182: =_xlfn.XLOOKUP(VALUE(I182), 'Processed closing data'!D$1:D$750, 'Processed closing data'!E$1:E$750, "") -> 2.84 | L182: =_xlfn.XLOOKUP(VALUE(I182), 'Processed closing data'!O$1:O$750, 'Processed closing data'!P$1:P$750, "") -> 27.6 | O182: 44831 | P182: 25.66
A183: 44818 | B183: 4031.45 | D183: 44832 | E183: 2.42 | I183: =A183 -> 44818 | J183: =B183 -> 4031.45 | K183: =_xlfn.XLOOKUP(VALUE(I183), 'Processed closing data'!D$1:D$750, 'Processed closing data'!E$1:E$750, "") -> 2.95 | L183: =_xlfn.XLOOKUP(VALUE(I183), 'Processed closing data'!O$1:O$750, 'Processed closing data'!P$1:P$750, "") -> 26.84 | O183: 44832 | P183: 25.8
... A185: 44820 | B185: 4010.65 | D185: 44834 | E185: 2.57 | I185: =A185 -> 44820 | J185: =B185 -> 4010.65 | K185: =_xlfn.XLOOKUP(VALUE(I185), 'Processed closing data'!D$1:D$750, 'Processed closing data'!E$1:E$750, "") -> 2.89 | L185: =_xlfn.XLOOKUP(VALUE(I185), 'Processed closing data'!O$1:O$750, 'Processed closing data'!P$1:P$750, "") -> 27.82 | O185: 44834 | P185: 26.18
A186: 44823 | B186: 4010.65 | D186: 44837 | E186: 2.57 | I186: =A186 -> 44823 | J186: =B186 -> 4010.65 | K186: 2.89 | L186: 27.82 | O186: 44837 | P186: 26.02
A187: 44824 | B187: 3981.32 | D187: 44838 | E187: 2.74 | I187: =A187 -> 44824 | J187: =B187 -> 3981.32 | K187: =_xlfn.XLOOKUP(VALUE(I187), 'Processed closing data'!D$1:D$750, 'Processed closing data'!E$1:E$750, "") -> 2.83 | L187: =_xlfn.XLOOKUP(VALUE(I187), 'Processed closing data'!O$1:O$750, 'Processed closing data'!P$1:P$750, "") -> 27.46 | O187: 44838 | P187: 26.3
A188: 44825 | B188: 4008.47 | D188: 44839 | E188: 2.6 | I188: =A188 -> 44825 | J188: =B188 -> 4008.47 | K188: =_xlfn.XLOOKUP(VALUE(I188), 'Processed closing data'!D$1:D$750, 'Processed closing data'!E$1:E$750, "") -> 2.84 | L188: =_xlfn.XLOOKUP(VALUE(I188), 'Processed closing data'!O$1:O$750, 'Processed closing data'!P$1:P$750, "") -> 28.2 | O188: 44839 | P188: 25.46
A189: 44826 | B189: 3959.43 | D189: 44840 | E189: 2.7 | I189: =A189 -> 44826 | J189: =B189 -> 3959.43 | K189: =_xlfn.XLOOKUP(VALUE(I189), 'Processed closing data'!D$1:D$750, 'Processed closing data'!E$1:E$750, "") -> 2.65 | L189: =_xlfn.XLOOKUP(VALUE(I189), 'Processed closing data'!O$1:O$750, 'Processed closing data'!P$1:P$750, "") -> 28.16 | O189: 44840 | P189: 25.88
A190: 44827 | B190: 3881.56 | D190: 44841 | E190: 2.71 | I190: =A190 -> 44827 | J190: =B190 -> 3881.56 | K190: =_xlfn.XLOOKUP(VALUE(I190), 'Processed closing data'!D$1:D$750, 'Processed closing data'!E$1:E$750, "") -> 2.46 | L190: =_xlfn.XLOOKUP(VALUE(I190), 'Processed closing data'!O$1:O$750, 'Processed closing data'!P$1:P$750, "") -> 27.3 | O190: 44841 | P190: 25.34
A191: 44830 | B191: 3874.7 | D191: 44844 | E191: 2.52 | I191: =A191 -> 44830 | J191: =B191 -> 3874.7 | K191: =_xlfn.XLOOKUP(VALUE(I191), 'Processed closing data'!D$1:D$750, 'Processed closing data'!E$1:E$750, "") -> 2.39 | L191: =_xlfn.XLOOKUP(VALUE(I191), 'Processed closing data'!O$1:O$750, 'Processed closing data'!P$1:P$750, "") -> 26.3 | O191: 44844 | P191: 24.44
A192: 44831 | B192: 3844.23 | D192: 44845 | E192: 2.5 | I192: =A192 -> 44831 | J192: =B192 -> 3844.23 | K192: =_xlfn.XLOOKUP(VALUE(I192), 'Processed closing data'!D$1:D$750, 'Processed closing data'!E$1:E$750, "") -> 2.38 | L192: =_xlfn.XLOOKUP(VALUE(I192), 'Processed closing data'!O$1:O$750, 'Processed closing data'!P$1:P$750, "") -> 25.66 | O192: 44845 | P192: 23.42
...

Sheet IS data
A1: OXFORD NANOPORE TECHNOLOGIES PLC | I1: GENUS PLC - Competitor
B4: 31/12/2024 GBP | C4: 31/12/2023 GBP | D4: 31/12/2022 GBP | J4: 30/06/2024 GBP | K4: 30/06/2023 GBP | L4: 30/06/2022 GBP
A5: ∟ Turnover | B5: 183191000 | C5: 169668000 | D5: 198603000 | I5: ∟ Turnover | J5: 668800000 | K5: 689700000 | L5: 593400000
A6: ∟ National Turnover | B6: 21126000 | D6: 198603000 | I6: ∟ National Turnover | J6: 92300000 | K6: 93100000 | L6: 88700000
A7: ∟ Overseas Turnover | B7: 162065000 | I7: ∟ Overseas Turnover | J7: 576500000 | K7: 596600000 | L7: 504700000
A8: ∟ Cost of Sales | B8: -77796000 | C8: -79187000 | D8: -74793000 | I8: ∟ Cost of Sales
A9: ∟ Exceptional Items pre GP | I9: ∟ Exceptional Items pre GP
A10: ∟ Other Income pre GP | I10: ∟ Other Income pre GP
A11: ∟ Gross Profit | B11: 105395000 | C11: 90481000 | D11: 123810000 | I11: ∟ Gross Profit
A12: ∟ Administration Expenses | B12: -257728000 | C12: -259090000 | D12: -222289000 | I12: ∟ Administration Expenses | J12: -637800000 | K12: -645700000 | L12: -542000000
A13: ∟ Other Operating Income/Costs pre OP | I13: ∟ Other Operating Income/Costs pre OP
A14: ∟ Exceptional Items pre OP | I14: ∟ Exceptional Items pre OP | J14: -24600000 | K14: -3500000 | L14: -2000000
A15: ∟ Operating Profit | B15: -152333000 | C15: -168609000 | D15: -98479000 | I15: ∟ Operating Profit | J15: 6400000 | K15: 40500000 | L15: 49400000
A16: ∟ Other Income | B16: 1096000 | C16: 2194000 | D16: 10755000 | I16: ∟ Other Income | J16: 17400000 | K16: 13200000 | L16: 5200000
A17: ∟ Total Other Income & Int. Received | B17: 15937000 | C17: 21047000 | D17: 16696000 | I17: ∟ Total Other Income & Int. Received | J17: 21300000 | K17: 14300000 | L17: 5600000
A18: ∟ Exceptional Items | I18: ∟ Exceptional Items
A19: ∟ Profit (Loss) on Sale of Operations | I19: ∟ Profit (Loss) on Sale of Operations
A20: ∟ Costs of Reorganisation | I20: ∟ Costs of Reorganisation
A21: ∟ Profit (Loss) on Disposal | I21: ∟ Profit (Loss) on Disposal
A22: ∟ Other Exceptional Items | I22: ∟ Other Exceptional Items
A23: ∟ Profit (Loss) before Interest paid | B23: -136396000 | C23: -147562000 | D23: -81783000 | I23: ∟ Profit (Loss) before Interest paid | J23: 27700000 | K23: 54800000 | L23: 55000000
A24: ∟ Interest Received | B24: 14841000 | C24: 18853000 | D24: 5941000 | I24: ∟ Interest Received | J24: 3900000 | K24: 1100000 | L24: 400000
A25: ∟ Interest Paid | B25: -3565000 | C25: -2206000 | D25: -1628000 | I25: ∟ Interest Paid | J25: -22200000 | K25: -15400000 | L25: -6600000
A26: ∟ Paid to Bank | B26: -3 | C26: -1 | D26: -221 | I26: ∟ Paid to Bank | J26: -17800000 | K26: -12300000 | L26: -4100000
A27: ∟ Paid on Hire Purchase | I27: ∟ Paid on Hire Purchase
A28: ∟ Paid on Leasing | B28: -3562000 | C28: -2205000 | D28: -1407000 | I28: ∟ Paid on Leasing | J28: -2800000 | K28: -1200000 | L28: -1100000
A29: ∟ Other Interest Paid | I29: ∟ Other Interest Paid | J29: -1600000 | K29: -1900000 | L29: -1400000
A30: ∟ Net Interest | B30: 11276000 | C30: 16647000 | D30: 4313000 | I30: ∟ Net Interest | J30: -18300000 | K30: -14300000 | L30: -6200000
A31: ∟ Profit (Loss) before Tax | B31: -139961000 | C31: -149768000 | D31: -83411000 | I31: ∟ Profit (Loss) before Tax | J31: 5500000 | K31: 39400000 | L31: 48400000
A32: ∟ Taxation | B32: -6227000 | C32: -4739000 | D32: -7614000 | I32: ∟ Taxation | J32: -3100000 | K32: -7600000 | L32: -11700000
A33: ∟ Profit (Loss) after Tax | B33: -146188000 | C33: -154507000 | D33: -91025000 | I33: ∟ Profit (Loss) after Tax | J33: 2400000 | K33: 31800000 | L33: 36700000
A34: ∟ Extraordinary Items | I34: ∟ Extraordinary Items
A35: ∟ Minority Interests | I35: ∟ Minority Interests | J35: 5500000 | K35: 1500000 | L35: 4200000
A36: ∟ Profit (Loss) for period [=Net income] | B36: -146188000 | C36: -154507000 | D36: -91025000 | I36: ∟ Profit (Loss) for period [=Net income] | J36: 7900000 | K36: 33300000 | L36: 40900000
A37: ∟ Dividends (Distributable profit) | I37: ∟ Dividends (Distributable profit) | J37: -21000000 | K37: -21000000 | L37: -20900000
A38: ∟ Retained Profit(Loss) | B38: -146188000 | C38: -154507000 | D38: -91025000 | I38: ∟ Retained Profit(Loss) | J38: -13100000 | K38: 12300000 | L38: 20000000
A40: ∟ Depreciation | B40: 13449000 | C40: 18105000 | D40: 20443000 | I40: ∟ Depreciation | J40: 20100000 | K40: 30200000 | L40: 27300000
A41: ∟ Depreciation Owned Assets | B41: 12068000 | C41: 16496000 | D41: 15968000 | I41: ∟ Depreciation Owned Assets | J41: 18400000 | K41: 18400000 | L41: 14800000
A42: ∟ Depreciation Other Assets | B42: 1381000 | C42: 1609000 | D42: 4475000 | I42: ∟ Depreciation Other Assets | K42: 11800000 | L42: 11600000
A43: ∟ Impairment of Tangible Assets | I43: ∟ Impairment of Tangible Assets | J43: 1700000 | L43: 900000
A44: ∟ Audit Fee | B44: 564 | C44: 570 | D44: 594 | I44: ∟ Audit Fee | J44: 1400000 | K44: 1000000 | L44: 1000000
A45: ∟ Audit Non-fee expenses | B45: 83 | C45: 90 | D45: 89 | I45: ∟ Audit Non-fee expenses
A46: ∟ Tax Advice | I46: ∟ Tax Advice
A47: ∟ Non-Tax Advisory Services | B47: 83 | C47: 90 | D47: 89 | I47: ∟ Non-Tax Advisory Services
A48: ∟ Other Auditors Services | I48: ∟ Other Auditors Services
A49: ∟ Non-Audit Fees paid to Other Auditors | I49: ∟ Non-Audit Fees paid to Other Auditors
A50: ∟ Total Amortization and Impairment | B50: 29835000 | C50: 23522000 | D50: 11428000 | I50: ∟ Total Amortization and Impairment | J50: 28600000 | K50: 13400000 | L50: 12600000
A51: ∟ Amortisation | B51: 29835000 | C51: 23522000 | D51: 11428000 | I51: ∟ Amortisation | J51: 28600000 | K51: 13400000 | L51: 12600000
A52: ∟ Impairment | I52: ∟ Impairment
A53: ∟ Total Operating Lease Rentals | B53: 971 | C53: 928 | D53: 602 | I53: ∟ Total Operating Lease Rentals | J53: 100000 | L53: 100000
A54: ∟ Hire of Plant & Machinery | D54: 602 | I54: ∟ Hire of Plant & Machinery
A55: ∟ Land & Building or Property Rents & Other | I55: ∟ Land & Building or Property Rents & Other
A56: ∟ Research & Development | B56: 98921000 | C56: 35671000 | I56: ∟ Research & Development | J56: 27800000 | K56: 93300000 | L56: 72900000
A57: ∟ Foreign Exchange Gains/Losses | B57: 504 | C57: 1385000 | D57: 2490000 | I57: ∟ Foreign Exchange Gains/Losses | J57: -600000 | K57: -800000 | L57: -800000
A58: ∟ Remuneration | B58: 150844000 | C58: 151525000 | D58: 144088000 | I58: ∟ Remuneration | J58: 235400000 | K58: 229700000 | L58: 197200000
A59: ∟ Wages & Salaries | B59: 124388000 | C59: 99111000 | D59: 81613000 | I59: ∟ Wages & Salaries | J59: 201700000 | K59: 198100000 | L59: 170900000
A60: ∟ Social Security Costs | B60: 11009000 | C60: 10193000 | D60: -12551000 | I60: ∟ Social Security Costs | J60: 18800000 | K60: 18100000 | L60: 16500000
A61: ∟ Pension Costs | B61: 4911000 | C61: 4113000 | D61: 3183000 | I61: ∟ Pension Costs | J61: 8100000 | K61: 7100000 | L61: 6200000
A62: ∟ Other Staff Costs | B62: 10536000 | C62: 38108000 | D62: 71843000 | I62: ∟ Other Staff Costs | J62: 6800000 | K62: 6400000 | L62: 3600000
A63: ∟ Directors' Remuneration | B63: 4351000 | C63: 4870000 | D63: 87028000 | I63: ∟ Directors' Remuneration | J63: 3951000 | K63: 2482000 | L63: 3153000
A64: ∟ Directors' Fees | B64: 1873000 | C64: 2662000 | D64: 3423000 | I64: ∟ Directors' Fees | J64: 1677000 | K64: 1035000 | L64: 1031000
A65: ∟ Pension Contribution | B65: 102 | C65: 135 | D65: 128 | I65: ∟ Pension Contribution | J65: 101000 | K65: 74000 | L65: 86000
A66: ∟ Other Emoluments | B66: 2376000 | C66: 2073000 | D66: 83477000 | I66: ∟ Other Emoluments | J66: 2173000 | K66: 1373000 | L66: 2036000
A67: ∟ Highest Paid Director | B67: 1819000 | C67: 1351000 | D67: 29212000 | I67: ∟ Highest Paid Director | J67: 2219000 | K67: 1210000 | L67: 1327000
A68: ∟ EBITDA | B68: -109049000 | C68: -126982000 | D68: -66608000 | I68: ∟ EBITDA | J68: 55100000 | K68: 84100000 | L68: 89300000
A69: ∟ Number of employees | B69: 1.315 | C69: 1.133 | D69: 922 | I69: ∟ Number of employees | J69: 3581 | K69: 3628 | L69: 3490

Sheet SoFP data
A1: OXFORD NANOPORE TECHNOLOGIES PLC | I1: GENUS PLC - Competitor
B4: 31/12/2024 GBP | C4: 31/12/2023 GBP | D4: 31/12/2022 GBP | J4: 30/06/2024 GBP | K4: 30/06/2023 GBP | L4: 30/06/2022 GBP
A5: Fixed Assets | I5: Fixed Assets
A6: Tangible Assets | B6: 66331000 | C6: 49890000 | D6: 63200000 | I6: Tangible Assets | J6: 127300000 | K6: 164400000 | L6: 171400000
A7: ∟ Land & Buildings | B7: 4572000 | C7: 5524000 | D7: 5885000 | I7: ∟ Land & Buildings | J7: 81400000 | K7: 93100000 | L7: 88100000
A8: ∟ Freehold Land | I8: ∟ Freehold Land
A9: ∟ Leasehold Land | B9: 4572000 | C9: 5524000 | D9: 5885000 | I9: ∟ Leasehold Land
A10: ∟ Fixtures & Fittings | I10: ∟ Fixtures & Fittings
A11: ∟ Plant & Vehicles | B11: 16579000 | C11: 10463000 | D11: 8283000 | I11: ∟ Plant & Vehicles | K11: 54400000 | L11: 53700000
A12: ∟ Plant | B12: 16579000 | C12: 10463000 | D12: 8283000 | I12: ∟ Plant
A13: ∟ Vehicles | I13: ∟ Vehicles
A14: ∟ Other Fixed Assets | B14: 45180000 | C14: 33903000 | D14: 49032000 | I14: ∟ Other Fixed Assets | J14: 45900000 | K14: 16900000 | L14: 29600000
A15: Intangible Assets | B15: 78674000 | C15: 65436000 | D15: 30039000 | I15: Intangible Assets | J15: 230400000 | K15: 174000000 | L15: 183000000
A16: Investments & other fixed assets | B16: 76950000 | C16: 214553000 | D16: 92651000 | I16: Investments & other fixed assets | J16: 400100000 | K16: 410100000 | L16: 406000000
A17: ∟ Fixed Assets | B17: 221955000 | C17: 329879000 | D17: 185890000 | I17: ∟ Fixed Assets | J17: 757800000 | K17: 748500000 | L17: 760400000
A19: Current Assets | I19: Current Assets
A20: Stock & W.I.P. | B20: 99453000 | C20: 101548000 | D20: 87698000 | I20: Stock & W.I.P. | J20: 57100000 | K20: 61300000 | L20: 50900000
A21: ∟ Stock | B21: 37631000 | C21: 50888000 | D21: 41852000 | I21: ∟ Stock | J21: 24500000 | K21: 26600000 | L21: 24500000
A22: ∟ W.I.P. | B22: 45637000 | C22: 39154000 | D22: 34960000 | I22: ∟ W.I.P.
A23: ∟ Finished Goods | B23: 16185000 | C23: 11506000 | D23: 10886000 | I23: ∟ Finished Goods | J23: 32600000 | K23: 34700000 | L23: 26400000
A24: Trade Debtors | B24: 37537000 | C24: 33830000 | D24: 41181000 | I24: Trade Debtors | J24: 115200000 | K24: 113900000 | L24: 108700000
A25: Bank & Deposits | B25: 199517000 | C25: 220536000 | D25: 356778000 | I25: Bank & Deposits | J25: 42500000 | K25: 36300000 | L25: 38800000
A26: Other Current Assets | B26: 44735000 | C26: 41494000 | D26: 30872000 | I26: Other Current Assets | J26: 22100000 | K26: 22200000 | L26: 24800000
A27: ∟ Group Loans (asset) | I27: ∟ Group Loans (asset)
A28: ∟ Directors Loans (asset) | I28: ∟ Directors Loans (asset)
A29: ∟ Other Debtors | B29: 11652000 | C29: 14101000 | D29: 9986000 | I29: ∟ Other Debtors | J29: 10400000 | K29: 10500000 | L29: 12300000
A30: ∟ Prepayments | B30: 13519000 | C30: 13544000 | D30: 11738000 | I30: ∟ Prepayments | J30: 9600000 | K30: 7700000 | L30: 8500000
A31: ∟ Deferred Taxation | B31: 19564000 | C31: 13849000 | D31: 9148000 | I31: ∟ Deferred Taxation | J31: 2100000 | K31: 4000000 | L31: 4000000
A32: Investments & other current assets | B32: 138853000 | C32: 49775000 | D32: 121471000 | I32: Investments & other current assets | J32: 34200000 | K32: 25300000 | L32: 34300000
A33: ∟ Current Assets | B33: 520095000 | C33: 447183000 | D33: 638000000 | I33: ∟ Current Assets | J33: 271100000 | K33: 259000000 | L33: 257500000
A35: Current Liabilities | I35: Current Liabilities
A36: Trade Creditors | B36: -51966000 | C36: -40340000 | D36: -23103000 | I36: Trade Creditors | J36: -42100000 | K36: -34800000 | L36: -36000000
A37: Short Term Loans & Overdrafts | D37: -16011000 | I37: Short Term Loans & Overdrafts | J37: -4900000 | K37: -14200000 | L37: -17200000
A38: ∟ Bank Overdrafts | I38: ∟ Bank Overdrafts | J38: -4900000 | K38: -4200000 | L38: -7100000
A39: ∟ Group Loans (short t.) | I39: ∟ Group Loans (short t.)
A40: ∟ Director Loans (short t.) | I40: ∟ Director Loans (short t.)
A41: ∟ Hire Purch. & Leas. (short t.) | D41: -15049000 | I41: ∟ Hire Purch. & Leas. (short t.) | K41: -10000000 | L41: -10100000
A42: ∟ Hire Purchase (short t.) | I42: ∟ Hire Purchase (short t.)
A43: ∟ Leasing (short t.) | D43: -15049000 | I43: ∟ Leasing (short t.) | K43: -10000000 | L43: -10100000
A44: ∟ Other Short Term Loans | D44: -962 | I44: ∟ Other Short Term Loans
A45: Total Other Current Liabilities | B45: -59524000 | C45: -48859000 | D45: -63418000 | I45: Total Other Current Liabilities | J45: -103600000 | K45: -98200000 | L45: -98100000
A46: ∟ Corporation Tax | D46: -1639000 | I46: ∟ Corporation Tax | J46: -5200000 | K46: -7400000 | L46: -4900000
A47: ∟ Dividends payable | I47: ∟ Dividends payable
A48: ∟ Accruals & Def. Inc. (short t.) | B48: -45707000 | C48: -33096000 | D48: -33801000 | I48: ∟ Accruals & Def. Inc. (short t.) | J48: -62600000 | K48: -58100000 | L48: -61400000
A49: ∟ Social Securities & V.A.T. | B49: -4474000 | C49: -4507000 | D49: -2585000 | I49: ∟ Social Securities & V.A.T. | J49: -7300000 | K49: -7700000 | L49: -9000000
A50: ∟ Other Current Liabilities | B50: -9343000 | C50: -11256000 | D50: -25393000 | I50: ∟ Other Current Liabilities | J50: -28500000 | K50: -25000000 | L50: -22800000
A51: ∟ Current Liabilities | B51: -111490000 | C51: -89199000 | D51: -102532000 | I51: ∟ Current Liabilities | J51: -150600000 | K51: -147200000 | L51: -151300000
A53: ∟ Net Current Assets | B53: 408605000 | C53: 357984000 | D53: 535468000 | I53: ∟ Net Current Assets | J53: 120500000 | K53: 111800000 | L53: 106200000
A54: ∟ Net Tangible Assets | B54: 551886000 | C54: 622427000 | D54: 691319000 | I54: ∟ Net Tangible Assets | J54: 647900000 | K54: 686300000 | L54: 683600000
A55: ∟ Working Capital | B55: 85024000 | C55: 95038000 | D55: 105776000 | I55: ∟ Working Capital | J55: 130200000 | K55: 140400000 | L55: 123600000
A56: ∟ Total Assets | B56: 742050000 | C56: 777062000 | D56: 823890000 | I56: ∟ Total Assets | J56: 1028900000 | K56: 1007500000 | L56: 1017900000
A57: ∟ Total Assets minus Current Liabilities | B57: 630560000 | C57: 687863000 | D57: 721358000 | I57: ∟ Total Assets minus Current Liabilities | J57: 878300000 | K57: 860300000 | L57: 866600000
A59: Long Term Liabilities | I59: Long Term Liabilities
A60: Long Term Debt | D60: -19049000 | I60: Long Term Debt | J60: -228200000 | K60: -217900000 | L60: -206600000
A61: ∟ Group Loans (long t.) | I61: ∟ Group Loans (long t.)
A62: ∟ Director Loans (long t.) | I62: ∟ Director Loans (long t.)
A63: ∟ Hire Purchase & Lease (LT) | D63: -19049000 | I63: ∟ Hire Purchase & Lease (LT) | K63: -21900000 | L63: -24500000
A64: ∟ Hire Purchase (long t.) | I64: ∟ Hire Purchase (long t.)
A65: ∟ Leasing (long t.) | D65: -19049000 | I65: ∟ Leasing (long t.) | K65: -21900000 | L65: -24500000
A66: ∟ Preference Shares (part of Liabilities) | I66: ∟ Preference Shares (part of Liabilities)
A67: ∟ Other Long Term Loans | I67: ∟ Other Long Term Loans | J67: -228200000 | K67: -196000000 | L67: -182100000
A68: Total Other Long Term Liab. | B68: -40783000 | C68: -37474000 | D68: -108 | I68: Total Other Long Term Liab. | J68: -54800000 | K68: -6800000 | L68: -7300000
A69: ∟ Accruals & Def. Inc. (long t.) | I69: ∟ Accruals & Def. Inc. (long t.)
A70: ∟ Other Long Term Liab. | B70: -40783000 | C70: -37474000 | D70: -108 | I70: ∟ Other Long Term Liab. | J70: -54800000 | K70: -6800000 | L70: -7300000
A71: Provisions for Other Liab. | B71: -3439000 | C71: -6538000 | D71: -8645000 | I71: Provisions for Other Liab. | J71: -44800000 | K71: -61500000 | L71: -72300000
A72: ∟ Deferred Tax | I72: ∟ Deferred Tax | J72: -44400000 | K72: -51200000 | L72: -60300000
A73: ∟ Other Provisions | B73: -3439000 | C73: -6538000 | D73: -8645000 | I73: ∟ Other Provisions | J73: -400000 | K73: -10300000 | L73: -12000000
A74: Pension Liabilities | I74: Pension Liabilities | J74: -6600000 | K74: -6900000 | L74: -8300000
A75: ∟ Long Term Liabilities | B75: -44222000 | C75: -44012000 | D75: -27802000 | I75: ∟ Long Term Liabilities | J75: -334400000 | K75: -293100000 | L75: -294500000
A77: ∟ Net assets | B77: 586338000 | C77: 643851000 | D77: 693556000 | I77: ∟ Net assets | J77: 543900000 | K77: 567200000 | L77: 572100000
A79: Shareholders Funds | I79: Shareholders Funds
A80: Issued Capital | B80: 96 | C80: 86 | D80: 83 | I80: Issued Capital | J80: 6600000 | K80: 6600000 | L80: 6600000
A81: ∟ Ordinary Shares | I81: ∟ Ordinary Shares
A82: ∟ Preference Shares (part of Equity) | I82: ∟ Preference Shares (part of Equity)
A83: ∟ Other Shares | I83: ∟ Other Shares
A84: Total Reserves | B84: 586242000 | C84: 643765000 | D84: 693473000 | I84: Total Reserves | J84: 541600000 | K84: 568300000 | L84: 571900000
A85: ∟ Share Premium Account | B85: 779697000 | C85: 698553000 | D85: 627557000 | I85: ∟ Share Premium Account | J85: 179100000 | K85: 179100000 | L85: 179100000
A86: ∟ Revaluation Reserves | I86: ∟ Revaluation Reserves
A87: ∟ Profit (Loss) Account | B87: -401962000 | C87: -257714000 | D87: -105991000 | I87: ∟ Profit (Loss) Account | J87: 351200000 | K87: 360600000 | L87: 340600000
A88: ∟ Other Reserves | B88: 208507000 | C88: 202926000 | D88: 171907000 | I88: ∟ Other Reserves | J88: 11300000 | K88: 28600000 | L88: 52200000
A89: Balance sheet Minorities | B89: n.a. | C89: n.a. | D89: n.a. | I89: Balance sheet Minorities | J89: -4300000 | K89: -7700000 | L89: -6400000
A90: ∟ Shareholders Funds | B90: 586338000 | C90: 643851000 | D90: 693556000 | I90: ∟ Shareholders Funds | J90: 543900000 | K90: 567200000 | L90: 572100000

Sheet Ret_data
A1: Date | B1: ONT | C1: GNS | D1: FTSE-350-Index
A2: ='My Data'!A3 -> 44564 | B2: 0 | C2: 0 | D2: 0 | F2: Tính bằng cách lấy ln((03/01/2022) / (31/12/2021)) | J2: Formula for Daily returns = Ln (Pt/Pt-1)
A3: ='My Data'!A4 -> 44565 | B3: =LN('My Data'!C4/'My Data'!C3) -> -0.039449966 | C3: =LN('My Data'!D4/'My Data'!D3) -> -0.012635179 | D3: =LN('My Data'!B4/'My Data'!B3) -> 0.016439086
A4: ='My Data'!A5 -> 44566 | B4: =LN('My Data'!C5/'My Data'!C4) -> -0.058298715 | C4: =LN('My Data'!D5/'My Data'!D4) -> -0.012796872 | D4: =LN('My Data'!B5/'My Data'!B4) -> 0.00036980572 | M4: natural log = (current price / previous price)
A5: ='My Data'!A6 -> 44567 | B5: =LN('My Data'!C6/'My Data'!C5) -> -0.045241964 | C5: =LN('My Data'!D6/'My Data'!D5) -> -0.032083799 | D5: =LN('My Data'!B6/'My Data'!B5) -> -0.0099508657
A6: ='My Data'!A7 -> 44568 | B6: =LN('My Data'!C7/'My Data'!C6) -> 0 | C6: =LN('My Data'!D7/'My Data'!D6) -> -0.013388237 | D6: =LN('My Data'!B7/'My Data'!B6) -> 0.0033997529
A7: ='My Data'!A8 -> 44571 | B7: =LN('My Data'!C8/'My Data'!C7) -> -0.068402727 | C7: =LN('My Data'!D8/'My Data'!D7) -> -0.033152207 | D7: =LN('My Data'!B8/'My Data'!B7) -> -0.0070397269
A8: ='My Data'!A9 -> 44572 | B8: =LN('My Data'!C9/'My Data'!C8) -> -0.06206371 | C8: =LN('My Data'!D9/'My Data'!D8) -> -0.0040531467 | D8: =LN('My Data'!B9/'My Data'!B8) -> 0.0053201931
A9: ='My Data'!A10 -> 44573 | B9: =LN('My Data'!C10/'My Data'!C9) -> 0.042402666 | C9: =LN('My Data'!D10/'My Data'!D9) -> -0.010433299 | D9: =LN('My Data'!B10/'My Data'!B9) -> 0.0068022466
A10: ='My Data'!A11 -> 44574 | B10: =LN('My Data'!C11/'My Data'!C10) -> -0.0054298776 | C10: =LN('My Data'!D11/'My Data'!D10) -> -0.045239703 | D10: =LN('My Data'!B11/'My Data'!B10) -> 0.00068676285
A11: ='My Data'!A12 -> 44575 | B11: =LN('My Data'!C12/'My Data'!C11) -> -0.022019238 | C11: =LN('My Data'!D12/'My Data'!D11) -> -0.016839465 | D11: =LN('My Data'!B12/'My Data'!B11) -> -0.0038823319
A12: ='My Data'!A13 -> 44578 | B12: =LN('My Data'!C13/'My Data'!C12) -> 0.016559716 | C12: =LN('My Data'!D13/'My Data'!D12) -> 0.012536326 | D12: =LN('My Data'!B13/'My Data'!B12) -> 0.0084448762
A13: ='My Data'!A14 -> 44579 | B13: =LN('My Data'!C14/'My Data'!C13) -> -0.060168521 | C13: =LN('My Data'!D14/'My Data'!D13) -> -0.014965281 | D13: =LN('My Data'!B14/'My Data'!B13) -> -0.0068388176
A14: ='My Data'!A15 -> 44580 | B14: =LN('My Data'!C15/'My Data'!C14) -> 0.011560822 | C14: =LN('My Data'!D15/'My Data'!D14) -> -0.0048756801 | D14: =LN('My Data'!B15/'My Data'!B14) -> 0.0028904682 | K14: ln(Ngày sau / Ngày trước)
A15: ='My Data'!A16 -> 44581 | B15: =LN('My Data'!C16/'My Data'!C15) -> 0.044951388 | C15: =LN('My Data'!D16/'My Data'!D15) -> -0.016260521 | D15: =LN('My Data'!B16/'My Data'!B15) -> -7.2101826e-05
A16: ='My Data'!A17 -> 44582 | B16: =LN('My Data'!C17/'My Data'!C16) -> -0.0091996969 | C16: =LN('My Data'!D17/'My Data'!D16) -> -0.057246083 | D16: =LN('My Data'!B17/'My Data'!B16) -> -0.013384297
A17: ='My Data'!A18 -> 44585 | B17: =LN('My Data'!C18/'My Data'!C17) -> -0.11963317 | C17: =LN('My Data'!D18/'My Data'!D17) -> -0.044093164 | D17: =LN('My Data'!B18/'My Data'!B17) -> -0.028355706
A18: ='My Data'!A19 -> 44586 | B18: =LN('My Data'!C19/'My Data'!C18) -> -0.0104713 | C18: =LN('My Data'!D19/'My Data'!D18) -> -0.0077263078 | D18: =LN('My Data'!B19/'My Data'!B18) -> 0.009941783
A19: ='My Data'!A20 -> 44587 | B19: =LN('My Data'!C20/'My Data'!C19) -> 0.053291297 | C19: =LN('My Data'!D20/'My Data'!D19) -> 0.026784875 | D19: =LN('My Data'!B20/'My Data'!B19) -> 0.012790147
A20: ='My Data'!A21 -> 44588 | B20: =LN('My Data'!C21/'My Data'!C20) -> -0.051188247 | C20: =LN('My Data'!D21/'My Data'!D20) -> 0.017112717 | D20: =LN('My Data'!B21/'My Data'!B20) -> 0.0092897056
A21: ='My Data'!A22 -> 44589 | B21: =LN('My Data'!C22/'My Data'!C21) -> -0.051735674 | C21: =LN('My Data'!D22/'My Data'!D21) -> -0.016573488 | D21: =LN('My Data'!B22/'My Data'!B21) -> -0.011420759
A22: ='My Data'!A23 -> 44592 | B22: =LN('My Data'!C23/'My Data'!C22) -> 0.070466711 | C22: =LN('My Data'!D23/'My Data'!D22) -> 0.024495367 | D22: =LN('My Data'!B23/'My Data'!B22) -> 0.0019650988
A23: ='My Data'!A24 -> 44593 | B23: =LN('My Data'!C24/'My Data'!C23) -> 0.020408872 | C23: =LN('My Data'!D24/'My Data'!D23) -> 0.007859616 | D23: =LN('My Data'!B24/'My Data'!B23) -> 0.009758592
A24: ='My Data'!A25 -> 44594 | B24: =LN('My Data'!C25/'My Data'!C24) -> 0.029852963 | C24: =LN('My Data'!D25/'My Data'!D24) -> -0.011020841 | D24: =LN('My Data'!B25/'My Data'!B24) -> 0.0058177062
A25: ='My Data'!A26 -> 44595 | B25: =LN('My Data'!C26/'My Data'!C25) -> -0.023810649 | C25: =LN('My Data'!D26/'My Data'!D25) -> -0.050876772 | D25: =LN('My Data'!B26/'My Data'!B25) -> -0.0080931109
A26: ='My Data'!A27 -> 44596 | B26: =LN('My Data'!C27/'My Data'!C26) -> 0.0080000427 | C26: =LN('My Data'!D27/'My Data'!D26) -> 0.010494435 | D26: =LN('My Data'!B27/'My Data'!B26) -> -0.0033118662
... A783: ='My Data'!A784 -> 45657 | B783: =LN('My Data'!C784/'My Data'!C783) -> 0.031498667 | C783: =LN('My Data'!D784/'My Data'!D783) -> 0.01168086 | D783: =LN('My Data'!B784/'My Data'!B783) -> 0.0069388256

Sheet FTSE All-Share Historical 
A1: Date | B1: Price
A2: 43832 | B2: 4285.97
A3: 43833 | B3: 4290.29
A4: 43836 | B4: 4260.71
A5: 43837 | B5: 4262.43
A6: 43838 | B6: 4256.79
A7: 43839 | B7: 4267.27
A8: 43840 | B8: 4259.91
A9: 43843 | B9: 4278.83
A10: 43844 | B10: 4282.37
A11: 43845 | B11: 4290.42
A12: 43846 | B12: 4275.36
A13: 43847 | B13: 4311.06
... A1262: 45656 | B1262: 4479.42

Sheet Mkt_calc
B1: Equity Return and Risk
C2: ONT | D2: FTSE-350-Index | E2: GNS
B3: Average Daily Return | C3: =AVERAGE(Ret_data!B2:B783) -> -0.0021590878 | D3: =AVERAGE(Ret_data!D2:D783) -> 8.2538205e-05 | E3: =AVERAGE(Ret_data!C2:C783) -> -0.0014817205
B4: Volatility (StD) | C4: =STDEV(Ret_data!B2:B783) -> 0.035796841 | D4: =STDEV(Ret_data!D2:D783) -> 0.0079590321 | E4: =STDEV(Ret_data!C2:C783) -> 0.023658622
B5: 3 year return | C5: =C3*252*3 -> -1.6322704 | D5: =D3*252*3 -> 0.062398883 | E5: =E3*252*3 -> -1.1201807
A6: Annual return | B6: 2022 | C6: =AVERAGE(Ret_data!B2:B261)*252 -> -1.0068667 | D6: =AVERAGE(Ret_data!D2:D261)*252 -> -0.026697664 | E6: =AVERAGE(Ret_data!C2:C261)*252 -> -0.48819738
B7: 2023 | C7: =AVERAGE(Ret_data!B262:B521)*252 -> -0.16656256 | D7: =AVERAGE(Ret_data!D262:D521)*252 -> 0.036859854 | E7: =AVERAGE(Ret_data!C262:C521)*252 -> -0.30873636
B8: 2024 | C8: =AVERAGE(Ret_data!B522:B783)*252 -> -0.45949187 | D8: =AVERAGE(Ret_data!D522:D783)*252 -> 0.051996716 | E8: =AVERAGE(Ret_data!C522:C783)*252 -> -0.32362978
A9: Annual volatility | B9: 2022 | C9: =STDEV(Ret_data!B2:B261)*SQRT(252) -> 0.63817623 | D9: =STDEV(Ret_data!D2:D261)*SQRT(252) -> 0.16267515 | E9: =STDEV(Ret_data!C2:C261)*SQRT(252) -> 0.41185255
B10: 2023 | C10: =STDEV(Ret_data!B262:B521)*SQRT(252) -> 0.47956892 | D10: =STDEV(Ret_data!D262:D521)*SQRT(252) -> 0.11455636 | E10: =STDEV(Ret_data!C262:C521)*SQRT(252) -> 0.31637225
B11: 2024 | C11: =STDEV(Ret_data!B522:B783)*SQRT(252) -> 0.57659673 | D11: =STDEV(Ret_data!D522:D783)*SQRT(252) -> 0.092035658 | E11: =STDEV(Ret_data!C522:C783)*SQRT(252) -> 0.39287362
A13: FROM FAME
D14: ONT | E14: GNS
B15: Beta (3Y) | D15: 1.4 | E15: 1.24
B16: PE ratio (TTM) | C16: 2022 | D16: -22.31 | E16: 67.83
C17: 2023 | D17: -11.24 | E17: 54.05
C18: 2024 | D18: -7.91 | E18: 168.09

Sheet Fin_calc
A3: Profitability Ratios: Operating Profit Margin (%) | G3: Efficiency Ratios: Net Asset Turnover | M3: Gearing ratios: Gearing Ratio (%)
B4: Company | C4: Competitor | H4: Company | I4: Competitor | N4: Company | O4: Competitor
A5: 2022 | B5: =('IS data'!D15 / 'IS data'!D5) -> -0.49585857 | C5: =('IS data'!L15 / 'IS data'!L5) -> 0.083249073 | G5: 2022 | H5: ='IS data'!D5 / 'SoFP data'!D57 -> 0.27531822 | I5: ='IS data'!L5 / 'SoFP data'!L57 -> 0.68474498 | M5: 2022 | N5: =ABS('SoFP data'!D75) / (ABS('SoFP data'!D75) + ABS('SoFP data'!D90)) -> 0.038541196 | O5: =ABS('SoFP data'!L75) / (ABS('SoFP data'!L75) + ABS('SoFP data'!L90)) -> 0.33983383
A6: 2023 | B6: =('IS data'!C15 / 'IS data'!C5) -> -0.9937584 | C6: =('IS data'!K15 / 'IS data'!K5) -> 0.058721183 | G6: 2023 | H6: ='IS data'!C5 / 'SoFP data'!C57 -> 0.24665958 | I6: ='IS data'!K5 / 'SoFP data'!K57 -> 0.80169708 | M6: 2023 | N6: =ABS('SoFP data'!C75) / (ABS('SoFP data'!C75) + ABS('SoFP data'!C90)) -> 0.063983671 | O6: =ABS('SoFP data'!K75) / (ABS('SoFP data'!K75) + ABS('SoFP data'!K90)) -> 0.34069511
A7: 2024 | B7: =('IS data'!B15 / 'IS data'!B5) -> -0.83155286 | C7: =('IS data'!J15 / 'IS data'!J5) -> 0.009569378 | G7: 2024 | H7: ='IS data'!B5 / 'SoFP data'!B57 -> 0.29052112 | I7: ='IS data'!J5 / 'SoFP data'!J57 -> 0.76147102 | M7: 2024 | N7: =ABS('SoFP data'!B75) / (ABS('SoFP data'!B75) + ABS('SoFP data'!B90)) -> 0.070131312 | O7: =ABS('SoFP data'!J75) / (ABS('SoFP data'!J75) + ABS('SoFP data'!J90)) -> 0.38073551
A27: Equity Ratios: Return on Shareholder Funds (%) | G27: Liquidity ratios: Current Ratio
B28: Company | C28: Competitor | H28: Company | I28: Competitor
A29: 2022 | B29: =('IS data'!D31 / 'SoFP data'!D90) -> -0.1202657 | C29: =('IS data'!L31 / 'SoFP data'!L90) -> 0.084600594 | G29: 2022 | H29: ='SoFP data'!D33 / ABS('SoFP data'!D51) -> 6.2224476 | I29: ='SoFP data'!L33 / ABS('SoFP data'!L51) -> 1.7019167
A30: 2023 | B30: =('IS data'!C31 / 'SoFP data'!C90) -> -0.23261283 | C30: =('IS data'!K31 / 'SoFP data'!K90) -> 0.069464034 | G30: 2023 | H30: ='SoFP data'!C33 / ABS('SoFP data'!C51) -> 5.0133185 | I30: ='SoFP data'!K33 / ABS('SoFP data'!K51) -> 1.7595109
A31: 2024 | B31: =('IS data'!B31 / 'SoFP data'!B90) -> -0.23870361 | C31: =('IS data'!J31 / 'SoFP data'!J90) -> 0.010112153 | G31: 2024 | H31: ='SoFP data'!B33 / ABS('SoFP data'!B51) -> 4.6649475 | I31: ='SoFP data'!J33 / ABS('SoFP data'!J51) -> 1.8001328

Sheet Custom Data
A4: OXFORD NANOPORE TECHNOLOGIES PLC | H4: GENUS PLC - Competitor
B8: 31/12/2024 | C8: 31/12/2023 | D8: 31/12/2022 | I8: 30/06/2024 | J8: 30/06/2023 | K8: 30/06/2022
B9: GBP | C9: GBP | D9: GBP | I9: GBP | J9: GBP | K9: GBP
A10: Profitability ratios | H10: Profitability ratios
A11: ∟ Return on Shareholders Funds (%) | B11: -23.87 | C11: -23.26 | D11: -12.03 | H11: ∟ Return on Shareholders Funds (%) | I11: 1.01 | J11: 6.95 | K11: 8.46
A12: ∟ Return on Capital Employed (%) | B12: -22.2 | C12: -21.77 | D12: -11.56 | H12: ∟ Return on Capital Employed (%) | I12: 0.63 | J12: 4.58 | K12: 5.59
A13: ∟ Return on Total Assets (%) | B13: -18.86 | C13: -19.27 | D13: -10.12 | H13: ∟ Return on Total Assets (%) | I13: 0.53 | J13: 3.91 | K13: 4.75
A14: ∟ Profit margin (%) | B14: -76.4 | C14: -88.27 | D14: -42 | H14: ∟ Profit margin (%) | I14: 0.82 | J14: 5.71 | K14: 8.16
A15: ∟ Gross margin (%) | B15: 57.53 | C15: 53.33 | D15: 62.34 | H15: ∟ Gross margin (%)
A16: ∟ Berry ratio (x) | B16: 0.41 | C16: 0.35 | D16: 0.56 | H16: ∟ Berry ratio (x)
A17: ∟ EBIT margin (%) | B17: -83.16 | C17: -99.38 | D17: -49.59 | H17: ∟ EBIT margin (%) | I17: 0.96 | J17: 5.87 | K17: 8.32
A18: ∟ EBITDA margin (%) | B18: -59.53 | C18: -74.84 | D18: -33.54 | H18: ∟ EBITDA margin (%) | I18: 8.24 | J18: 12.19 | K18: 15.05
A20: Operational ratios | H20: Operational ratios
A21: ∟ Net Assets Turnover (x) | B21: 0.29 | C21: 0.25 | D21: 0.28 | H21: ∟ Net Assets Turnover (x) | I21: 0.76 | J21: 0.8 | K21: 0.68
A22: ∟ Fixed Assets Turnover (x) | B22: 0.83 | C22: 0.51 | D22: 1.07 | H22: ∟ Fixed Assets Turnover (x) | I22: 0.88 | J22: 0.92 | K22: 0.78
A23: ∟ Interest Cover (x) | B23: -38.26 | C23: -66.89 | D23: -50.24 | H23: ∟ Interest Cover (x) | I23: 1.25 | J23: 3.56 | K23: 8.33
A24: ∟ Stock Turnover (x) | B24: 1.84 | C24: 1.67 | D24: 2.26 | H24: ∟ Stock Turnover (x) | I24: 11.71 | J24: 11.25 | K24: 11.66
A25: ∟ Debtors Turnover (x) | B25: 4.88 | C25: 5.02 | D25: 4.82 | H25: ∟ Debtors Turnover (x) | I25: 5.81 | J25: 6.06 | K25: 5.46
A26: ∟ Debtor Collection (days) | B26: 74.79 | C26: 72.78 | D26: 75.68 | H26: ∟ Debtor Collection (days) | I26: 62.87 | J26: 60.28 | K26: 66.86
A27: ∟ Creditors Payment (days) | B27: 103.54 | C27: 86.78 | D27: 42.46 | H27: ∟ Creditors Payment (days) | I27: 22.98 | J27: 18.42 | K27: 22.14
A29: Structure ratios | H29: Structure ratios
A30: ∟ Current ratio (x) | B30: 4.66 | C30: 5.01 | D30: 6.22 | H30: ∟ Current ratio (x) | I30: 1.8 | J30: 1.76 | K30: 1.7
A31: ∟ Liquidity ratio (x) | B31: 3.77 | C31: 3.87 | D31: 5.37 | H31: ∟ Liquidity ratio (x) | I31: 1.42 | J31: 1.34 | K31: 1.37
A32: ∟ Shareholders liquidity ratio (x) | B32: 13.26 | C32: 14.63 | D32: 24.95 | H32: ∟ Shareholders liquidity ratio (x) | I32: 1.63 | J32: 1.94 | K32: 1.94
A33: ∟ Solvency ratio (Asset based) (%) | B33: 79.02 | C33: 82.86 | D33: 84.18 | H33: ∟ Solvency ratio (Asset based) (%) | I33: 52.86 | J33: 56.3 | K33: 56.2
A34: ∟ Solvency ratio (Liability based) (%) | B34: n.s. | C34: n.s. | D34: n.s. | H34: ∟ Solvency ratio (Liability based) (%) | I34: n.s. | J34: n.s. | K34: n.s.
A35: ∟ Asset Cover (x) | D35: 43.25 | H35: ∟ Asset Cover (x) | I35: 4.51 | J35: 4.62 | K35: 4.93
A36: ∟ Gearing (%) | B36: 7.54 | C36: 6.84 | D36: 6.32 | H36: ∟ Gearing (%) | I36: 62.38 | J36: 54.18 | K36: 54.48
A38: Per employee ratios | H38: Per employee ratios
A39: ∟ Profit per employee (unit) | B39: -106434 | C39: -132187 | D39: -90467 | H39: ∟ Profit per employee (unit) | I39: 1536 | J39: 10860 | K39: 13868
A40: ∟ Turnover per employee (unit) | B40: 139309 | C40: 149751 | D40: 215405 | H40: ∟ Turnover per employee (unit) | I40: 186763 | J40: 190105 | K40: 170029
A41: ∟ Salaries/Turnover | B41: 82.34 | C41: 89.31 | D41: 72.55 | H41: ∟ Salaries/Turnover | I41: 35.2 | J41: 33.3 | K41: 33.23
A42: ∟ Average Remuneration per employee (unit) | B42: 114710 | C42: 133738 | D42: 156278 | H42: ∟ Average Remuneration per employee (unit) | I42: 65736 | J42: 63313 | K42: 56504
A43: ∟ Shareholders Funds per employee (unit) | B43: n.s. | C43: n.s. | D43: n.s. | H43: ∟ Shareholders Funds per employee (unit) | I43: 151885 | J43: 156340 | K43: 163926
A44: ∟ Working Capital per employee (unit) | B44: 64657 | C44: 83882 | D44: 114725 | H44: ∟ Working Capital per employee (unit) | I44: 36359 | J44: 38699 | K44: 35415
A45: ∟ Total Assets per employee (unit) | B45: 564297 | C45: 685845 | D45: 893590 | H45: ∟ Total Assets per employee (unit) | I45: 287322 | J45: 277701 | K45: 291662

Sheet Report
A1: Code | B1: ONT
A2: Name | B2: OXFORD NANOPORE TECHNOLOGIES PLC
A3: Sector | B3: Biotechnology and Life Sciences
A6: Table 1 | B6: Key ratios of Oxford Nanopore Technologies
B7: Ratios | C7: 2022 | D7: 2023 | E7: 2024
B8: Operating Profit Margin (%) | C8: -0.4959 | D8: -0.9938 | E8: -0.8316
B9: Return on Shareholder Funds (%) | C9: -0.1203 | D9: -0.2326 | E9: -0.2387
B10: Net Assest Turnover | C10: 0.28 | D10: 0.25 | E10: 0.29
B11: Gearing Ratio | C11: 0.0418 | D11: 0.0734 | E11: 0.0816
B12: Current Ratio | C12: 6.22 | D12: 5.01 | E12: 4.66
A15: Table 2 | B15: Key Market Coefficients and Performance Metrics for ONT Shares
B16: Market CoEfficient | C16: 2022 | D16: 2023 | E16: 2024
B17: Annual Return (%) | C17: -1.0069 | D17: -0.1666 | E17: -0.4595
B18: Annual Volatility (%) | C18: 0.6382 | D18: 0.4796 | E18: 0.5766
B19: P/E Ratio | C19: -22.31 | D19: -11.24 | E19: -7.91
A22: Chart 1 | B22: Operating Profit Margin between ONT and GNS
A43: Chart 2 | B43: Current Ratio between ONT and GNS
A64: Chart 3 | B64: Gearing Ratio between ONT and GNS
A85: Chart 4 | B85: Return on Shareholder Funds between ONT and GNS
A108: Chart 5 | B108: Comparative Annual Returns Trend: ONT, GNS, and FTSE-350
A128: Chart 6 | B128: Comparative Annual Volatility Trend: ONT, GNS, and FTSE-350

Sheet IS Raw Data
B1: 31/12/2024 GBP | C1: 31/12/2023 GBP | D1: 31/12/2022 GBP
A2: Original documents | B2: 2024 12 months Cons. Unqualified IFRS | C2: 2023 12 months Cons. Unqualified IFRS | D2: 2022 12 months Cons. Unqualified IFRS
A3: ∟ Turnover | B3: 183,191,000 | C3: 169,668,000 | D3: 198,603,000
A4: ∟ National Turnover | B4: 21,126,000 | D4: 198,603,000
A5: ∟ Overseas Turnover | B5: 162,065,000
A6: ∟ Cost of Sales | B6: -77,796,000 | C6: -79,187,000 | D6: -74,793,000
A7: ∟ Exceptional Items pre GP
A8: ∟ Other Income pre GP
A9: ∟ Gross Profit | B9: 105,395,000 | C9: 90,481,000 | D9: 123,810,000
A10: ∟ Administration Expenses | B10: -257,728,000 | C10: -259,090,000 | D10: -222,289,000
A11: ∟ Other Operating Income/Costs pre OP
A12: ∟ Exceptional Items pre OP
A13: ∟ Operating Profit | B13: -152,333,000 | C13: -168,609,000 | D13: -98,479,000
A14: ∟ Other Income | B14: 1,096,000 | C14: 2,194,000 | D14: 10,755,000
A15: ∟ Total Other Income & Int. Received | B15: 15,937,000 | C15: 21,047,000 | D15: 16,696,000
A16: ∟ Exceptional Items
A17: ∟ Profit (Loss) on Sale of Operations
A18: ∟ Costs of Reorganisation
A19: ∟ Profit (Loss) on Disposal
A20: ∟ Other Exceptional Items
A21: ∟ Profit (Loss) before Interest paid | B21: -136,396,000 | C21: -147,562,000 | D21: -81,783,000
A22: ∟ Interest Received | B22: 14,841,000 | C22: 18,853,000 | D22: 5,941,000
A23: ∟ Interest Paid | B23: -3,565,000 | C23: -2,206,000 | D23: -1,628,000
A24: ∟ Paid to Bank | B24: -3 | C24: -1 | D24: -221
A25: ∟ Paid on Hire Purchase
A26: ∟ Paid on Leasing | B26: -3,562,000 | C26: -2,205,000 | D26: -1,407,000
A27: ∟ Other Interest Paid
A28: ∟ Net Interest | B28: 11,276,000 | C28: 16,647,000 | D28: 4,313,000
A29: ∟ Profit (Loss) before Tax | B29: -139,961,000 | C29: -149,768,000 | D29: -83,411,000
A30: ∟ Taxation | B30: -6,227,000 | C30: -4,739,000 | D30: -7,614,000
A31: ∟ Profit (Loss) after Tax | B31: -146,188,000 | C31: -154,507,000 | D31: -91,025,000
A32: ∟ Extraordinary Items
A33: ∟ Minority Interests
A34: ∟ Profit (Loss) for period [=Net income] | B34: -146,188,000 | C34: -154,507,000 | D34: -91,025,000
A35: ∟ Dividends (Distributable profit)
A36: ∟ Retained Profit(Loss) | B36: -146,188,000 | C36: -154,507,000 | D36: -91,025,000
A38: ∟ Depreciation | B38: 13,449,000 | C38: 18,105,000 | D38: 20,443,000
A39: ∟ Depreciation Owned Assets | B39: 12,068,000 | C39: 16,496,000 | D39: 15,968,000
A40: ∟ Depreciation Other Assets | B40: 1,381,000 | C40: 1,609,000 | D40: 4,475,000
A41: ∟ Impairment of Tangible Assets
A42: ∟ Audit Fee | B42: 564 | C42: 570 | D42: 594
A43: ∟ Audit Non-fee expenses | B43: 83 | C43: 90 | D43: 89
A44: ∟ Tax Advice
A45: ∟ Non-Tax Advisory Services | B45: 83 | C45: 90 | D45: 89
A46: ∟ Other Auditors Services
A47: ∟ Non-Audit Fees paid to Other Auditors
A48: ∟ Total Amortization and Impairment | B48: 29,835,000 | C48: 23,522,000 | D48: 11,428,000
A49: ∟ Amortisation | B49: 29,835,000 | C49: 23,522,000 | D49: 11,428,000
A50: ∟ Impairment
A51: ∟ Total Operating Lease Rentals | B51: 971 | C51: 928 | D51: 602
A52: ∟ Hire of Plant & Machinery | D52: 602
A53: ∟ Land & Building or Property Rents & Other
A54: ∟ Research & Development | B54: 98,921,000 | C54: 35,671,000
A55: ∟ Foreign Exchange Gains/Losses | B55: 504 | C55: 1,385,000 | D55: 2,490,000
A56: ∟ Remuneration | B56: 150,844,000 | C56: 151,525,000 | D56: 144,088,000
A57: ∟ Wages & Salaries | B57: 124,388,000 | C57: 99,111,000 | D57: 81,613,000
A58: ∟ Social Security Costs | B58: 11,009,000 | C58: 10,193,000 | D58: -12,551,000
A59: ∟ Pension Costs | B59: 4,911,000 | C59: 4,113,000 | D59: 3,183,000
A60: ∟ Other Staff Costs | B60: 10,536,000 | C60: 38,108,000 | D60: 71,843,000
A61: ∟ Directors' Remuneration | B61: 4,351,000 | C61: 4,870,000 | D61: 87,028,000
A62: ∟ Directors' Fees | B62: 1,873,000 | C62: 2,662,000 | D62: 3,423,000
A63: ∟ Pension Contribution | B63: 102 | C63: 135 | D63: 128
A64: ∟ Other Emoluments | B64: 2,376,000 | C64: 2,073,000 | D64: 83,477,000
A65: ∟ Highest Paid Director | B65: 1,819,000 | C65: 1,351,000 | D65: 29,212,000
A66: ∟ EBITDA | B66: -109,049,000 | C66: -126,982,000 | D66: -66,608,000
A67: ∟ Number of employees | B67: 1.315 | C67: 1.133 | D67: 922
B69: 31/12/2024 GBP | C69: 31/12/2023 GBP | D69: 31/12/2022 GBP
A70: Original documents | B70: 2024 12 months Cons. Unqualified IFRS | C70: 2023 12 months Cons. Unqualified IFRS | D70: 2022 12 months Cons. Unqualified IFRS
A71: © 2025 Moody’s Analytics, Inc. and/or their licensors and affiliates. All rights reserved.

Sheet SoFP Raw Data
B1: 31/12/2024 GBP | C1: 31/12/2023 GBP | D1: 31/12/2022 GBP
A2: Original documents | B2: 2024 12 months Cons. Unqualified IFRS | C2: 2023 12 months Cons. Unqualified IFRS | D2: 2022 12 months Cons. Unqualified IFRS
A3: Fixed Assets
A4: Tangible Assets | B4: 66,331,000 | C4: 49,890,000 | D4: 63,200,000
A5: ∟ Land & Buildings | B5: 4,572,000 | C5: 5,524,000 | D5: 5,885,000
A6: ∟ Freehold Land
A7: ∟ Leasehold Land | B7: 4,572,000 | C7: 5,524,000 | D7: 5,885,000
A8: ∟ Fixtures & Fittings
A9: ∟ Plant & Vehicles | B9: 16,579,000 | C9: 10,463,000 | D9: 8,283,000
A10: ∟ Plant | B10: 16,579,000 | C10: 10,463,000 | D10: 8,283,000
A11: ∟ Vehicles
A12: ∟ Other Fixed Assets | B12: 45,180,000 | C12: 33,903,000 | D12: 49,032,000
A13: Intangible Assets | B13: 78,674,000 | C13: 65,436,000 | D13: 30,039,000
A14: Investments & other fixed assets | B14: 76,950,000 | C14: 214,553,000 | D14: 92,651,000
A15: ∟ Fixed Assets | B15: 221,955,000 | C15: 329,879,000 | D15: 185,890,000
A17: Current Assets
A18: Stock & W.I.P. | B18: 99,453,000 | C18: 101,548,000 | D18: 87,698,000
A19: ∟ Stock | B19: 37,631,000 | C19: 50,888,000 | D19: 41,852,000
A20: ∟ W.I.P. | B20: 45,637,000 | C20: 39,154,000 | D20: 34,960,000
A21: ∟ Finished Goods | B21: 16,185,000 | C21: 11,506,000 | D21: 10,886,000
A22: Trade Debtors | B22: 37,537,000 | C22: 33,830,000 | D22: 41,181,000
A23: Bank & Deposits | B23: 199,517,000 | C23: 220,536,000 | D23: 356,778,000
A24: Other Current Assets | B24: 44,735,000 | C24: 41,494,000 | D24: 30,872,000
A25: ∟ Group Loans (asset)
A26: ∟ Directors Loans (asset)
A27: ∟ Other Debtors | B27: 11,652,000 | C27: 14,101,000 | D27: 9,986,000
A28: ∟ Prepayments | B28: 13,519,000 | C28: 13,544,000 | D28: 11,738,000
A29: ∟ Deferred Taxation | B29: 19,564,000 | C29: 13,849,000 | D29: 9,148,000
A30: Investments & other current assets | B30: 138,853,000 | C30: 49,775,000 | D30: 121,471,000
A31: ∟ Current Assets | B31: 520,095,000 | C31: 447,183,000 | D31: 638,000,000
A33: Current Liabilities
A34: Trade Creditors | B34: -51,966,000 | C34: -40,340,000 | D34: -23,103,000
A35: Short Term Loans & Overdrafts | D35: -16,011,000
A36: ∟ Bank Overdrafts
A37: ∟ Group Loans (short t.)
A38: ∟ Director Loans (short t.)
A39: ∟ Hire Purch. & Leas. (short t.) | D39: -15,049,000
A40: ∟ Hire Purchase (short t.)
A41: ∟ Leasing (short t.) | D41: -15,049,000
A42: ∟ Other Short Term Loans | D42: -962
A43: Total Other Current Liabilities | B43: -59,524,000 | C43: -48,859,000 | D43: -63,418,000
A44: ∟ Corporation Tax | D44: -1,639,000
A45: ∟ Dividends payable
A46: ∟ Accruals & Def. Inc. (short t.) | B46: -45,707,000 | C46: -33,096,000 | D46: -33,801,000
A47: ∟ Social Securities & V.A.T. | B47: -4,474,000 | C47: -4,507,000 | D47: -2,585,000
A48: ∟ Other Current Liabilities | B48: -9,343,000 | C48: -11,256,000 | D48: -25,393,000
A49: ∟ Current Liabilities | B49: -111,490,000 | C49: -89,199,000 | D49: -102,532,000
A51: ∟ Net Current Assets | B51: 408,605,000 | C51: 357,984,000 | D51: 535,468,000
A52: ∟ Net Tangible Assets | B52: 551,886,000 | C52: 622,427,000 | D52: 691,319,000
A53: ∟ Working Capital | B53: 85,024,000 | C53: 95,038,000 | D53: 105,776,000
A54: ∟ Total Assets | B54: 742,050,000 | C54: 777,062,000 | D54: 823,890,000
A55: ∟ Total Assets minus Current Liabilities | B55: 630,560,000 | C55: 687,863,000 | D55: 721,358,000
A57: Long Term Liabilities
A58: Long Term Debt | D58: -19,049,000
A59: ∟ Group Loans (long t.)
A60: ∟ Director Loans (long t.)
A61: ∟ Hire Purchase & Lease (LT) | D61: -19,049,000
A62: ∟ Hire Purchase (long t.)
A63: ∟ Leasing (long t.) | D63: -19,049,000
A64: ∟ Preference Shares (part of Liabilities)
A65: ∟ Other Long Term Loans
A66: Total Other Long Term Liab. | B66: -40,783,000 | C66: -37,474,000 | D66: -108
A67: ∟ Accruals & Def. Inc. (long t.)
A68: ∟ Other Long Term Liab. | B68: -40,783,000 | C68: -37,474,000 | D68: -108
A69: Provisions for Other Liab. | B69: -3,439,000 | C69: -6,538,000 | D69: -8,645,000
A70: ∟ Deferred Tax
A71: ∟ Other Provisions | B71: -3,439,000 | C71: -6,538,000 | D71: -8,645,000
A72: Pension Liabilities
A73: ∟ Long Term Liabilities | B73: -44,222,000 | C73: -44,012,000 | D73: -27,802,000
A75: ∟ Net assets | B75: 586,338,000 | C75: 643,851,000 | D75: 693,556,000
A77: Shareholders Funds
A78: Issued Capital | B78: 96 | C78: 86 | D78: 83
A79: ∟ Ordinary Shares
A80: ∟ Preference Shares (part of Equity)
A81: ∟ Other Shares
A82: Total Reserves | B82: 586,242,000 | C82: 643,765,000 | D82: 693,473,000
A83: ∟ Share Premium Account | B83: 779,697,000 | C83: 698,553,000 | D83: 627,557,000
A84: ∟ Revaluation Reserves
A85: ∟ Profit (Loss) Account | B85: -401,962,000 | C85: -257,714,000 | D85: -105,991,000
A86: ∟ Other Reserves | B86: 208,507,000 | C86: 202,926,000 | D86: 171,907,000
A87: Balance sheet Minorities | B87: n.a. | C87: n.a. | D87: n.a.
A88: ∟ Shareholders Funds | B88: 586,338,000 | C88: 643,851,000 | D88: 693,556,000
A90: Balance sheetShareholders Funds
B91: 31/12/2024 GBP | C91: 31/12/2023 GBP | D91: 31/12/2022 GBP
A92: Original documents | B92: 2024 12 months Cons. Unqualified IFRS | C92: 2023 12 months Cons. Unqualified IFRS | D92: 2022 12 months Cons. Unqualified IFRS
A93: © 2025 Moody’s Analytics, Inc. and/or their licensors and affiliates. All rights reserved.

Sheet Closing Price Raw Data
A1: 45657 | B1: 1.29 | E1: 1.29
A2: 45656 | B2: 1.25 | E2: 1.25
A3: 45653 | B3: 1.27 | E3: 1.27
A4: 45650 | B4: 1.35 | E4: 1.35
A5: 45649 | B5: 1.29 | E5: 1.29
A6: 45646 | B6: 1.43 | E6: 1.43
A7: 45645 | B7: 1.38 | E7: 1.38
A8: 45644 | B8: 1.43 | E8: 1.43
A9: 45643 | B9: 1.53 | E9: 1.53
A10: 45642 | B10: 1.57 | E10: 1.57
A11: 45639 | B11: 1.55 | E11: 1.55
A12: 45638 | B12: 1.55 | E12: 1.55
... A114: 45495 | B114: 1.20 | E114: 1.20
A115: 45492 | B115: 45839 | E115: 45839
A116: 45491 | B116: 45962 | E116: 45962
A117: 45490 | B117: 45931 | E117: 45931
A118: 45489 | B118: 45778 | E118: 45778
A119: 45488 | B119: 45778 | E119: 45778
A120: 45485 | B120: 45778 | E120: 45778
A121: 45484 | B121: 45809 | E121: 45809
A122: 45483 | B122: 45778 | E122: 45778
A123: 45482 | B123: 45658 | E123: 45658
A124: 45481 | B124: 45748 | E124: 45748
A125: 45478 | B125: 45778 | E125: 45778
A126: 45477 | B126: 45778 | E126: 45778
A127: 45476 | B127: 45689 | E127: 45689
A128: 45475 | B128: 0.99 | E128: 0.99
A129: 45474 | B129: 0.98 | E129: 0.98
A130: 45471 | B130: 0.94 | E130: 0.94
A131: 45470 | B131: 0.98 | E131: 0.98
A132: 45469 | B132: 0.90 | E132: 0.90
A133: 45468 | B133: 0.87 | E133: 0.87
A134: 45467 | B134: 0.87 | E134: 0.87
A135: 45464 | B135: 0.92 | E135: 0.92
A136: 45463 | B136: 0.97 | E136: 0.97
A137: 45462 | B137: 0.97 | E137: 0.97
A138: 45461 | B138: 0.97 | E138: 0.97
A139: 45460 | B139: 0.97 | E139: 0.97
... A141: 45456 | B141: 0.98 | E141: 0.98
A142: 45455 | B142: 45717 | E142: 45717
A143: 45454 | B143: 45717 | E143: 45717
A144: 45453 | B144: 45689 | E144: 45689
A145: 45450 | B145: 45689 | E145: 45689
A146: 45449 | B146: 45717 | E146: 45717
A147: 45448 | B147: 45717 | E147: 45717
A148: 45447 | B148: 45748 | E148: 45748
A149: 45446 | B149: 45809 | E149: 45809
A150: 45443 | B150: 45839 | E150: 45839
A151: 45442 | B151: 45778 | E151: 45778
A152: 45441 | B152: 45778 | E152: 45778
A153: 45440 | B153: 45931 | E153: 45931
... A160: 45428 | B160: 45992 | E160: 45992
A161: 45427 | B161: 1.14 | E161: 1.14
A162: 45426 | B162: 45962 | E162: 45962
A163: 45425 | B163: 45931 | E163: 45931
A164: 45422 | B164: 1.14 | E164: 1.14
A165: 45421 | B165: 1.13 | E165: 1.13
A166: 45420 | B166: 1.15 | E166: 1.15
A167: 45419 | B167: 45962 | E167: 45962
A168: 45415 | B168: 45931 | E168: 45931
A169: 45414 | B169: 45809 | E169: 45809
A170: 45413 | B170: 45658 | E170: 45658
A171: 45412 | B171: 0.98 | E171: 0.98
A172: 45411 | B172: 45748 | E172: 45748
A173: 45408 | B173: 0.97 | E173: 0.97
A174: 45407 | B174: 0.93 | E174: 0.93
A175: 45406 | B175: 45717 | E175: 45717
A176: 45405 | B176: 45717 | E176: 45717
A177: 45404 | B177: 0.96 | E177: 0.96
A178: 45401 | B178: 0.93 | E178: 0.93
A179: 45400 | B179: 0.95 | E179: 0.95
A180: 45399 | B180: 0.99 | E180: 0.99
A181: 45398 | B181: 1.00 | E181: 1.00
A182: 45397 | B182: 45839 | E182: 45839
A183: 45394 | B183: 45839 | E183: 45839
A184: 45393 | B184: 45901 | E184: 45901
A185: 45392 | B185: 45992 | E185: 45992
A186: 45391 | B186: 1.15 | E186: 1.15
A187: 45390 | B187: 45992 | E187: 45992
A188: 45387 | B188: 1.13 | E188: 1.13
A189: 45386 | B189: 1.17 | E189: 1.17
A190: 45385 | B190: 1.16 | E190: 1.16
A191: 45384 | B191: 1.17 | E191: 1.17
A192: 45379 | B192: 1.22 | E192: 1.22
A193: 45378 | B193: 1.27 | E193: 1.27
A194: 45377 | B194: 1.24 | E194: 1.24
A195: 45376 | B195: 1.23 | E195: 1.23
A196: 45373 | B196: 1.29 | E196: 1.29
A197: 45372 | B197: 1.33 | E197: 1.33
A198: 45371 | B198: 1.37 | E198: 1.37
A199: 45370 | B199: 1.36 | E199: 1.36
... A249: 45300 | B249: 1.75 | E249: 1.75
A250: 45299 | B250: 45690 | E250: 45690
A251: 45296 | B251: 1.95 | E251: 1.95
A252: 45295 | B252: 1.95 | E252: 1.95
A253: 45294 | B253: 1.92 | E253: 1.92
A254: 45293 | B254: 2.00 | E254: 2.00
A255: 45289 | B255: 45871 | E255: 45871
A256: 45288 | B256: 45810 | E256: 45810
A257: 45287 | B257: 45810 | E257: 45810
...

Sheet All stock Data
C1: XLON:FSTA | D1: XLON:GFRD | E1: XLON:HFD | F1: XLON:BOOT | G1: XLON:HSW | H1: XLON:KMR | I1: XLON:MARS | J1: XLON:MOTR | K1: XLON:NXR | L1: XLON:OTB | M1: XLON:OXB | N1: XLON:MAB | O1: XLON:YNGA | P1: XLON:MGNS | Q1: XLON:KIE | R1: XLON:COST | S1: XLON:VTU | T1: XLON:VCP | U1: XLON:JHD | V1: XLON:WJG | W1: XLON:RIO | X1: XLON:AAL | Y1: XLON:CAML | Z1: XLON:JDW | AA1: XLON:CKN | AB1: XLON:BAB | AC1: XLON:OCN | AD1: XLON:FERG | AE1: XLON:JET2 | AF1: XLON:HIK | AG1: XLON:SNG
A2: Date | C2: Close | D2: Close | E2: Close | F2: Close | G2: Close | H2: Close | I2: Close | J2: Close | K2: Close | L2: Close | M2: Close | N2: Close | O2: Close | P2: Close | Q2: Close | R2: Close | S2: Close | T2: Close | U2: Close | V2: Close | W2: Close | X2: Close | Y2: Close | Z2: Close | AA2: Close | AB2: Close | AC2: Close | AD2: Close | AE2: Close | AF2: Close | AG2: Close
A3: 43832 | B3: =VLOOKUP(A3,'FTSE All-Share Historical '!A:B,2,FALSE) -> 4285.97 | C3: 960 | D3: 886 | E3: 170.3 | F3: 330 | G3: 128.8 | H3: 239 | I3: 129.6 | J3: 289 | K3: 278 | L3: 489.2 | M3: 673 | N3: 456.5 | O3: 1627.5 | P3: 1620 | Q3: 94.75 | R3: 165 | S3: 38.3 | T3: 432.5 | U3: 270.5 | V3: 244 | W3: 4526.5 | X3: 2193.1259 | Y3: 223 | Z3: 1678 | AA3: 3030 | AB3: 631 | AC3: 990 | AD3: 6978 | AE3: 1723 | AF3: 1985 | AG3: 4.2439
A4: 43833 | B4: =VLOOKUP(A4,'FTSE All-Share Historical '!A:B,2,FALSE) -> 4290.29 | C4: 940 | D4: 165.86 | E4: 167.8 | F4: 322 | G4: 128.8 | H4: 239 | I4: 128.2 | J4: 294 | K4: 276 | L4: 490 | M4: 670 | N4: 456.5 | O4: 1650 | P4: 1610 | Q4: 91.7 | R4: 166.6 | S4: 37 | T4: 434 | U4: 266 | V4: 246 | W4: 4504 | X4: 2177.6884 | Y4: 221 | Z4: 1676 | AA4: 2995 | AB4: 613 | AC4: 990 | AD4: 7006 | AE4: 1675 | AF4: 1986 | AG4: 4.6051
A5: 43836 | B5: =VLOOKUP(A5,'FTSE All-Share Historical '!A:B,2,FALSE) -> 4260.71 | C5: 950 | D5: 163 | E5: 162.3 | F5: 330 | G5: 127.8 | H5: 241 | I5: 125.7 | J5: 290 | K5: 280 | L5: 478 | M5: 675 | N5: 443 | O5: 1660 | P5: 1580 | Q5: 90.5 | R5: 164.2 | S5: 36.4 | T5: 432.5 | U5: 269 | V5: 244 | W5: 4430 | X5: 2136.3557 | Y5: 216 | Z5: 1644 | AA5: 2935 | AB5: 628.4 | AC5: 995 | AD5: 6906 | AE5: 1674 | AF5: 1912 | AG5: 4.4245
A6: 43837 | B6: =VLOOKUP(A6,'FTSE All-Share Historical '!A:B,2,FALSE) -> 4262.43 | C6: 966 | D6: 136.42 | E6: 159.9 | F6: 330 | G6: 130.4 | H6: 245 | I6: 125 | J6: 288 | K6: 280 | L6: 481.8 | M6: 670 | N6: 439.5 | O6: 1637.5 | P6: 1616 | Q6: 89.5 | R6: 167 | S6: 37.1 | T6: 435 | U6: 273 | V6: 244 | W6: 4440 | X6: 2151.2952 | Y6: 215.5 | Z6: 1626 | AA6: 2955 | AB6: 646.6 | AC6: 995 | AD6: 6948 | AE6: 1670 | AF6: 1882.5 | AG6: 4.3703
A7: 43838 | B7: =VLOOKUP(A7,'FTSE All-Share Historical '!A:B,2,FALSE) -> 4256.79 | C7: 958 | D7: 144.08 | E7: 158 | F7: 320 | G7: 130 | H7: 240.5 | I7: 122.7 | J7: 290 | K7: 280 | L7: 468.4 | M7: 665 | N7: 421.5 | O7: 1605 | P7: 1640 | Q7: 87.05 | R7: 166.6 | S7: 36.9 | T7: 438 | U7: 268 | V7: 242.5 | W7: 4500 | X7: 2144.3234 | Y7: 217 | Z7: 1625 | AA7: 2945 | AB7: 641 | AC7: 990 | AD7: 6980 | AE7: 1675 | AF7: 1874.5 | AG7: 4.6954
A8: 43839 | B8: =VLOOKUP(A8,'FTSE All-Share Historical '!A:B,2,FALSE) -> 4267.27 | C8: 956 | D8: 151.5 | E8: 154.1 | F8: 315 | G8: 133 | H8: 235 | I8: 123.1 | J8: 278 | K8: 283.5 | L8: 461 | M8: 675 | N8: 433 | O8: 1650 | P8: 1652 | Q8: 83.1 | R8: 162.6 | S8: 37.35 | T8: 437.5 | U8: 270 | V8: 242 | W8: 4451 | X8: 2135.3597 | Y8: 224.5 | Z8: 1622 | AA8: 2925 | AB8: 643.2 | AC8: 980 | AD8: 7146 | AE8: 1705 | AF8: 1902 | AG8: 4.6051
A9: 43840 | B9: =VLOOKUP(A9,'FTSE All-Share Historical '!A:B,2,FALSE) -> 4259.91 | C9: 962 | D9: 158.4 | E9: 142 | F9: 313 | G9: 136 | H9: 233 | I9: 121.2 | J9: 277 | K9: 283 | L9: 461 | M9: 690 | N9: 433 | O9: 1630 | P9: 1664 | Q9: 82.5 | R9: 166 | S9: 37.25 | T9: 432 | U9: 270 | V9: 242 | W9: 4488 | X9: 2156.2751 | Y9: 222 | Z9: 1605 | AA9: 2925 | AB9: 636 | AC9: 980 | AD9: 7078 | AE9: 1817 | AF9: 1906.5 | AG9: 4.4606
A10: 43843 | B10: =VLOOKUP(A10,'FTSE All-Share Historical '!A:B,2,FALSE) -> 4278.83 | C10: 978 | D10: 157.7 | E10: 146 | F10: 313 | G10: 144 | H10: 240 | I10: 118.4 | J10: 286 | K10: 289 | L10: 464 | M10: 700 | N10: 420.5 | O10: 1622.5 | P10: 1648 | Q10: 83.8 | R10: 168.6 | S10: 37 | T10: 440 | U10: 278 | V10: 241.5 | W10: 4555 | X10: 2176.6924 | Y10: 228 | Z10: 1600 | AA10: 2925 | AB10: 638.4 | AC10: 975 | AD10: 7166 | AE10: 1806 | AF10: 1928 | AG10: 4.4606
A11: 43844 | B11: =VLOOKUP(A11,'FTSE All-Share Historical '!A:B,2,FALSE) -> 4282.37 | C11: 961 | D11: 158.26 | E11: 146 | F11: 325 | G11: 143.6 | H11: 235 | I11: 120.8 | J11: 295 | K11: 290 | L11: 450.2 | M11: 695 | N11: 425 | O11: 1620 | P11: 1646 | Q11: 81.95 | R11: 170.2 | S11: 36.7 | T11: 440 | U11: 275 | V11: 248 | W11: 4545 | X11: 2163.7448 | Y11: 230 | Z11: 1599 | AA11: 2905 | AB11: 632.6 | AC11: 980 | AD11: 7216 | AE11: 1803 | AF11: 1944.5 | AG11: 4.9121
A12: 43845 | B12: =VLOOKUP(A12,'FTSE All-Share Historical '!A:B,2,FALSE) -> 4290.42 | C12: 970 | D12: 151.86 | E12: 145.5 | F12: 335 | G12: 149.8 | H12: 236 | I12: 122.3 | J12: 294 | K12: 285 | L12: 457 | M12: 700 | N12: 417 | O12: 1610 | P12: 1680 | Q12: 77.5 | R12: 165.2 | S12: 36.1 | T12: 437.5 | U12: 281 | V12: 248.5 | W12: 4523 | X12: 2152.7892 | Y12: 228 | Z12: 1600 | AA12: 2950 | AB12: 618.8 | AC12: 1000 | AD12: 7176 | AE12: 1820 | AF12: 1975 | AG12: 5.0927
A13: 43846 | B13: =VLOOKUP(A13,'FTSE All-Share Historical '!A:B,2,FALSE) -> 4275.36 | C13: 970 | D13: 145.98 | E13: 153.5 | F13: 328 | G13: 149.4 | H13: 235 | I13: 123.4 | J13: 300 | K13: 281 | L13: 455.8 | M13: 671 | N13: 412.5 | O13: 1630 | P13: 1716 | Q13: 78 | R13: 170.4 | S13: 36.8 | T13: 437.5 | U13: 281 | V13: 250 | W13: 4526.5 | X13: 2166.7327 | Y13: 220.5 | Z13: 1600 | AA13: 3010 | AB13: 609.8 | AC13: 1025 | AD13: 7170 | AE13: 1777 | AF13: 1910.5 | AG13: 5.9596
A14: 43847 | B14: =VLOOKUP(A14,'FTSE All-Share Historical '!A:B,2,FALSE) -> 4311.06 | C14: 970 | D14: 142.88 | E14: 152 | F14: 342 | G14: 153.2 | H14: 237 | I14: 121.3 | J14: 304 | K14: 290 | L14: 437 | M14: 679 | N14: 411 | O14: 1625 | P14: 1696 | Q14: 78.4 | R14: 175.6 | S14: 38.15 | T14: 440 | U14: 279 | V14: 255 | W14: 4651 | X14: 2236.4506 | Y14: 224.5 | Z14: 1623 | AA14: 3075 | AB14: 620.2 | AC14: 1025 | AD14: 7176 | AE14: 1792 | AF14: 1955.5 | AG14: 5.779
... A357: 44343 | B357: =VLOOKUP(A357,'FTSE All-Share Historical '!A:B,2,FALSE) -> 4030.8 | C357: 884 | D357: 129.3 | E357: 385.2 | F357: 283 | G357: 100.8 | H357: 441 | I357: 93.7 | J357: 280 | K357: 297 | L357: 419.5 | M357: 1152 | N357: 316.2 | O357: 1630 | P357: 2275 | Q357: 116.6 | R357: 58.6 | S357: 43 | T357: 1010 | U357: 245 | V357: 238.5 | W357: 6074 | X357: 3124.8559 | Y357: 274 | Z357: 1354 | AA357: 3075 | AB357: 305 | AC357: 1065 | AD357: 9624 | AE357: 1345.5 | AF357: 2454 | AG357: 106.0439
A358: 44344 | B358: =VLOOKUP(A358,'FTSE All-Share Historical '!A:B,2,FALSE) -> 4032.98 | C358: 842 | D358: 125.8 | E358: 381.4 | F358: #N/A | G358: 97.2 | H358: 431 | I358: 91.35 | J358: 268 | K358: 305 | L358: 408 | M358: 1140 | N358: 305 | O358: 1610 | P358: 2235 | Q358: 115 | R358: 58.1 | S358: 43.5 | T358: 1005 | U358: 250 | V358: 225 | W358: 6064 | X358: 3122.366 | Y358: 272 | Z358: 1317 | AA358: 3080 | AB358: 299.1 | AC358: 1080 | AD358: 9584 | AE358: 1350 | AF358: 2444 | AG358: 117.7463
A359: 44348 | B359: =VLOOKUP(A359,'FTSE All-Share Historical '!A:B,2,FALSE) -> 4066.34 | C359: 924 | D359: 125.4 | E359: 386.6 | F359: 285 | G359: 97.9 | H359: 449 | I359: 94.7 | J359: 287 | K359: 297 | L359: 421.5 | M359: 1132 | N359: 310.8 | O359: 1600 | P359: 2270 | Q359: 115.2 | R359: 58.8 | S359: 43.9 | T359: 1025 | U359: 249.5 | V359: 226 | W359: 6305 | X359: 3248.3562 | Y359: 277.5 | Z359: 1351 | AA359: 3110 | AB359: 298.7 | AC359: 1070 | AD359: 9632 | AE359: 1360 | AF359: 2435 | AG359: 126.9204
A360: 44349 | B360: =VLOOKUP(A360,'FTSE All-Share Historical '!A:B,2,FALSE) -> 4081.16 | C360: 900 | D360: 126 | E360: 380.8 | F360: 280 | G360: 98 | H360: 441 | I360: 94.7 | J360: 276 | K360: 309 | L360: 427.5 | M360: 1120 | N360: 312.6 | O360: 1590 | P360: 2280 | Q360: 114.8 | R360: 58.6 | S360: 44.7 | T360: 1005 | U360: 248.5 | V360: 222 | W360: 6305 | X360: 3282.2191 | Y360: 284.5 | Z360: 1338 | AA360: 3105 | AB360: 306.9 | AC360: 1070 | AD360: 9660 | AE360: 1357.5 | AF360: 2423 | AG360: 122.8029
A361: 44350 | B361: =VLOOKUP(A361,'FTSE All-Share Historical '!A:B,2,FALSE) -> 4056.42 | C361: 854 | D361: 127.9 | E361: 376.4 | F361: 277 | G361: 96 | H361: 450 | I361: 93 | J361: 279 | K361: 302.5 | L361: 428 | M361: 1128 | N361: 307.2 | O361: 1590 | P361: 2250 | Q361: 113 | R361: 57.1 | S361: 46.3 | T361: 1005 | U361: 251 | V361: 224.5 | W361: 6172 | X361: 3188.1 | Y361: 274.5 | Z361: 1315 | AA361: 3115 | AB361: 305.4 | AC361: 1070 | AD361: 9802 | AE361: 1293 | AF361: 2403 | AG361: 121.1414
A362: 44351 | B362: =VLOOKUP(A362,'FTSE All-Share Historical '!A:B,2,FALSE) -> 4059.61 | C362: 882 | D362: 128.9 | E362: 379 | F362: 280 | G362: 97 | H362: 441 | I362: 94.35 | J362: 281 | K362: 298 | L362: 418 | M362: 1140 | N362: 311.6 | O362: 1590 | P362: 2230 | Q362: 112 | R362: 57.4 | S362: 46 | T362: 1000 | U362: 252 | V362: 217 | W362: 6219 | X362: 3241.3844 | Y362: 280.5 | Z362: 1327 | AA362: 3085 | AB362: 303.1 | AC362: 1065 | AD362: 9824 | AE362: 1303 | AF362: 2409 | AG362: 115.6514
A363: 44354 | B363: =VLOOKUP(A363,'FTSE All-Share Historical '!A:B,2,FALSE) -> 4065.88 | C363: 856 | D363: 126.2 | E363: 389.2 | F363: 277 | G363: 95.8 | H363: 441 | I363: 93.2 | J363: 275 | K363: 307 | L363: 404.5 | M363: 1136 | N363: 314 | O363: 1580 | P363: 2220 | Q363: 113.4 | R363: 59 | S363: 46.5 | T363: 1005 | U363: 252 | V363: 218 | W363: 6141 | X363: 3153 | Y363: 273 | Z363: 1325 | AA363: 3120 | AB363: 308.2 | AC363: 1065 | AD363: 9862 | AE363: 1282.5 | AF363: 2425 | AG363: 112.6897
A364: 44355 | B364: =VLOOKUP(A364,'FTSE All-Share Historical '!A:B,2,FALSE) -> 4073.88 | C364: 888 | D364: 126 | E364: 397.2 | F364: 270 | G364: 96 | H364: 453 | I364: 94.2 | J364: 278 | K364: 306 | L364: 384 | M364: 1148 | N364: 315 | O364: 1600 | P364: 2200 | Q364: 113.2 | R364: 58.9 | S364: 46.2 | T364: 1015 | U364: 253 | V364: 214 | W364: 6192 | X364: 3183 | Y364: 268.5 | Z364: 1329 | AA364: 3095 | AB364: 301 | AC364: 1065 | AD364: 9880 | AE364: 1267.5 | AF364: 2418 | AG364: 104.9604
A365: 44356 | B365: =VLOOKUP(A365,'FTSE All-Share Historical '!A:B,2,FALSE) -> 4062.85 | C365: 850 | D365: 122.8 | E365: 388 | F365: 276 | G365: 97 | H365: 444 | I365: 93.15 | J365: 274.5 | K365: 319 | L365: 374 | M365: 1152 | N365: 311.2 | O365: 1605 | P365: 2185 | Q365: 112 | R365: 57.6 | S365: 46 | T365: 976 | U365: 251 | V365: 214 | W365: 6068 | X365: 3102.5 | Y365: 264 | Z365: 1330 | AA365: 3100 | AB365: 296.6 | AC365: 1065 | AD365: 9726 | AE365: 1290 | AF365: 2446 | AG365: 114.1345
A366: 44357 | B366: =VLOOKUP(A366,'FTSE All-Share Historical '!A:B,2,FALSE) -> 4061.37 | C366: 872 | D366: 125 | E366: 397.2 | F366: 279 | G366: 97.3 | H366: 443 | I366: 91 | J366: 275 | K366: 322 | L366: 379 | M366: 1208 | N366: 303.2 | O366: 1595 | P366: 2170 | Q366: 113.8 | R366: 57.2 | S366: 45.7 | T366: 1005 | U366: 250 | V366: 210 | W366: 6033 | X366: 3099.5 | Y366: 259 | Z366: 1279 | AA366: 3100 | AB366: 299 | AC366: 1065 | AD366: 9576 | AE366: 1271 | AF366: 2445 | AG366: 111.9674
A367: 44358 | B367: =VLOOKUP(A367,'FTSE All-Share Historical '!A:B,2,FALSE) -> 4086.98 | C367: 862 | D367: 125 | E367: 395 | F367: 270 | G367: 96 | H367: 444 | I367: 91.5 | J367: 275 | K367: 328 | L367: 374 | M367: 1246 | N367: 303.2 | O367: 1590 | P367: 2195 | Q367: 114.4 | R367: 57 | S367: 45.4 | T367: 998 | U367: 251 | V367: 211 | W367: 6119 | X367: 3147 | Y367: 265 | Z367: 1288 | AA367: 3100 | AB367: 303 | AC367: 1065 | AD367: 9572 | AE367: 1279 | AF367: 2447 | AG367: 110.7393
A368: 44361 | B368: =VLOOKUP(A368,'FTSE All-Share Historical '!A:B,2,FALSE) -> 4093.25 | C368: 868 | D368: 125 | E368: 394.6 | F368: 266 | G368: 96.7 | H368: 444 | I368: 89.9 | J368: 270 | K368: 330 | L368: 359 | M368: 1288 | N368: 299.4 | O368: 1580 | P368: 2215 | Q368: 117 | R368: 57.7 | S368: 46.2 | T368: 1010 | U368: 256 | V368: 214.5 | W368: 6092 | X368: 3112.5 | Y368: 269.5 | Z368: 1237 | AA368: 3105 | AB368: 299.2 | AC368: 1080 | AD368: 9622 | AE368: 1240 | AF368: 2465 | AG368: 111.3895
A369: 44362 | B369: =VLOOKUP(A369,'FTSE All-Share Historical '!A:B,2,FALSE) -> 4101.74 | C369: 850 | D369: 127.4 | E369: 398.8 | F369: 266 | G369: 98.6 | H369: 452 | I369: 90.3 | J369: 279 | K369: 336 | L369: 348.5 | M369: 1310 | N369: 297.4 | O369: 1600 | P369: 2205 | Q369: 116.4 | R369: 58 | S369: 46.4 | T369: 1030 | U369: 252 | V369: 211 | W369: 6014 | X369: 2999 | Y369: 259 | Z369: 1248 | AA369: 3095 | AB369: 291.1 | AC369: 1110 | AD369: 9818 | AE369: 1232.5 | AF369: 2486 | AG369: 126.3425
A370: 44363 | B370: =VLOOKUP(A370,'FTSE All-Share Historical '!A:B,2,FALSE) -> 4107.15 | C370: 874 | D370: 128 | E370: 405.8 | F370: 266 | G370: 99 | H370: 446 | I370: 91.2 | J370: 275 | K370: 328 | L370: 345 | M370: 1280 | N370: 293 | O370: 1590 | P370: 2220 | Q370: 118.6 | R370: 57.9 | S370: 46.5 | T370: 1020 | U370: 253 | V370: 210 | W370: 6020 | X370: 2963.5 | Y370: 254.5 | Z370: 1225 | AA370: 3140 | AB370: 296.7 | AC370: 1130 | AD370: 9914 | AE370: 1225 | AF370: 2512 | AG370: 126.1258
... A421: 44434 | B421: =VLOOKUP(A421,'FTSE All-Share Historical '!A:B,2,FALSE) -> 4121.23 | C421: 820 | D421: 174.1 | E421: 369 | F421: 275 | G421: 87 | H421: 421 | I421: 85.45 | J421: 337.5 | K421: 287 | L421: 360 | M421: 1450 | N421: 287.2 | O421: 1605 | P421: 2545 | Q421: 130.8 | R421: 61.7 | S421: 52.4 | T421: 1045 | U421: 283 | V421: 236 | W421: 5316 | X421: 2994 | Y421: 233.5 | Z421: 1115 | AA421: 3750 | AB421: 372.8 | AC421: 1030 | AD421: 10230 | AE421: 1174 | AF421: 2525 | AG421: 114.1345
A422: 44435 | B422: =VLOOKUP(A422,'FTSE All-Share Historical '!A:B,2,FALSE) -> 4135.49 | C422: 787 | D422: 169.2 | E422: 367 | F422: #N/A | G422: 84 | H422: 420 | I422: 85.45 | J422: 337 | K422: 295 | L422: 365.5 | M422: 1472 | N422: 289.8 | O422: 1615 | P422: 2580 | Q422: 128.6 | R422: 59.9 | S422: 52.4 | T422: 1045 | U422: 285 | V422: 241 | W422: 5404 | X422: 3084 | Y422: 241.5 | Z422: 1112 | AA422: 3795 | AB422: 369.5 | AC422: 1020 | AD422: 10225 | AE422: 1161.5 | AF422: 2524 | AG422: 111.9674
A423: 44439 | B423: =VLOOKUP(A423,'FTSE All-Share Historical '!A:B,2,FALSE) -> 4123.45 | C423: 774 | D423: 170.1 | E423: 363.6 | F423: 286 | G423: 86.4 | H423: 427 | I423: 86.35 | J423: 338.5 | K423: 298 | L423: 352.5 | M423: 1482 | N423: 294.6 | O423: 1605 | P423: 2570 | Q423: 128.6 | R423: 59 | S423: 54 | T423: 1115 | U423: 287 | V423: 238 | W423: 5382 | X423: 3069 | Y423: 250 | Z423: 1113 | AA423: 3820 | AB423: 363.1 | AC423: 1025 | AD423: 10505 | AE423: 1154 | AF423: 2538 | AG423: 110.3781
A424: 44440 | B424: =VLOOKUP(A424,'FTSE All-Share Historical '!A:B,2,FALSE) -> 4142.37 | C424: 770 | D424: 168.5 | E424: 356.6 | F424: 273 | G424: 86.4 | H424: 425 | I424: 87 | J424: 355 | K424: 302 | L424: 357.5 | M424: 1490 | N424: 295 | O424: 1610 | P424: 2635 | Q424: 127.4 | R424: 61.4 | S424: 54.8 | T424: 1095 | U424: 287 | V424: 237 | W424: 5332 | X424: 3067.5 | Y424: 242 | Z424: 1118 | AA424: 3910 | AB424: 365.4 | AC424: 1030 | AD424: 10565 | AE424: 1193 | AF424: 2560 | AG424: 110.8838
A425: 44441 | B425: =VLOOKUP(A425,'FTSE All-Share Historical '!A:B,2,FALSE) -> 4148.24 | C425: 744 | D425: 171.5 | E425: 355 | F425: 276 | G425: 88.6 | H425: 425 | I425: 85.85 | J425: 345 | K425: 316 | L425: 361 | M425: 1502 | N425: 292.6 | O425: 1630 | P425: 2645 | Q425: 127.8 | R425: 60.4 | S425: 56 | T425: 1050 | U425: 283 | V425: 237 | W425: 5406 | X425: 3074.5 | Y425: 242.5 | Z425: 1120 | AA425: 3900 | AB425: 357.2 | AC425: 1030 | AD425: 10645 | AE425: 1191 | AF425: 2565 | AG425: 111.1727
A426: 44442 | B426: =VLOOKUP(A426,'FTSE All-Share Historical '!A:B,2,FALSE) -> 4135.18 | C426: 726 | D426: 167.9 | E426: 355.8 | F426: 279 | G426: 87.6 | H426: 420 | I426: 84.5 | J426: 337 | K426: 299 | L426: 354 | M426: 1514 | N426: 285.4 | O426: 1620 | P426: 2685 | Q426: 129.8 | R426: 58.6 | S426: 59.6 | T426: 1060 | U426: 278 | V426: 239.5 | W426: 5408 | X426: 3091 | Y426: 237 | Z426: 1097 | AA426: 3935 | AB426: 351.3 | AC426: 1030 | AD426: 10610 | AE426: 1159.5 | AF426: 2572 | AG426: 111.1727
A427: 44445 | B427: =VLOOKUP(A427,'FTSE All-Share Historical '!A:B,2,FALSE) -> 4159.94 | C427: 726 | D427: 169.3 | E427: 351 | F427: 270 | G427: 85 | H427: 420 | I427: 84.35 | J427: 333 | K427: 300 | L427: 353 | M427: 1506 | N427: 285.2 | O427: 1590 | P427: 2610 | Q427: 129.2 | R427: 59.8 | S427: 56.2 | T427: 1050 | U427: 281 | V427: 249 | W427: 5337 | X427: 3078.5 | Y427: 239.5 | Z427: 1099 | AA427: 3965 | AB427: 349.9 | AC427: 1025 | AD427: 10765 | AE427: 1173 | AF427: 2603 | AG427: 110.5226
A428: 44446 | B428: =VLOOKUP(A428,'FTSE All-Share Historical '!A:B,2,FALSE) -> 4137.32 | C428: 730 | D428: 171 | E428: 351.4 | F428: 273 | G428: 87.9 | H428: 425 | I428: 82.25 | J428: 333 | K428: 299 | L428: 347 | M428: 1486 | N428: 283.4 | O428: 1595 | P428: 2570 | Q428: 128 | R428: 60.3 | S428: 55.4 | T428: 1045 | U428: 281.5 | V428: 247 | W428: 5360 | X428: 3096 | Y428: 239 | Z428: 1082 | AA428: 4010 | AB428: 347.2 | AC428: 1025 | AD428: 10700 | AE428: 1150.5 | AF428: 2576 | AG428: 111.245
A429: 44447 | B429: =VLOOKUP(A429,'FTSE All-Share Historical '!A:B,2,FALSE) -> 4104.05 | C429: 730 | D429: 170 | E429: 342.8 | F429: 279 | G429: 86.8 | H429: 425 | I429: 80.4 | J429: 331 | K429: 302 | L429: 338.5 | M429: 1476 | N429: 281 | O429: 1620 | P429: 2560 | Q429: 125 | R429: 58.7 | S429: 54.4 | T429: 1055 | U429: 277 | V429: 241 | W429: 5305 | X429: 3047.5 | Y429: 235 | Z429: 1056 | AA429: 4000 | AB429: 339.8 | AC429: 1025 | AD429: 10555 | AE429: 1135.5 | AF429: 2525 | AG429: 108.5
A430: 44448 | B430: =VLOOKUP(A430,'FTSE All-Share Historical '!A:B,2,FALSE) -> 4068.81 | C430: 750 | D430: 170.3 | E430: 330.4 | F430: 287 | G430: 86.4 | H430: 427 | I430: 81.15 | J430: 331 | K430: 305 | L430: 341 | M430: 1446 | N430: 271.4 | O430: 1620 | P430: 2590 | Q430: 125 | R430: 60.4 | S430: 54.2 | T430: 1040 | U430: 278 | V430: 243 | W430: 5163 | X430: 3028 | Y430: 231 | Z430: 1060 | AA430: 3910 | AB430: 340.5 | AC430: 1025 | AD430: 10575 | AE430: 1102.5 | AF430: 2520 | AG430: 112.8342
A431: 44449 | B431: =VLOOKUP(A431,'FTSE All-Share Historical '!A:B,2,FALSE) -> 4069.07 | C431: 768 | D431: 166.9 | E431: 309 | F431: 288 | G431: 86 | H431: 434 | I431: 80.7 | J431: 335 | K431: 302 | L431: 346 | M431: 1454 | N431: 268 | O431: 1590 | P431: 2580 | Q431: 124 | R431: 60.4 | S431: 54.6 | T431: 1015 | U431: 276.5 | V431: 243 | W431: 5264 | X431: 3071.5 | Y431: 233.5 | Z431: 1056 | AA431: 3870 | AB431: 340.2 | AC431: 1025 | AD431: 10570 | AE431: 1070 | AF431: 2531 | AG431: 126.8482
A432: 44452 | B432: =VLOOKUP(A432,'FTSE All-Share Historical '!A:B,2,FALSE) -> 4088.93 | C432: 740 | D432: 170.3 | E432: 301.8 | F432: 280 | G432: 83.6 | H432: 438 | I432: 82.8 | J432: 336 | K432: 303 | L432: 358 | M432: 1478 | N432: 270.8 | O432: 1590 | P432: 2550 | Q432: 124 | R432: 61.3 | S432: 53.6 | T432: 1020 | U432: 273 | V432: 250 | W432: 5287 | X432: 3093 | Y432: 232.5 | Z432: 1060 | AA432: 3845 | AB432: 355.4 | AC432: 1020 | AD432: 10640 | AE432: 1130.5 | AF432: 2500 | AG432: 125.6924
A433: 44453 | B433: =VLOOKUP(A433,'FTSE All-Share Historical '!A:B,2,FALSE) -> 4069.91 | C433: 734 | D433: 170 | E433: 300 | F433: 278 | G433: 85 | H433: 436 | I433: 80.3 | J433: 343 | K433: 305 | L433: 326.5 | M433: 1460 | N433: 265 | O433: 1550 | P433: 2560 | Q433: 123 | R433: 59.8 | S433: 54.2 | T433: 1010 | U433: 270.5 | V433: 248 | W433: 5179 | X433: 2996.5 | Y433: 232 | Z433: 1046 | AA433: 3815 | AB433: 360.2 | AC433: 1020 | AD433: 10575 | AE433: 1117.5 | AF433: 2485 | AG433: 119.1911
A434: 44454 | B434: =VLOOKUP(A434,'FTSE All-Share Historical '!A:B,2,FALSE) -> 4053.58 | C434: 692 | D434: 171.6 | E434: 295.2 | F434: 275 | G434: 78 | H434: 435 | I434: 78.45 | J434: 338 | K434: 307 | L434: 310 | M434: 1478 | N434: 257.8 | O434: 1525 | P434: 2515 | Q434: 125.2 | R434: 59.8 | S434: 53 | T434: 1015 | U434: 269 | V434: 250 | W434: 5219 | X434: 2953.5 | Y434: 247.5 | Z434: 1005 | AA434: 3745 | AB434: 356.2 | AC434: 1020 | AD434: 10495 | AE434: 1115.5 | AF434: 2449 | AG434: 117.0239
... A505: 44553 | B505: =VLOOKUP(A505,'FTSE All-Share Historical '!A:B,2,FALSE) -> 4216.65 | C505: 710 | D505: 186.7 | E505: 344.4 | F505: 278 | G505: 68.6 | H505: 459 | I505: 74.35 | J505: 325 | K505: 318 | L505: 260 | M505: 1220 | N505: 246.6 | O505: 1545 | P505: 2475 | Q505: 108.4 | R505: 51.6 | S505: 69 | T505: 1200 | U505: 284 | V505: 256 | W505: 4864.5 | X505: 3010.5 | Y505: 246 | Z505: 918 | AA505: 3750 | AB505: 318.7 | AC505: 932.5 | AD505: 13050 | AE505: 1049.5 | AF505: 2186 | AG505: 151.6977
A506: 44554 | B506: =VLOOKUP(A506,'FTSE All-Share Historical '!A:B,2,FALSE) -> 4216.17 | C506: 714 | D506: 182.8 | E506: 341.8 | F506: #N/A | G506: 68.6 | H506: 448 | I506: 74.95 | J506: 322.5 | K506: 313 | L506: 270.5 | M506: 1200 | N506: 246.6 | O506: 1525 | P506: 2465 | Q506: 108.4 | R506: 52.6 | S506: 68.4 | T506: 1190 | U506: 278.5 | V506: 260.5 | W506: 4866.5 | X506: 3040.5 | Y506: 245 | Z506: 929.5 | AA506: 3750 | AB506: 318.4 | AC506: 932.5 | AD506: 13100 | AE506: 1042.5 | AF506: 2189 | AG506: 150.9753
A507: 44559 | B507: =VLOOKUP(A507,'FTSE All-Share Historical '!A:B,2,FALSE) -> 4246.9 | C507: 696 | D507: 183.9 | E507: 347.6 | F507: 280 | G507: 68.5 | H507: 459 | I507: 74.45 | J507: 327 | K507: 310 | L507: 274.5 | M507: 1202 | N507: 247.8 | O507: 1535 | P507: 2505 | Q507: 110.8 | R507: 51 | S507: 67.4 | T507: 1165 | U507: 285 | V507: 264 | W507: 4846 | X507: 3028 | Y507: 250 | Z507: 933 | AA507: 3840 | AB507: 324.5 | AC507: 932.5 | AD507: 13275 | AE507: 1071.5 | AF507: 2228 | AG507: 145.9187
A508: 44560 | B508: =VLOOKUP(A508,'FTSE All-Share Historical '!A:B,2,FALSE) -> 4239.25 | C508: 682 | D508: 187.2 | E508: 345 | F508: 284 | G508: 69.2 | H508: 453 | I508: 75.75 | J508: 337.5 | K508: 315 | L508: 275.5 | M508: 1198 | N508: 250.6 | O508: 1535 | P508: 2500 | Q508: 110 | R508: 53 | S508: 68 | T508: 1200 | U508: 288 | V508: 263.5 | W508: 4900.5 | X508: 3019.5 | Y508: 250.5 | Z508: 944 | AA508: 3855 | AB508: 319 | AC508: 932.5 | AD508: 13220 | AE508: 1061 | AF508: 2220 | AG508: 149.5306
A509: 44561 | B509: =VLOOKUP(A509,'FTSE All-Share Historical '!A:B,2,FALSE) -> 4228.67 | C509: 714 | D509: 179.8 | E509: 345.4 | F509: #N/A | G509: 68.5 | H509: 464 | I509: 77 | J509: 350 | K509: 313 | L509: 285 | M509: 1230 | N509: 256 | O509: 1560 | P509: 2520 | Q509: 110 | R509: 53.4 | S509: 68.8 | T509: 1200 | U509: 287 | V509: 261.5 | W509: 4892 | X509: 3016 | Y509: 259 | Z509: 961 | AA509: 3880 | AB509: 318.6 | AC509: 932.5 | AD509: 13105 | AE509: 1115 | AF509: 2219 | AG509: 150.253
A510: 44565 | B510: =VLOOKUP(A510,'FTSE All-Share Historical '!A:B,2,FALSE) -> 4298.76 | C510: 754 | D510: 177.9 | E510: 358.6 | F510: 281 | G510: 71.7 | H510: 465 | I510: 78 | J510: 335 | K510: 321 | L510: 296.5 | M510: 1210 | N510: 263.6 | O510: 1660 | P510: 2530 | Q510: 109.8 | R510: 54 | S510: 73 | T510: 1200 | U510: 281 | V510: 267 | W510: 4938.5 | X510: 3096.5 | Y510: 255 | Z510: 964.5 | AA510: 3965 | AB510: 328.6 | AC510: 935 | AD510: 13305 | AE510: 1181 | AF510: 2189 | AG510: 144.474
A511: 44566 | B511: =VLOOKUP(A511,'FTSE All-Share Historical '!A:B,2,FALSE) -> 4300.35 | C511: 742 | D511: 181.2 | E511: 359 | F511: 279 | G511: 71.2 | H511: 488 | I511: 78.5 | J511: 324 | K511: 325 | L511: 300.5 | M511: 1202 | N511: 259.8 | O511: 1610 | P511: 2490 | Q511: 111 | R511: 54 | S511: 72 | T511: 1210 | U511: 282 | V511: 269.5 | W511: 5035 | X511: 3182 | Y511: 251 | Z511: 973 | AA511: 3870 | AB511: 327.1 | AC511: 935 | AD511: 13290 | AE511: 1185 | AF511: 2191 | AG511: 138.0449
A512: 44567 | B512: =VLOOKUP(A512,'FTSE All-Share Historical '!A:B,2,FALSE) -> 4257.77 | C512: 722 | D512: 178.5 | E512: 357.4 | F512: 275 | G512: 70 | H512: 475 | I512: 78.85 | J512: 334 | K512: 322 | L512: 290 | M512: 1152 | N512: 258.6 | O512: 1590 | P512: 2470 | Q512: 110.4 | R512: 53.1 | S512: 69.2 | T512: 1190 | U512: 284 | V512: 269.5 | W512: 5078 | X512: 3164 | Y512: 232 | Z512: 970.5 | AA512: 3820 | AB512: 341.3 | AC512: 935 | AD512: 12965 | AE512: 1199.5 | AF512: 2125 | AG512: 145.1964
A513: 44568 | B513: =VLOOKUP(A513,'FTSE All-Share Historical '!A:B,2,FALSE) -> 4272.27 | C513: 750 | D513: 176.7 | E513: 359.4 | F513: 278 | G513: 69 | H513: 470 | I513: 78.5 | J513: 331 | K513: 325 | L513: 293.5 | M513: 1136 | N513: 257.6 | O513: 1565 | P513: 2455 | Q513: 108.8 | R513: 53.2 | S513: 68.2 | T513: 1195 | U513: 280 | V513: 263.5 | W513: 5212 | X513: 3257 | Y513: 226.5 | Z513: 961 | AA513: 3975 | AB513: 341.3 | AC513: 935 | AD513: 12840 | AE513: 1237.5 | AF513: 2134 | AG513: 143.7516
A514: 44571 | B514: =VLOOKUP(A514,'FTSE All-Share Historical '!A:B,2,FALSE) -> 4242.3 | C514: 730 | D514: 173 | E514: 356.2 | F514: 275 | G514: 71.2 | H514: 480 | I514: 78 | J514: 334 | K514: 320 | L514: 297 | M514: 1100 | N514: 263 | O514: 1600 | P514: 2365 | Q514: 105.4 | R514: 56 | S514: 70.4 | T514: 1190 | U514: 275 | V514: 256 | W514: 5202 | X514: 3242 | Y514: 228 | Z514: 969 | AA514: 3830 | AB514: 346.4 | AC514: 935 | AD514: 12355 | AE514: 1264 | AF514: 2103 | AG514: 144.474
A515: 44572 | B515: =VLOOKUP(A515,'FTSE All-Share Historical '!A:B,2,FALSE) -> 4264.93 | C515: 740 | D515: 175 | E515: 360 | F515: 285 | G515: 69.2 | H515: 476 | I515: 79.6 | J515: 327.5 | K515: 314 | L515: 293 | M515: 1092 | N515: 263.4 | O515: 1565 | P515: 2325 | Q515: 105.4 | R515: 52.6 | S515: 70.8 | T515: 1175 | U515: 283 | V515: 259.5 | W515: 5301 | X515: 3239 | Y515: 223 | Z515: 958.5 | AA515: 3780 | AB515: 344.4 | AC515: 935 | AD515: 12450 | AE515: 1250.5 | AF515: 2098 | AG515: 138.984
A516: 44573 | B516: =VLOOKUP(A516,'FTSE All-Share Historical '!A:B,2,FALSE) -> 4294.04 | C516: 738 | D516: 175 | E516: 362 | F516: 285 | G516: 70 | H516: 470 | I516: 80 | J516: 318 | K516: 316 | L516: 293 | M516: 1062 | N516: 257.6 | O516: 1600 | P516: 2310 | Q516: 108 | R516: 53.6 | S516: 72.4 | T516: 1200 | U516: 290 | V516: 257.5 | W516: 5452 | X516: 3364.5 | Y516: 237.5 | Z516: 917.5 | AA516: 3810 | AB516: 331.7 | AC516: 935 | AD516: 12715 | AE516: 1249 | AF516: 2080 | AG516: 139.4896
A517: 44574 | B517: =VLOOKUP(A517,'FTSE All-Share Historical '!A:B,2,FALSE) -> 4296.99 | C517: 726 | D517: 175 | E517: 364 | F517: 283 | G517: 70 | H517: 453 | I517: 82.65 | J517: 322 | K517: 324 | L517: 295.5 | M517: 1026 | N517: 260 | O517: 1540 | P517: 2370 | Q517: 107.2 | R517: 53 | S517: 72 | T517: 1200 | U517: 289 | V517: 263 | W517: 5463 | X517: 3355 | Y517: 235 | Z517: 927 | AA517: 3860 | AB517: 339.2 | AC517: 935 | AD517: 12800 | AE517: 1273 | AF517: 2061 | AG517: 139.6341
A518: 44575 | B518: =VLOOKUP(A518,'FTSE All-Share Historical '!A:B,2,FALSE) -> 4280.34 | C518: 718 | D518: 174.8 | E518: 357 | F518: 279.5 | G518: 75 | H518: 459 | I518: 83.25 | J518: 308 | K518: 322 | L518: 297 | M518: 1016 | N518: 262 | O518: 1565 | P518: 2340 | Q518: 106.4 | R518: 52.6 | S518: 74.8 | T518: 1200 | U518: 298 | V518: 263.5 | W518: 5392 | X518: 3306 | Y518: 227 | Z518: 925.5 | AA518: 3800 | AB518: 342.8 | AC518: 935 | AD518: 12455 | AE518: 1257.5 | AF518: 2056 | AG518: 137.6837
A519: 44578 | B519: =VLOOKUP(A519,'FTSE All-Share Historical '!A:B,2,FALSE) -> 4316.64 | C519: 742 | D519: 176 | E519: 358 | F519: 293 | G519: 80.6 | H519: 458 | I519: 81.95 | J519: 317 | K519: 325 | L519: 292.5 | M519: 994 | N519: 264 | O519: 1540 | P519: 2330 | Q519: 106.6 | R519: 51 | S519: 75 | T519: 1175 | U519: 290 | V519: 264.5 | W519: 5393 | X519: 3371.5 | Y519: 230 | Z519: 921 | AA519: 3840 | AB519: 345.1 | AC519: 935 | AD519: 12530 | AE519: 1267 | AF519: 2069 | AG519: 140.8621
A520: 44579 | B520: =VLOOKUP(A520,'FTSE All-Share Historical '!A:B,2,FALSE) -> 4287.22 | C520: 740 | D520: 178.8 | E520: 346 | F520: 287 | G520: 77.4 | H520: 450 | I520: 82.5 | J520: 309 | K520: 321 | L520: 285.5 | M520: 975 | N520: 264.4 | O520: 1540 | P520: 2310 | Q520: 109.6 | R520: 50 | S520: 71.6 | T520: 1150 | U520: 290 | V520: 267 | W520: 5443 | X520: 3376 | Y520: 229.5 | Z520: 903.5 | AA520: 3825 | AB520: 343.6 | AC520: 935 | AD520: 12125 | AE520: 1247 | AF520: 2029 | AG520: 150.9753
A521: 44580 | B521: =VLOOKUP(A521,'FTSE All-Share Historical '!A:B,2,FALSE) -> 4299.63 | C521: 712 | D521: 176.7 | E521: 347 | F521: 295 | G521: 75.5 | H521: 450 | I521: 83.65 | J521: 309 | K521: 320 | L521: 288.5 | M521: 973 | N521: 261 | O521: 1575 | P521: 2310 | Q521: 108.6 | R521: 48.3 | S521: 68.6 | T521: 1075 | U521: 288.5 | V521: 270 | W521: 5654 | X521: 3517.5 | Y521: 237 | Z521: 919.5 | AA521: 3715 | AB521: 344.2 | AC521: 935 | AD521: 11905 | AE521: 1233 | AF521: 2020 | AG521: 148.2303
... A590: 44679 | B590: =VLOOKUP(A590,'FTSE All-Share Historical '!A:B,2,FALSE) -> 4197.13 | C590: 596 | D590: 175 | E590: 224.8 | F590: 324 | G590: 84 | H590: 491 | I590: 76.05 | J590: 248 | K590: 243 | L590: 222 | M590: 545 | N590: 225.8 | O590: 1440 | P590: 2190 | Q590: 77.2 | R590: 40 | S590: 50.8 | T590: 610 | U590: 240 | V590: 248 | W590: 5628 | X590: 3453.5 | Y590: 270 | Z590: 730 | AA590: 3700 | AB590: 304.6 | AC590: 975 | AD590: 10080 | AE590: 1237.5 | AF590: 2029 | AG590: 17.1491
A591: 44680 | B591: =VLOOKUP(A591,'FTSE All-Share Historical '!A:B,2,FALSE) -> 4216.64 | C591: 596 | D591: 175 | E591: 226.4 | F591: #N/A | G591: 84.6 | H591: 472.5 | I591: 75.05 | J591: 242 | K591: 240 | L591: 230 | M591: 570 | N591: 228 | O591: 1386 | P591: 2175 | Q591: 79.3 | R591: 40 | S591: 51.8 | T591: 640 | U591: 248 | V591: 247.5 | W591: 5706 | X591: 3586 | Y591: 268 | Z591: 735.5 | AA591: 3690 | AB591: 306.4 | AC591: 965 | AD591: 10140 | AE591: 1240.5 | AF591: 1883.5 | AG591: 19.2295
A592: 44684 | B592: =VLOOKUP(A592,'FTSE All-Share Historical '!A:B,2,FALSE) -> 4218.6 | C592: 602 | D592: 175.6 | E592: 226 | F592: 323 | G592: 84.4 | H592: 487 | I592: 73.1 | J592: 244 | K592: 232 | L592: 218 | M592: 525 | N592: 227.8 | O592: 1416 | P592: 2125 | Q592: 78.5 | R592: 42.35 | S592: 52.7 | T592: 660 | U592: 240 | V592: 245.5 | W592: 5645 | X592: 3580 | Y592: 278 | Z592: 741 | AA592: 3660 | AB592: 313.2 | AC592: 995 | AD592: 9938 | AE592: 1236 | AF592: 1890 | AG592: 17.6258
A593: 44685 | B593: =VLOOKUP(A593,'FTSE All-Share Historical '!A:B,2,FALSE) -> 4177.02 | C593: 608 | D593: 171 | E593: 222.8 | F593: 321 | G593: 83.6 | H593: 493 | I593: 71.45 | J593: 254 | K593: 226 | L593: 221 | M593: 521 | N593: 228.2 | O593: 1394 | P593: 2080 | Q593: 77.6 | R593: 42 | S593: 51 | T593: 690 | U593: 240 | V593: 242 | W593: 5492 | X593: 3507.5 | Y593: 269 | Z593: 730 | AA593: 3650 | AB593: 312.4 | AC593: 990 | AD593: 9758 | AE593: 1183 | AF593: 1852.5 | AG593: 17.8859
A594: 44686 | B594: =VLOOKUP(A594,'FTSE All-Share Historical '!A:B,2,FALSE) -> 4177.55 | C594: 608 | D594: 170 | E594: 221.2 | F594: 316 | G594: 84.7 | H594: 479.5 | I594: 69.1 | J594: 244 | K594: 228 | L594: 224.5 | M594: 515 | N594: 214.2 | O594: 1394 | P594: 2030 | Q594: 78 | R594: 42 | S594: 50.1 | T594: 600 | U594: 236 | V594: 242.5 | W594: 5481 | X594: 3521 | Y594: 255 | Z594: 718 | AA594: 3555 | AB594: 304.8 | AC594: 1000 | AD594: 9764 | AE594: 1169.5 | AF594: 1685.5 | AG594: 18.4638
A595: 44687 | B595: =VLOOKUP(A595,'FTSE All-Share Historical '!A:B,2,FALSE) -> 4114.56 | C595: 584 | D595: 169 | E595: 221.4 | F595: 315 | G595: 82.7 | H595: 476 | I595: 67.65 | J595: 245 | K595: 226 | L595: 219 | M595: 497.5 | N595: 210 | O595: 1400 | P595: 2030 | Q595: 76.5 | R595: 42.4 | S595: 49 | T595: 552 | U595: 222 | V595: 234.5 | W595: 5440 | X595: 3488.5 | Y595: 255 | Z595: 718.5 | AA595: 3545 | AB595: 306 | AC595: 990 | AD595: 9332 | AE595: 1123 | AF595: 1735 | AG595: 19.1428
A596: 44690 | B596: =VLOOKUP(A596,'FTSE All-Share Historical '!A:B,2,FALSE) -> 4017.43 | C596: 601 | D596: 167 | E596: 223.8 | F596: 315 | G596: 82.8 | H596: 463.5 | I596: 64.65 | J596: 238 | K596: 218 | L596: 208 | M596: 485 | N596: 209.4 | O596: 1352 | P596: 1960 | Q596: 74.5 | R596: 40 | S596: 47 | T596: 588 | U596: 216 | V596: 232.5 | W596: 5188 | X596: 3300 | Y596: 233 | Z596: 705 | AA596: 3400 | AB596: 304.8 | AC596: 985 | AD596: 9110 | AE596: 1071.5 | AF596: 1697 | AG596: 17.727
A597: 44691 | B597: =VLOOKUP(A597,'FTSE All-Share Historical '!A:B,2,FALSE) -> 4032.49 | C597: 584 | D597: 167 | E597: 223.8 | F597: 332 | G597: 81 | H597: 457 | I597: 63.45 | J597: 240 | K597: 222 | L597: 210.5 | M597: 485 | N597: 208 | O597: 1360 | P597: 1958 | Q597: 74.5 | R597: 39.55 | S597: 48 | T597: 600 | U597: 222 | V597: 225 | W597: 5163 | X597: 3286 | Y597: 228 | Z597: 700 | AA597: 3385 | AB597: 301.4 | AC597: 1020 | AD597: 9174 | AE597: 1074 | AF597: 1741 | AG597: 17.6981
A598: 44692 | B598: =VLOOKUP(A598,'FTSE All-Share Historical '!A:B,2,FALSE) -> 4090.08 | C598: 590 | D598: 170 | E598: 226 | F598: 320 | G598: 84.9 | H598: 457 | I598: 61.85 | J598: 241 | K598: 230 | L598: 218.5 | M598: 486 | N598: 205.8 | O598: 1350 | P598: 1974 | Q598: 76.1 | R598: 39.5 | S598: 52.2 | T598: 552 | U598: 222 | V598: 225.5 | W598: 5357 | X598: 3397.5 | Y598: 235.5 | Z598: 721 | AA598: 3370 | AB598: 307.6 | AC598: 1020 | AD598: 9402 | AE598: 1112.5 | AF598: 1729.5 | AG598: 17.8714
A599: 44693 | B599: =VLOOKUP(A599,'FTSE All-Share Historical '!A:B,2,FALSE) -> 4030.88 | C599: 582 | D599: 170.8 | E599: 227.8 | F599: 325 | G599: 83.8 | H599: 445 | I599: 60.35 | J599: 237 | K599: 220 | L599: 214.5 | M599: 473.5 | N599: 204.6 | O599: 1330 | P599: 1936 | Q599: 75.3 | R599: 39.5 | S599: 48.6 | T599: 554 | U599: 220 | V599: 224 | W599: 5203 | X599: 3242.5 | Y599: 228.5 | Z599: 705 | AA599: 3225 | AB599: 304.8 | AC599: 975 | AD599: 9634 | AE599: 1112.5 | AF599: 1697 | AG599: 16.8601
A600: 44694 | B600: =VLOOKUP(A600,'FTSE All-Share Historical '!A:B,2,FALSE) -> 4132.07 | C600: 588 | D600: 172.4 | E600: 227.8 | F600: 325 | G600: 87.9 | H600: 441 | I600: 63 | J600: 238.5 | K600: 240 | L600: 217.5 | M600: 500 | N600: 215.8 | O600: 1340 | P600: 2005 | Q600: 76.7 | R600: 39 | S600: 51.8 | T600: 570 | U600: 226 | V600: 230.5 | W600: 5320 | X600: 3304.5 | Y600: 234.5 | Z600: 730.5 | AA600: 3300 | AB600: 310.4 | AC600: 1010 | AD600: 9874 | AE600: 1138 | AF600: 1724 | AG600: 19.2873
A601: 44697 | B601: =VLOOKUP(A601,'FTSE All-Share Historical '!A:B,2,FALSE) -> 4154.12 | C601: 574 | D601: 175.2 | E601: 223 | F601: 316 | G601: 86.6 | H601: 447.5 | I601: 62.5 | J601: 239 | K601: 244 | L601: 219 | M601: 503 | N601: 212 | O601: 1338 | P601: 1956 | Q601: 75.6 | R601: 39 | S601: 54.3 | T601: 596 | U601: 226 | V601: 231 | W601: 5339 | X601: 3348.5 | Y601: 236 | Z601: 730 | AA601: 3250 | AB601: 311 | AC601: 1010 | AD601: 9696 | AE601: 1131.5 | AF601: 1711 | AG601: 25.283
A602: 44698 | B602: =VLOOKUP(A602,'FTSE All-Share Historical '!A:B,2,FALSE) -> 4183.88 | C602: 574 | D602: 175 | E602: 220.4 | F602: 326 | G602: 87.1 | H602: 460 | I602: 62.5 | J602: 238 | K602: 242 | L602: 220 | M602: 507 | N602: 214 | O602: 1338 | P602: 1968 | Q602: 75.4 | R602: 39.65 | S602: 54.6 | T602: 600 | U602: 230 | V602: 237 | W602: 5470 | X602: 3498.5 | Y602: 233 | Z602: 736.5 | AA602: 3280 | AB602: 311 | AC602: 995 | AD602: 9936 | AE602: 1139 | AF602: 1726.5 | AG602: 22.4079
A603: 44699 | B603: =VLOOKUP(A603,'FTSE All-Share Historical '!A:B,2,FALSE) -> 4142.34 | C603: 586 | D603: 175 | E603: 217.6 | F603: 324 | G603: 89 | H603: 459 | I603: 58 | J603: 238 | K603: 250 | L603: 228.5 | M603: 487.5 | N603: 211 | O603: 1332 | P603: 1940 | Q603: 76 | R603: 40.85 | S603: 54.8 | T603: 660 | U603: 223 | V603: 228 | W603: 5372 | X603: 3413 | Y603: 232.5 | Z603: 706.5 | AA603: 3200 | AB603: 316.8 | AC603: 985 | AD603: 9604 | AE603: 1141 | AF603: 1678.5 | AG603: 22.1045
... A612: 44712 | B612: =VLOOKUP(A612,'FTSE All-Share Historical '!A:B,2,FALSE) -> 4237.22 | C612: 552 | D612: 175 | E612: 224.2 | F612: 345 | G612: 100 | H612: 495 | I612: 54.55 | J612: 230 | K612: 237 | L612: 202.5 | M612: 511 | N612: 207.6 | O612: 1300 | P612: 2080 | Q612: 78.5 | R612: 39 | S612: 58.6 | T612: 514 | U612: 229 | V612: 232 | W612: 5750 | X612: 3887 | Y612: 258 | Z612: 746.5 | AA612: 3100 | AB612: 337.6 | AC612: 965 | AD612: 9532 | AE612: 1168 | AF612: 1698.5 | AG612: 18.7816
A613: 44713 | B613: =VLOOKUP(A613,'FTSE All-Share Historical '!A:B,2,FALSE) -> 4197.38 | C613: 564 | D613: 175 | E613: 223.6 | F613: #N/A | G613: 104.4 | H613: 484.5 | I613: 54.95 | J613: 232 | K613: 238 | L613: 196.8 | M613: 490.5 | N613: 208 | O613: 1290 | P613: 2080 | Q613: 76.8 | R613: 39.4 | S613: 59.1 | T613: 556 | U613: 232 | V613: 232 | W613: 5758 | X613: 3850 | Y613: 257.5 | Z613: 739 | AA613: 3140 | AB613: 350 | AC613: 967.5 | AD613: 9312 | AE613: 1130 | AF613: 1673 | AG613: 19.0561
A614: 44718 | B614: =VLOOKUP(A614,'FTSE All-Share Historical '!A:B,2,FALSE) -> 4240.32 | C614: 568 | D614: 175 | E614: 224.6 | F614: 336 | G614: 103 | H614: 486 | I614: 55.2 | J614: 234 | K614: 245 | L614: 200.5 | M614: 499 | N614: 206 | O614: 1300 | P614: 2100 | Q614: 78.5 | R614: 39.975 | S614: 56.4 | T614: 548 | U614: 231 | V614: 228.5 | W614: 5956 | X614: 3966.5 | Y614: 264 | Z614: 743 | AA614: 3205 | AB614: 358.8 | AC614: 980 | AD614: 9580 | AE614: 1130.5 | AF614: 1675 | AG614: 18.8105
A615: 44719 | B615: =VLOOKUP(A615,'FTSE All-Share Historical '!A:B,2,FALSE) -> 4232.51 | C615: 564 | D615: 176 | E615: 219 | F615: 329 | G615: 104 | H615: 486 | I615: 56.2 | J615: 232 | K615: 245 | L615: 198.2 | M615: 502 | N615: 203.8 | O615: 1284 | P615: 2100 | Q615: 78.1 | R615: 39.25 | S615: 57.6 | T615: 550 | U615: 230 | V615: 231.5 | W615: 6091 | X615: 4017.5 | Y615: 263 | Z615: 750 | AA615: 3145 | AB615: 362.4 | AC615: 962.5 | AD615: 9494 | AE615: 1102.5 | AF615: 1661.5 | AG615: 19.3884
A616: 44720 | B616: =VLOOKUP(A616,'FTSE All-Share Historical '!A:B,2,FALSE) -> 4226.89 | C616: 570 | D616: 180.4 | E616: 220 | F616: 330 | G616: 106.4 | H616: 487.5 | I616: 58 | J616: 219 | K616: 240 | L616: 197.6 | M616: 514 | N616: 208.4 | O616: 1270 | P616: 2095 | Q616: 77.4 | R616: 39.2 | S616: 58.2 | T616: 530 | U616: 225 | V616: 230 | W616: 6065 | X616: 4007 | Y616: 263 | Z616: 759 | AA616: 3200 | AB616: 363 | AC616: 960 | AD616: 9500 | AE616: 1078.5 | AF616: 1646.5 | AG616: 19.504
A617: 44721 | B617: =VLOOKUP(A617,'FTSE All-Share Historical '!A:B,2,FALSE) -> 4164.27 | C617: 570 | D617: 185.2 | E617: 214 | F617: 324 | G617: 103 | H617: 488 | I617: 58.8 | J617: 226.5 | K617: 249 | L617: 199 | M617: 509 | N617: 207.6 | O617: 1264 | P617: 2065 | Q617: 75.9 | R617: 41 | S617: 58 | T617: 489 | U617: 234 | V617: 228 | W617: 5900 | X617: 3904.5 | Y617: 263 | Z617: 763.5 | AA617: 3200 | AB617: 367.6 | AC617: 970 | AD617: 9310 | AE617: 1047.5 | AF617: 1611 | AG617: 19.3884
A618: 44722 | B618: =VLOOKUP(A618,'FTSE All-Share Historical '!A:B,2,FALSE) -> 4076.7 | C618: 576 | D618: 183 | E618: 208.6 | F618: 323 | G618: 101 | H618: 485 | I618: 58 | J618: 226.5 | K618: 240 | L618: 187.8 | M618: 486 | N618: 203.4 | O618: 1230 | P618: 2040 | Q618: 72.8 | R618: 39.6 | S618: 56.5 | T618: 466 | U618: 230 | V618: 224 | W618: 5690 | X618: 3613 | Y618: 257 | Z618: 741 | AA618: 3200 | AB618: 366.2 | AC618: 962.5 | AD618: 9146 | AE618: 1003 | AF618: 1583.5 | AG618: 18.7816
A619: 44725 | B619: =VLOOKUP(A619,'FTSE All-Share Historical '!A:B,2,FALSE) -> 4007.68 | C619: 576 | D619: 182.6 | E619: 204.4 | F619: 319 | G619: 99.5 | H619: 465 | I619: 56.15 | J619: 228 | K619: 240 | L619: 173.2 | M619: 451 | N619: 201 | O619: 1224 | P619: 1976 | Q619: 70.2 | R619: 39 | S619: 54.8 | T619: 426 | U619: 229 | V619: 214.5 | W619: 5580 | X619: 3518.5 | Y619: 250 | Z619: 730 | AA619: 3175 | AB619: 359.8 | AC619: 962.5 | AD619: 8952 | AE619: 960.2 | AF619: 1537.5 | AG619: 19.504
A620: 44726 | B620: =VLOOKUP(A620,'FTSE All-Share Historical '!A:B,2,FALSE) -> 3995.35 | C620: 580 | D620: 181.8 | E620: 201.2 | F620: 320 | G620: 102.6 | H620: 466 | I620: 56.15 | J620: 225.5 | K620: 235 | L620: 170.4 | M620: 429.5 | N620: 200.2 | O620: 1226 | P620: 1912 | Q620: 70.5 | R620: 39.475 | S620: 55.3 | T620: 455 | U620: 220 | V620: 217 | W620: 5555 | X620: 3455 | Y620: 248 | Z620: 719.5 | AA620: 3160 | AB620: 360 | AC620: 947.5 | AD620: 9186 | AE620: 950.8 | AF620: 1509.5 | AG620: 19.504
A621: 44727 | B621: =VLOOKUP(A621,'FTSE All-Share Historical '!A:B,2,FALSE) -> 4044.51 | C621: 606 | D621: 176 | E621: 197.5 | F621: 320 | G621: 102.4 | H621: 470 | I621: 57.1 | J621: 213 | K621: 233 | L621: 170 | M621: 439.5 | N621: 207.2 | O621: 1200 | P621: 1918 | Q621: 69.9 | R621: 39 | S621: 53.5 | T621: 476 | U621: 224 | V621: 210.5 | W621: 5635 | X621: 3551 | Y621: 251.5 | Z621: 723 | AA621: 3110 | AB621: 349.8 | AC621: 960 | AD621: 9130 | AE621: 993 | AF621: 1518 | AG621: 19.504
A622: 44728 | B622: =VLOOKUP(A622,'FTSE All-Share Historical '!A:B,2,FALSE) -> 3918.07 | C622: 630 | D622: 175 | E622: 142.8 | F622: 320 | G622: 106.8 | H622: 435.5 | I622: 54.9 | J622: 203 | K622: 235 | L622: 162.8 | M622: 419.5 | N622: 196.9 | O622: 1212 | P622: 1822 | Q622: 68 | R622: 38 | S622: 53 | T622: 438 | U622: 215 | V622: 206 | W622: 5444 | X622: 3447 | Y622: 241 | Z622: 690.5 | AA622: 2975 | AB622: 328 | AC622: 975 | AD622: 8680 | AE622: 939.8 | AF622: 1485 | AG622: 19.5762
A623: 44729 | B623: =VLOOKUP(A623,'FTSE All-Share Historical '!A:B,2,FALSE) -> 3910.86 | C623: 624 | D623: 174 | E623: 156.8 | F623: 312 | G623: 106.4 | H623: 439.5 | I623: 54.2 | J623: 210 | K623: 240 | L623: 163 | M623: 415 | N623: 199.8 | O623: 1206 | P623: 1858 | Q623: 67.9 | R623: 36 | S623: 52 | T623: 440 | U623: 216 | V623: 206 | W623: 5177 | X623: 3344.5 | Y623: 234 | Z623: 700.5 | AA623: 2915 | AB623: 329.6 | AC623: 1050 | AD623: 8950 | AE623: 985.6 | AF623: 1496.5 | AG623: 21.5411
A624: 44732 | B624: =VLOOKUP(A624,'FTSE All-Share Historical '!A:B,2,FALSE) -> 3963.31 | C624: 618 | D624: 173.6 | E624: 153.4 | F624: 312 | G624: 101.6 | H624: 439 | I624: 55.15 | J624: 215 | K624: 235 | L624: 169.2 | M624: 454 | N624: 206.4 | O624: 1218 | P624: 1798 | Q624: 69.8 | R624: 35.5 | S624: 52.4 | T624: 462 | U624: 211 | V624: 205.5 | W624: 5125 | X624: 3353.5 | Y624: 233.5 | Z624: 700 | AA624: 2945 | AB624: 331 | AC624: 990 | AD624: 8962 | AE624: 1029.5 | AF624: 1500 | AG624: 25.283
A625: 44733 | B625: =VLOOKUP(A625,'FTSE All-Share Historical '!A:B,2,FALSE) -> 3975.58 | C625: 610 | D625: 176 | E625: 148.8 | F625: 314 | G625: 100 | H625: 436 | I625: 54.25 | J625: 210 | K625: 237 | L625: 161 | M625: 459 | N625: 201.8 | O625: 1190 | P625: 1776 | Q625: 70.6 | R625: 35 | S625: 53.1 | T625: 475 | U625: 210 | V625: 208 | W625: 5250 | X625: 3374 | Y625: 237.5 | Z625: 688 | AA625: 2950 | AB625: 329.6 | AC625: 970 | AD625: 9018 | AE625: 987.6 | AF625: 1482 | AG625: 23.5637
... A672: 44798 | B672: =VLOOKUP(A672,'FTSE All-Share Historical '!A:B,2,FALSE) -> 4139.86 | C672: 614 | D672: 161 | E672: 127.8 | F672: 283 | G672: 83 | H672: 447 | I672: 37.5 | J672: 199 | K672: 210 | L672: 127 | M672: 447 | N672: 160.4 | O672: 1218 | P672: 1774 | Q672: 70 | R672: 40.5 | S672: 51 | T672: 361 | U672: 200.5 | V672: 205 | W672: 4951 | X672: 2919.5 | Y672: 231.5 | Z672: 499.6 | AA672: 3050 | AB672: 322.6 | AC672: 890 | AD672: 10235 | AE672: 873.6 | AF672: 1354 | AG672: 15.7477
A673: 44799 | B673: =VLOOKUP(A673,'FTSE All-Share Historical '!A:B,2,FALSE) -> 4112.34 | C673: 620 | D673: 160.4 | E673: 124.7 | F673: #N/A | G673: 85.15 | H673: 443 | I673: 36.66 | J673: 195.75 | K673: 204 | L673: 120.4 | M673: 435.5 | N673: 157.5 | O673: 1218 | P673: 1730 | Q673: 70.4 | R673: 41 | S673: 50.3 | T673: 364 | U673: 198 | V673: 198 | W673: 4980 | X673: 2922.5 | Y673: 232 | Z673: 492 | AA673: 3060 | AB673: 321.2 | AC673: 875 | AD673: 10085 | AE673: 854.2 | AF673: 1336 | AG673: 15.8921
A674: 44803 | B674: =VLOOKUP(A674,'FTSE All-Share Historical '!A:B,2,FALSE) -> 4080.77 | C674: 590 | D674: 158.4 | E674: 127.4 | F674: 280 | G674: 83 | H674: 443.5 | I674: 36.04 | J674: 195.75 | K674: 205 | L674: 123.4 | M674: 438 | N674: 155.6 | O674: 1198 | P674: 1744 | Q674: 72.1 | R674: 40 | S674: 49.7 | T674: 350 | U674: 201 | V674: 192.4 | W674: 4815 | X674: 2786.5 | Y674: 225.5 | Z674: 490.8 | AA674: 3025 | AB674: 326.8 | AC674: 870 | AD674: 10025 | AE674: 848.6 | AF674: 1319.5 | AG674: 15.1698
A675: 44804 | B675: =VLOOKUP(A675,'FTSE All-Share Historical '!A:B,2,FALSE) -> 4041.53 | C675: 572 | D675: 157.6 | E675: 130.6 | F675: 281 | G675: 83 | H675: 444.5 | I675: 36.36 | J675: 197.5 | K675: 212 | L675: 128 | M675: 457 | N675: 154.5 | O675: 1176 | P675: 1726 | Q675: 71.6 | R675: 40 | S675: 48.65 | T675: 344 | U675: 205 | V675: 189.4 | W675: 4771 | X675: 2783 | Y675: 230 | Z675: 482 | AA675: 3015 | AB675: 329 | AC675: 850 | AD675: 9986 | AE675: 854.4 | AF675: 1313 | AG675: 15.8921
A676: 44805 | B676: =VLOOKUP(A676,'FTSE All-Share Historical '!A:B,2,FALSE) -> 3959.37 | C676: 566 | D676: 159 | E676: 130.2 | F676: 279 | G676: 83 | H676: 438.5 | I676: 36.32 | J676: 195 | K676: 210 | L676: 127.8 | M676: 420.5 | N676: 149.1 | O676: 1160 | P676: 1646 | Q676: 70.4 | R676: 38.45 | S676: 48 | T676: 362 | U676: 200 | V676: 185.2 | W676: 4607.5 | X676: 2678 | Y676: 216 | Z676: 471.8 | AA676: 2770 | AB676: 316.4 | AC676: 857.5 | AD676: 9788 | AE676: 866 | AF676: 1289.5 | AG676: 15.2709
A677: 44806 | B677: =VLOOKUP(A677,'FTSE All-Share Historical '!A:B,2,FALSE) -> 4033.38 | C677: 569 | D677: 155.8 | E677: 132.7 | F677: 279 | G677: 82 | H677: 441 | I677: 38.8 | J677: 195.25 | K677: 212 | L677: 121.2 | M677: 432.5 | N677: 153.6 | O677: 1130 | P677: 1688 | Q677: 70.7 | R677: 39.25 | S677: 47.8 | T677: 369 | U677: 200 | V677: 189 | W677: 4700.5 | X677: 2751.5 | Y677: 218.5 | Z677: 484 | AA677: 2860 | AB677: 320.6 | AC677: 845 | AD677: 9946 | AE677: 900 | AF677: 1308 | AG677: 16.1811
A678: 44809 | B678: =VLOOKUP(A678,'FTSE All-Share Historical '!A:B,2,FALSE) -> 4029.14 | C678: 546 | D678: 153.2 | E678: 134 | F678: 279 | G678: 77 | H678: 440 | I678: 39.5 | J678: 195.75 | K678: 206 | L678: 118.4 | M678: 423.5 | N678: 153.6 | O678: 1126 | P678: 1666 | Q678: 70.3 | R678: 40 | S678: 46.75 | T678: 391 | U678: 196 | V678: 184.4 | W678: 4732.5 | X678: 2769 | Y678: 218 | Z678: 488.6 | AA678: 2810 | AB678: 320.2 | AC678: 860 | AD678: 9872 | AE678: 859.8 | AF678: 1279 | AG678: 16.6217
A679: 44810 | B679: =VLOOKUP(A679,'FTSE All-Share Historical '!A:B,2,FALSE) -> 4041.41 | C679: 550 | D679: 162.2 | E679: 133.5 | F679: 279 | G679: 80 | H679: 437.5 | I679: 41.46 | J679: 198 | K679: 216 | L679: 114.8 | M679: 421.5 | N679: 164.9 | O679: 1126 | P679: 1686 | Q679: 70.9 | R679: 39.1 | S679: 46.5 | T679: 401 | U679: 202 | V679: 186 | W679: 4733.5 | X679: 2806.5 | Y679: 219.5 | Z679: 511 | AA679: 2700 | AB679: 325 | AC679: 862.5 | AD679: 9894 | AE679: 882.4 | AF679: 1292 | AG679: 15.8921
A680: 44811 | B680: =VLOOKUP(A680,'FTSE All-Share Historical '!A:B,2,FALSE) -> 4011.63 | C680: 540 | D680: 160 | E680: 154.3 | F680: 276 | G680: 81.2 | H680: 426.5 | I680: 41.56 | J680: 195 | K680: 212 | L680: 115 | M680: 426.5 | N680: 156.6 | O680: 1130 | P680: 1672 | Q680: 70.8 | R680: 40 | S680: 46.25 | T680: 454 | U680: 203 | V680: 183.8 | W680: 4632 | X680: 2744 | Y680: 219 | Z680: 505 | AA680: 2690 | AB680: 320.2 | AC680: 845 | AD680: 9882 | AE680: 894.2 | AF680: 1282 | AG680: 17.3369
A681: 44812 | B681: =VLOOKUP(A681,'FTSE All-Share Historical '!A:B,2,FALSE) -> 4025.18 | C681: 538 | D681: 158.6 | E681: 150 | F681: 275 | G681: 85.3 | H681: 429 | I681: 45.24 | J681: 195 | K681: 209 | L681: 116.2 | M681: 437.5 | N681: 162.3 | O681: 1132 | P681: 1630 | Q681: 71.7 | R681: 42 | S681: 46 | T681: 449 | U681: 203 | V681: 177.4 | W681: 4725.5 | X681: 2794.5 | Y681: 222 | Z681: 513.5 | AA681: 2665 | AB681: 323 | AC681: 890 | AD681: 10030 | AE681: 873.4 | AF681: 1266.5 | AG681: 15.8921
A682: 44813 | B682: =VLOOKUP(A682,'FTSE All-Share Historical '!A:B,2,FALSE) -> 4077.03 | C682: 510 | D682: 155 | E682: 154.7 | F682: 276 | G682: 81.8 | H682: 432.5 | I682: 46.14 | J682: 192.5 | K682: 215 | L682: 124.2 | M682: 451 | N682: 165.4 | O682: 1090 | P682: 1670 | Q682: 73 | R682: 41.3 | S682: 45.5 | T682: 480 | U682: 209 | V682: 184 | W682: 4860 | X682: 2926.5 | Y682: 232 | Z682: 521 | AA682: 2725 | AB682: 320.4 | AC682: 845 | AD682: 10135 | AE682: 875.6 | AF682: 1285.5 | AG682: 15.6176
A683: 44816 | B683: =VLOOKUP(A683,'FTSE All-Share Historical '!A:B,2,FALSE) -> 4144.91 | C683: 510 | D683: 157 | E683: 160.3 | F683: 274 | G683: 82.2 | H683: 440 | I683: 45.4 | J683: 194 | K683: 216 | L683: 135 | M683: 455 | N683: 172.2 | O683: 1138 | P683: 1730 | Q683: 75.5 | R683: 42.25 | S683: 44.6 | T683: 578 | U683: 203 | V683: 181.8 | W683: 4944.5 | X683: 2990.5 | Y683: 240.5 | Z683: 538.5 | AA683: 2770 | AB683: 324.6 | AC683: 850 | AD683: 10260 | AE683: 879.8 | AF683: 1316 | AG683: 14.8086
A684: 44817 | B684: =VLOOKUP(A684,'FTSE All-Share Historical '!A:B,2,FALSE) -> 4092.77 | C684: 500 | D684: 159.4 | E684: 154.1 | F684: 274 | G684: 79 | H684: 445 | I684: 43.46 | J684: 192.5 | K684: 217 | L684: 128.2 | M684: 453 | N684: 169 | O684: 1140 | P684: 1660 | Q684: 75.1 | R684: 42.8 | S684: 46 | T684: 578 | U684: 205 | V684: 176 | W684: 4909 | X684: 2920.5 | Y684: 240 | Z684: 523 | AA684: 2720 | AB684: 324 | AC684: 850 | AD684: 10150 | AE684: 862.2 | AF684: 1266.5 | AG684: 14.628
...
