Workbook

Sheet definitions
B1: Element | C1: Descriptor | D1: Guide on what it means in this context
A2: 5 | B2: 22 | C2: Ability to act with poise, in a calm and objective manner | D2: Composure, level headedness, calmness in the face of aversity, remaining constructive and objective
A3: 1 | B3: 33 | C3: Ability to admit mistakes and learn from failure | D3: to understand that failure and mistakes are opportunities for learning, feedback and even creativity. Learning from consequential events or circumstances, having a growth mindset
A4: 19 | B4: 10 | C4: Ability to anticipate and evaluate human reactions | D4: predict that an event will lead to a future state—emotional, mental, physiological and phsycal and then assess and judge the possible reactions of others.
A5: 28 | B5: 13 | C5: Ability to communicate | D5: The capacity to covey messages to others through speaking, writing, reading, listening, reflection using verbal and non-verbal elements to achive the goals of communicating
A6: 14 | B6: 11 | C6: Ability to gain trust and respect | D6: he capacity to be dependable, honest, and accountable, and to demonstrate integrity and expertise. Accountability, honesty, consistency, supportive, open communication, transparancy and reliability.
A7: 13 | B7: 2 | C7: Ability to learn quickly and easily | D7: A quick learner is someone who can understand and process information in a relatively short space of time
A8: 24 | B8: 14 | C8: Ability to listen | D8: the process of receiving, constructing meaning from and responding to spoken and/or nonverbal messages and confirming common understanding
A9: 2 | B9: 3 | C9: Ability to observe, gather, select, and evaluate facts | D9: using all of the senses, as appropriate, to find out about the characteristics, properties and attributes of objects, places and events, critically evaulate, apply reasoning and critical thinking to diverse situations and circumstances
A10: 23 | B10: 17 | C10: Ability to persuade and motivate | D10: the ability to influence other people's thoughts and opinions using convincing arguments and facts; and to encourage and inspireothers to boost productivity and improve work quality
A11: 16 | B11: 32 | C11: Ability to recognize the limitations of one's competence | D11: Knowing where your knowledge, skills and abilities are limited and how they apply to doing or achiving something successfully or efficently
A12: 17 | B12: 16 | C12: Ability to share knowledge, teach, and train people | D12: foster learning in others sharing knowledge and expertise, guiding and nurturing others in their learning
A13: 36 | B13: 6 | C13: Ability to synthesize and generalize | D13: bringing information together from a variety of sources and forming new ideas about the topics and using prior knowledge, skill and understanding to infer possible outcomes.
... A28: 25 | B28: 5 | C28: Inductive and deductive reasoning | D28: Applying reasoning either specific to general or general to specific and abductive, knowing when and where to apply which type of reasoning and when others apply reasoning
B29: 1 | C29: Intellectual ability | D29: a general mental ability for reasoning, planning, solving problems, think abstractly, comprehending complex ideas, and learning
A30: 4 | B30: 18 | C30: Intellectual and emotional maturity | D30: Intellectual maturity is the ability to use logic and reason to learn and solve problems. Emotional maturity is the ability to understand and manage emotions, especially in stressful or conflicting situations
A31: 37 | B31: 24 | C31: Personal drive and initiative | D31: The ability to do what needs to be done without being prompted by others or the willingness to take a fresh approach
A32: 32 | B32: 9 | C32: Respect and tolerance for other people | D32: treating them with dignity and valuing their unique qualities and accepting that people can have different beliefs, ideas, and values.
A33: 29 | B33: 25 | C33: Right degree of self-confidence | D33: a realistic sense of your abilities and a positive belief in yourself. Feeling of trust in yourself that allows you to take on challenges and succeed. knowing strengths and weakness well, and have a positive view of yourself. You set realistic expectations and goals, communicate assertively, and can handle criticism well.
A34: 39 | B34: 19 | C34: Stability of behaviour and action | D34: consistency of behaviour (attitude) and action (deed or doing something). Somewhat reliable
A35: 10 | C35: Economic reasoning (micro/ macro fundamentals)
A36: 15 | C36: Data handling (cleaning, structuring datasets)
A37: 18 | C37: Policy analysis & trade-off thinking
A38: 21 | C38: Data visualisation & dashboards
A39: 27 | C39: Econometrics & causal inference
A40: 31 | C40: Forecasting / scenario analysis
A41: 34 | C41: Tools (Excel + R/Python/Stata/AI tools)

Sheet initial assessment
C2: 0 | D2: 1 | E2: 2 | F2: 3 | G2: 4
B3: Category | C3: I don't know what this is | D3: I am aware of this | E3: I am developing this | F3: I am competent in this | G3: I am strong in this
B4: Economics Thinking Capability | D4: x | I4: =IF(ISNA(MATCH("x",$C4:$G4,0)),0,MATCH("x",$C4:$G4,0)) -> 2 | J4: =IF(I4=0,0,I4-1) -> 1
B5: Economic Skills | D5: x | I5: =IF(ISNA(MATCH("x",$C5:$G5,0)),0,MATCH("x",$C5:$G5,0)) -> 2 | J5: =IF(I5=0,0,I5-1) -> 1
B6: Research & Delivery Skills | E6: x | I6: =IF(ISNA(MATCH("x",$C6:$G6,0)),0,MATCH("x",$C6:$G6,0)) -> 3 | J6: =IF(I6=0,0,I6-1) -> 2
B7: Stakeholder & Customer Awareness | D7: x | I7: =IF(ISNA(MATCH("x",$C7:$G7,0)),0,MATCH("x",$C7:$G7,0)) -> 2 | J7: =IF(I7=0,0,I7-1) -> 1
B8: Collaboration & Ways of Working | E8: x | I8: =IF(ISNA(MATCH("x",$C8:$G8,0)),0,MATCH("x",$C8:$G8,0)) -> 3 | J8: =IF(I8=0,0,I8-1) -> 2
B9: Feedback, Development & Career Management | D9: x | I9: =IF(ISNA(MATCH("x",$C9:$G9,0)),0,MATCH("x",$C9:$G9,0)) -> 2 | J9: =IF(I9=0,0,I9-1) -> 1
B10: Professionalism & Organisational Skills | E10: x | I10: =IF(ISNA(MATCH("x",$C10:$G10,0)),0,MATCH("x",$C10:$G10,0)) -> 3 | J10: =IF(I10=0,0,I10-1) -> 2

Sheet Self-assessment
B1: Quality | D1: area | G1: 0 | H1: 0 | I1: 1 | J1: 2 | K1: 3 | L1: 4 | M1: Comments
H2: I don't know what this is | I2: I am aware of this | J2: I am developing this | K2: I am competent in this | L2: I am strong in this | M2: Justification | O2: Instructions
A3: 1 | B3: Ability to admit mistakes and learn from failure | C3: E | D3: sa | F3: =IF(ISNA(MATCH("x",$H3:$L3,0)),0,MATCH("x",$H3:$L3,0)) -> 3 | G3: =IF(F3=0,0,F3-1) -> 2 | J3: x | M3: Group presentation back in the English-level course showed that I accept judgment from the teacher about the lack of knowledge of an area and change the topic to one that is suitable for my strengths and skills
A4: 2 | B4: Ability to observe, gather, select, and evaluate facts | C4: A | D4: int | F4: =IF(ISNA(MATCH("x",$H4:$L4,0)),0,MATCH("x",$H4:$L4,0)) -> 2 | G4: =IF(F4=0,0,F4-1) -> 1 | I4: x | M4: My ability is still based on researching original ideas and my own assumptions, not by using strategic tools
A5: 3 | B5: Creative imagination and original thinking | C5: A | D5: cr | F5: =IF(ISNA(MATCH("x",$H5:$L5,0)),0,MATCH("x",$H5:$L5,0)) -> 3 | G5: =IF(F5=0,0,F5-1) -> 2 | J5: x | M5: I sometimes have ideas that go beyond the framework or guidelines in the assignment
A6: 4 | B6: Intellectual and emotional maturity | C6: F | D6: re | F6: =IF(ISNA(MATCH("x",$H6:$L6,0)),0,MATCH("x",$H6:$L6,0)) -> 3 | G6: =IF(F6=0,0,F6-1) -> 2 | J6: x | M6: I stay calm during group disagreements, and most of the time, I'm the one who clears the air, leading people to the right track
A7: 5 | B7: Ability to act with poise, in a calm and objective manner | C7: F | D7: is | F7: =IF(ISNA(MATCH("x",$H7:$L7,0)),0,MATCH("x",$H7:$L7,0)) -> 3 | G7: =IF(F7=0,0,F7-1) -> 2 | J7: x | M7: I frequently evaluate ethical implications and emotional factors within case study analyses.
A8: 6 | B8: Extreme honesty | C8: F | D8: eth | F8: =IF(ISNA(MATCH("x",$H8:$L8,0)),0,MATCH("x",$H8:$L8,0)) -> 4 | G8: =IF(F8=0,0,F8-1) -> 3 | K8: x | M8: I always cite sources accurately and never misrepresent data, even when it leads to unfavorable results.
A9: 7 | B9: Ethics and integrity | C9: F | D9: eth | F9: =IF(ISNA(MATCH("x",$H9:$L9,0)),0,MATCH("x",$H9:$L9,0)) -> 3 | G9: =IF(F9=0,0,F9-1) -> 2 | J9: x | M9: I consistently adhere to professional standards and prioritize transparency in all financial reports/assignments
A10: 8 | B10: Facility in oral and written communication | C10: F | D10: co | F10: =IF(ISNA(MATCH("x",$H10:$L10,0)),0,MATCH("x",$H10:$L10,0)) -> 3 | G10: =IF(F10=0,0,F10-1) -> 2 | J10: x | M10: I can deliver presentations with a high level of confidence and can write a well essays within my research and knowledge
A11: 9 | B11: Ability to withstand pressures, and live with frustrations and uncertainties | C11: F | D11: re | F11: =IF(ISNA(MATCH("x",$H11:$L11,0)),0,MATCH("x",$H11:$L11,0)) -> 3 | G11: =IF(F11=0,0,F11-1) -> 2 | J11: x | M11: I possess high resilience to exam pressure, although I remain sensitive to and uncertain about my future career path | O11: 2. in the columns headed 1 to 4 for the question rank yourself by
A12: 10 | B12: Economic reasoning (micro/ macro fundamentals) | C12: A | D12: tech | F12: =IF(ISNA(MATCH("x",$H12:$L12,0)),0,MATCH("x",$H12:$L12,0)) -> 3 | G12: =IF(F12=0,0,F12-1) -> 2 | J12: x | M12: I understand the basic concepts of microeconomics and macroeconomics (supply, demand, GDP, CPI, etc.) from the Basic Economics course, but I do not know the advanced concepts. | O12: 3. Putting x in the column for the quality
A13: 11 | B13: Good judgment | C13: B | D13: int | F13: =IF(ISNA(MATCH("x",$H13:$L13,0)),0,MATCH("x",$H13:$L13,0)) -> 3 | G13: =IF(F13=0,0,F13-1) -> 2 | J13: x | M13: I always strictly follow the school's code, such as never being late, and being the one who sets the rules for group projects | O13: 4. Complete for all of the questions
A14: 12 | B14: Courtesy and good manners | C14: D | D14: is | F14: =IF(ISNA(MATCH("x",$H14:$L14,0)),0,MATCH("x",$H14:$L14,0)) -> 3 | G14: =IF(F14=0,0,F14-1) -> 2 | J14: x | M14: I always maintains a highly professional and formal tone in all written communications and academic submissions | O14: 5. when completed (and not before) review the results on the Results Sheet
A15: 13 | B15: Ability to learn quickly and easily | C15: E | D15: int | F15: =IF(ISNA(MATCH("x",$H15:$L15,0)),0,MATCH("x",$H15:$L15,0)) -> 3 | G15: =IF(F15=0,0,F15-1) -> 2 | J15: x | M15: I can demonstrates rapid skill acquisition through self-taught programming and the independent integration of AI tools into daily workflows
A16: 14 | B16: Ability to gain trust and respect | C16: C | D16: is | F16: =IF(ISNA(MATCH("x",$H16:$L16,0)),0,MATCH("x",$H16:$L16,0)) -> 4 | G16: =IF(F16=0,0,F16-1) -> 3 | K16: x | M16: Group members say they trust me to complete my part on time and lead the group to focus and finish projects on time
A17: 15 | B17: Data handling (cleaning, structuring datasets) | C17: A1 | D17: tech | F17: =IF(ISNA(MATCH("x",$H17:$L17,0)),0,MATCH("x",$H17:$L17,0)) -> 2 | G17: =IF(F17=0,0,F17-1) -> 1 | I17: x | M17: I can use Excel and other tools to illustrate simple datasets but not large and big datasets
A18: 16 | B18: Ability to recognize the limitations of one's competence | C18: F | D18: sa | F18: =IF(ISNA(MATCH("x",$H18:$L18,0)),0,MATCH("x",$H18:$L18,0)) -> 3 | G18: =IF(F18=0,0,F18-1) -> 2 | J18: x | M18: I am aware of my current knowledge boundaries as a first-year student and proactively seek guidance when facing complex tasks beyond my current training.
A19: 17 | B19: Ability to share knowledge, teach, and train people | C19: B | D19: co | F19: =IF(ISNA(MATCH("x",$H19:$L19,0)),0,MATCH("x",$H19:$L19,0)) -> 3 | G19: =IF(F19=0,0,F19-1) -> 2 | J19: x | M19: I can explain the basic concepts of the Banking and Finance major to my friends and can taught them how to do the work correctly
A20: 18 | B20: Policy analysis & trade-off thinking | C20: A | D20: tech | F20: =IF(ISNA(MATCH("x",$H20:$L20,0)),0,MATCH("x",$H20:$L20,0)) -> 2 | G20: =IF(F20=0,0,F20-1) -> 1 | I20: x | M20: I understand the definition of trade-offs and can apply it when making my daily decisions but have not applied them in real policy or real world situations
A21: 19 | B21: Ability to anticipate and evaluate human reactions | C21: C | D21: is | F21: =IF(ISNA(MATCH("x",$H21:$L21,0)),0,MATCH("x",$H21:$L21,0)) -> 3 | G21: =IF(F21=0,0,F21-1) -> 2 | J21: x | M21: I can sense the frustration, anger, and confusion in my group and I know how to encourage, explain to them
A22: 20 | B22: Genuine desire to help others | C22: C | D22: eth | F22: =IF(ISNA(MATCH("x",$H22:$L22,0)),0,MATCH("x",$H22:$L22,0)) -> 3 | G22: =IF(F22=0,0,F22-1) -> 2 | J22: x | M22: I actively help my peers during group projects or with some concepts that they misunderstanding
A23: 21 | B23: Data visualisation & dashboards | C23: A1 | D23: tech | F23: =IF(ISNA(MATCH("x",$H23:$L23,0)),0,MATCH("x",$H23:$L23,0)) -> 2 | G23: =IF(F23=0,0,F23-1) -> 1 | I23: x | M23: I cannot create complex data visualisation but can create and understand the basic ones
A24: 22 | B24: Healthy ambition | C24: E | D24: re | F24: =IF(ISNA(MATCH("x",$H24:$L24,0)),0,MATCH("x",$H24:$L24,0)) -> 3 | G24: =IF(F24=0,0,F24-1) -> 2 | J24: x | M24: I am motivated to build a career that can benefits my family and my hobby
A25: 23 | B25: Ability to persuade and motivate | C25: C | D25: is | F25: =IF(ISNA(MATCH("x",$H25:$L25,0)),0,MATCH("x",$H25:$L25,0)) -> 3 | G25: =IF(F25=0,0,F25-1) -> 2 | J25: x | M25: I can effectively communicate strategic ideas during group discussions to align team objectives
A26: 24 | B26: Ability to listen | C26: D | D26: co | F26: =IF(ISNA(MATCH("x",$H26:$L26,0)),0,MATCH("x",$H26:$L26,0)) -> 3 | G26: =IF(F26=0,0,F26-1) -> 2 | J26: x | M26: I listen carefully to what other people say and can provide them with advice or suggestions
A27: 25 | B27: Inductive and deductive reasoning | C27: A | D27: int | F27: =IF(ISNA(MATCH("x",$H27:$L27,0)),0,MATCH("x",$H27:$L27,0)) -> 3 | G27: =IF(F27=0,0,F27-1) -> 2 | J27: x | M27: I can apply logical reasoning to most of my works or projects, using evidence to support my point of view
A28: 26 | B28: Ability to understand people and work with them | C28: C | D28: is | F28: =IF(ISNA(MATCH("x",$H28:$L28,0)),0,MATCH("x",$H28:$L28,0)) -> 3 | G28: =IF(F28=0,0,F28-1) -> 2 | J28: x | M28: I can work with other people and even work well with people whose characteristics I know
A29: 27 | B29: Econometrics & causal inference | C29: A1 | D29: tech | F29: =IF(ISNA(MATCH("x",$H29:$L29,0)),0,MATCH("x",$H29:$L29,0)) -> 2 | G29: =IF(F29=0,0,F29-1) -> 1 | I29: x | M29: I have studied the basic concepts, such as showing relationships via charts and baseline statistics but cannot do complex or complicate things
A30: 28 | B30: Ability to communicate | C30: F | D30: co | F30: =IF(ISNA(MATCH("x",$H30:$L30,0)),0,MATCH("x",$H30:$L30,0)) -> 3 | G30: =IF(F30=0,0,F30-1) -> 2 | J30: x | M30: I can communicate effectively with my friends or classmates, and I am able to speak or use both Vietnamese and English fluently.
A31: 29 | B31: Right degree of self-confidence | C31: F | D31: sa | F31: =IF(ISNA(MATCH("x",$H31:$L31,0)),0,MATCH("x",$H31:$L31,0)) -> 3 | G31: =IF(F31=0,0,F31-1) -> 2 | J31: x | M31: I maintain a balanced level of self-confidence, being certain of my foundational knowledge while remaining humble and open to feedback from professors and senior peers.
A32: 30 | B32: Independence in drawing unbiased conclusions | C32: A | D32: eth | F32: =IF(ISNA(MATCH("x",$H32:$L32,0)),0,MATCH("x",$H32:$L32,0)) -> 2 | G32: =IF(F32=0,0,F32-1) -> 1 | I32: x | M32: I am can analyse basic financial data based on objective evidence rather than personal assumptions, while still relying on academic frameworks to ensure my conclusions remain impartial
A33: 31 | B33: Forecasting / scenario analysis | C33: A1 | D33: tech | F33: =IF(ISNA(MATCH("x",$H33:$L33,0)),0,MATCH("x",$H33:$L33,0)) -> 2 | G33: =IF(F33=0,0,F33-1) -> 1 | I33: x | M33: I cannot make predictions or forecasts yet but I can calculate the suitable financial data, financial ratios
A34: 32 | B34: Respect and tolerance for other people | C34: D | D34: is | F34: =IF(ISNA(MATCH("x",$H34:$L34,0)),0,MATCH("x",$H34:$L34,0)) -> 3 | G34: =IF(F34=0,0,F34-1) -> 2 | J34: x | M34: I frequently incorporate ethical implications and diverse perspectives into comprehensive case study evaluations
A35: 33 | B35: Courage, initiative, and perseverance in action | C35: F | D35: re | F35: =IF(ISNA(MATCH("x",$H35:$L35,0)),0,MATCH("x",$H35:$L35,0)) -> 2 | G35: =IF(F35=0,0,F35-1) -> 1 | I35: x | M35: I like to study and do things on my own but I can still work in a team and communicate effectively
A36: 34 | B36: Tools (Excel + R/Python/Stata/AI tools) | C36: A1 | D36: tech | F36: =IF(ISNA(MATCH("x",$H36:$L36,0)),0,MATCH("x",$H36:$L36,0)) -> 3 | G36: =IF(F36=0,0,F36-1) -> 2 | J36: x | M36: I am highly proficient in utilising advanced AI tools, Python, and web development frameworks to automate tasks and build applications but I'm still learning more
A37: 35 | B37: Flexibility and adaptability to changed conditions | C37: F | D37: re | F37: =IF(ISNA(MATCH("x",$H37:$L37,0)),0,MATCH("x",$H37:$L37,0)) -> 3 | G37: =IF(F37=0,0,F37-1) -> 2 | J37: x | M37: I am learning to adjust my study methods and technical approaches when facing new academic challenges or unexpected situations in my personal project
A38: 36 | B38: Ability to synthesize and generalize | C38: A | D38: int | F38: =IF(ISNA(MATCH("x",$H38:$L38,0)),0,MATCH("x",$H38:$L38,0)) -> 3 | G38: =IF(F38=0,0,F38-1) -> 2 | J38: x | M38: I can summarise the contents of every module that I learned into a checklist to study more effeciency
A39: 37 | B39: Personal drive and initiative | C39: E | D39: re | F39: =IF(ISNA(MATCH("x",$H39:$L39,0)),0,MATCH("x",$H39:$L39,0)) -> 3 | G39: =IF(F39=0,0,F39-1) -> 2 | J39: x | M39: I set my goals for every module that I enrol in, and I try my best to achieve them. Moreover, I am proactively looking for and learning AI tools to enhance my hobby
A40: 38 | B40: Entrepreneurial spirit | C40: E | D40: cr | F40: =IF(ISNA(MATCH("x",$H40:$L40,0)),0,MATCH("x",$H40:$L40,0)) -> 2 | G40: =IF(F40=0,0,F40-1) -> 1 | I40: x | M40: I have started a project on my own but I'm lacking sufficient skills, so I will try to learn it through my teacher's guidelines
A41: 39 | B41: Stability of behaviour and action | C41: F | D41: re | F41: =IF(ISNA(MATCH("x",$H41:$L41,0)),0,MATCH("x",$H41:$L41,0)) -> 3 | G41: =IF(F41=0,0,F41-1) -> 2 | J41: x | M41: I maintain a consistent and professional work ethic, ensuring that my academic assignments and personal projects are handled with steady reliability
B43: Competences/Capabilities as listed by Canadian Management Consultancy Competence Framework
B44: https://www.cmc-canada.ca/web/default/files/CMC_Competency_Framework_2018.pdf

Sheet Job Description
B1: Quality | D1: area | G1: 0 | H1: 0 | I1: 1 | J1: 2 | K1: 3 | L1: 4 | M1: Comments
H2: Job does not require this | I2: job requires me to be aware of this | J2: job requires me to be developing this | K2: job requires me to be competent in this | L2: job requires me to be strongly competent in this | M2: Justification | O2: Instructions
A3: 1 | B3: Ability to admit mistakes and learn from failure | C3: E | D3: sa | F3: =IF(ISNA(MATCH("x",$H3:$L3,0)),0,MATCH("x",$H3:$L3,0)) -> 5 | G3: =IF(F3=0,0,F3-1) -> 4 | L3: x | M3: Essential. A hidden error in a financial model (e.g., DCF or LBO) can cost millions. Owning mistakes immediately prevents compounding financial disasters.
A4: 2 | B4: Ability to observe, gather, select, and evaluate facts | C4: A | D4: int | F4: =IF(ISNA(MATCH("x",$H4:$L4,0)),0,MATCH("x",$H4:$L4,0)) -> 5 | G4: =IF(F4=0,0,F4-1) -> 4 | L4: x | M4: The absolute core of due diligence. Analysts must sift through 10-Ks, earnings call transcripts, and market data to extract only what impacts valuation.
A5: 3 | B5: Creative imagination and original thinking | C5: A | D5: cr | F5: =IF(ISNA(MATCH("x",$H5:$L5,0)),0,MATCH("x",$H5:$L5,0)) -> 3 | G5: =IF(F5=0,0,F5-1) -> 2 | J5: x | M5: Finance is heavily regulated. While creative problem-solving in structuring deals is nice, standard, compliant methodologies (GAAP/IFRS) are prioritised over "imagination."
A6: 4 | B6: Intellectual and emotional maturity | C6: F | D6: re | F6: =IF(ISNA(MATCH("x",$H6:$L6,0)),0,MATCH("x",$H6:$L6,0)) -> 4 | G6: =IF(F6=0,0,F6-1) -> 3 | K6: x | M6: Required to handle intense market volatility, strict earnings-season deadlines, and harsh feedback from senior portfolio managers or executives.
A7: 5 | B7: Ability to act with poise, in a calm and objective manner | C7: F | D7: is | F7: =IF(ISNA(MATCH("x",$H7:$L7,0)),0,MATCH("x",$H7:$L7,0)) -> 5 | G7: =IF(F7=0,0,F7-1) -> 4 | L7: x | M7: Markets panic; analysts must not. Objectivity is crucial to ensure recommendations are based on data, not market hysteria or personal bias.
A8: 6 | B8: Extreme honesty | C8: F | D8: eth | F8: =IF(ISNA(MATCH("x",$H8:$L8,0)),0,MATCH("x",$H8:$L8,0)) -> 5 | G8: =IF(F8=0,0,F8-1) -> 4 | L8: x | M8: Non-negotiable. Any misrepresentation of financial health or data manipulation leads to severe regulatory and legal consequences (SEC/FCA compliance).
A9: 7 | B9: Ethics and integrity | C9: F | D9: eth | F9: =IF(ISNA(MATCH("x",$H9:$L9,0)),0,MATCH("x",$H9:$L9,0)) -> 5 | G9: =IF(F9=0,0,F9-1) -> 4 | L9: x | M9: The foundation of banking. Strict adherence to confidentiality (preventing insider trading) and ethical guidelines is a zero-tolerance area.
A10: 8 | B10: Facility in oral and written communication | C10: F | D10: co | F10: =IF(ISNA(MATCH("x",$H10:$L10,0)),0,MATCH("x",$H10:$L10,0)) -> 5 | G10: =IF(F10=0,0,F10-1) -> 4 | L10: x | M10: Must be able to translate complex quantitative models into clear, digestible investment pitches and executive summaries.
A11: 9 | B11: Ability to withstand pressures, and live with frustrations and uncertainties | C11: F | D11: re | F11: =IF(ISNA(MATCH("x",$H11:$L11,0)),0,MATCH("x",$H11:$L11,0)) -> 5 | G11: =IF(F11=0,0,F11-1) -> 4 | L11: x | M11: High-stakes deals and M&A activities involve long hours, ambiguous data, and constant pressure. Resilience is a baseline requirement. | O11: 2. in the columns headed 1 to 4 for the question rank yourself by
A12: 10 | B12: Economic reasoning (micro/ macro fundamentals) | C12: A | D12: tech | F12: =IF(ISNA(MATCH("x",$H12:$L12,0)),0,MATCH("x",$H12:$L12,0)) -> 5 | G12: =IF(F12=0,0,F12-1) -> 4 | L12: x | M12: Must be able to understand how inflation, interest rates (central bank policies), and microeconomic shifts directly impact asset valuations. | O12: 3. Putting 1 in the column for the quality
A13: 11 | B13: Good judgment | C13: B | D13: int | F13: =IF(ISNA(MATCH("x",$H13:$L13,0)),0,MATCH("x",$H13:$L13,0)) -> 5 | G13: =IF(F13=0,0,F13-1) -> 4 | L13: x | M13: Required when data is incomplete. Will often have to make sound assumptions in forecasting models regarding growth rates or terminal values. | O13: 4. Complete for all of the questions
A14: 12 | B14: Courtesy and good manners | C14: D | D14: is | F14: =IF(ISNA(MATCH("x",$H14:$L14,0)),0,MATCH("x",$H14:$L14,0)) -> 4 | G14: =IF(F14=0,0,F14-1) -> 3 | K14: x | M14: Important for maintaining professional internal relations and client-facing interactions (e.g., meeting with company management during equity research). | O14: 5. when completed (and not before) review the results on the Results Sheet
A15: 13 | B15: Ability to learn quickly and easily | C15: E | D15: int | F15: =IF(ISNA(MATCH("x",$H15:$L15,0)),0,MATCH("x",$H15:$L15,0)) -> 5 | G15: =IF(F15=0,0,F15-1) -> 4 | L15: x | M15: Financial regulations, software tools, and market dynamics evolve rapidly. Adaptability to new information is highly prized.
A16: 14 | B16: Ability to gain trust and respect | C16: C | D16: is | F16: =IF(ISNA(MATCH("x",$H16:$L16,0)),0,MATCH("x",$H16:$L16,0)) -> 4 | G16: =IF(F16=0,0,F16-1) -> 3 | K16: x | M16: Necessary to build credibility with senior analysts, stakeholders, and clients who are relying on your financial advice.
A17: 15 | B17: Data handling (cleaning, structuring datasets) | C17: A1 | D17: tech | F17: =IF(ISNA(MATCH("x",$H17:$L17,0)),0,MATCH("x",$H17:$L17,0)) -> 5 | G17: =IF(F17=0,0,F17-1) -> 4 | L17: x | M17: A significant portion of early career will be spent cleaning raw financial data from Bloomberg, Refinitiv, or internal databases before analysis.
A18: 16 | B18: Ability to recognize the limitations of one's competence | C18: F | D18: sa | F18: =IF(ISNA(MATCH("x",$H18:$L18,0)),0,MATCH("x",$H18:$L18,0)) -> 5 | G18: =IF(F18=0,0,F18-1) -> 4 | L18: x | M18: Highly critical. An analyst must know when a financial model, tax implication, or transaction structure exceeds their current expertise. Proactively escalating complex issues to senior associates prevents catastrophic financial errors. Guesswork in banking is unacceptable.
A19: 17 | B19: Ability to share knowledge, teach, and train people | C19: B | D19: co | F19: =IF(ISNA(MATCH("x",$H19:$L19,0)),0,MATCH("x",$H19:$L19,0)) -> 2 | G19: =IF(F19=0,0,F19-1) -> 1 | I19: x | M19: Not expected at the junior or entry-level. This becomes relevant only when transitioning to an Associate or VP role.
A20: 18 | B20: Policy analysis & trade-off thinking | C20: A | D20: tech | F20: =IF(ISNA(MATCH("x",$H20:$L20,0)),0,MATCH("x",$H20:$L20,0)) -> 4 | G20: =IF(F20=0,0,F20-1) -> 3 | K20: x | M20: Important for assessing how new banking regulations, tax laws, or fiscal policies will affect a company's bottom line or investment strategy.
A21: 19 | B21: Ability to anticipate and evaluate human reactions | C21: C | D21: is | F21: =IF(ISNA(MATCH("x",$H21:$L21,0)),0,MATCH("x",$H21:$L21,0)) -> 3 | G21: =IF(F21=0,0,F21-1) -> 2 | J21: x | M21: Helpful for understanding market sentiment or consumer behavior, but secondary to hard quantitative metrics for a pure analyst.
A22: 20 | B22: Genuine desire to help others | C22: C | D22: eth | F22: =IF(ISNA(MATCH("x",$H22:$L22,0)),0,MATCH("x",$H22:$L22,0)) -> 2 | G22: =IF(F22=0,0,F22-1) -> 1 | I22: x | M22: Great for team culture, but corporate finance is fundamentally driven by ROI, profitability, and analytical rigor.
A23: 21 | B23: Data visualisation & dashboards | C23: A1 | D23: tech | F23: =IF(ISNA(MATCH("x",$H23:$L23,0)),0,MATCH("x",$H23:$L23,0)) -> 5 | G23: =IF(F23=0,0,F23-1) -> 4 | L23: x | M23: Highly demanded. Must be able to use tools like PowerBI, Tableau, or advanced Excel charting to present financial health dynamically to the BOD.
A24: 22 | B24: Healthy ambition | C24: E | D24: re | F24: =IF(ISNA(MATCH("x",$H24:$L24,0)),0,MATCH("x",$H24:$L24,0)) -> 4 | G24: =IF(F24=0,0,F24-1) -> 3 | K24: x | M24: The finance sector is notoriously competitive. Drive is necessary for career progression and having the stamina to tackle complex, high-profile deals.
A25: 23 | B25: Ability to persuade and motivate | C25: C | D25: is | F25: =IF(ISNA(MATCH("x",$H25:$L25,0)),0,MATCH("x",$H25:$L25,0)) -> 4 | G25: =IF(F25=0,0,F25-1) -> 3 | K25: x | M25: Crucial when defending investment thesis or budget recommendations during investment committee meetings.
A26: 24 | B26: Ability to listen | C26: D | D26: co | F26: =IF(ISNA(MATCH("x",$H26:$L26,0)),0,MATCH("x",$H26:$L26,0)) -> 4 | G26: =IF(F26=0,0,F26-1) -> 3 | K26: x | M26: Essential for accurately capturing the requirements of Managing Directors, clients, or understanding the nuances in an earnings call.
A27: 25 | B27: Inductive and deductive reasoning | C27: A | D27: int | F27: =IF(ISNA(MATCH("x",$H27:$L27,0)),0,MATCH("x",$H27:$L27,0)) -> 5 | G27: =IF(F27=0,0,F27-1) -> 4 | L27: x | M27: The essence of financial analysis: deducing corporate health from balance sheets and inducing market trends from macroeconomic indicators.
A28: 26 | B28: Ability to understand people and work with them | C28: C | D28: is | F28: =IF(ISNA(MATCH("x",$H28:$L28,0)),0,MATCH("x",$H28:$L28,0)) -> 4 | G28: =IF(F28=0,0,F28-1) -> 3 | K28: x | M28: Cross-functional collaboration is frequent. Will need to gather inputs from accounting, operations, and sales to build accurate budgets (FP&A).
A29: 27 | B29: Econometrics & causal inference | C29: A1 | D29: tech | F29: =IF(ISNA(MATCH("x",$H29:$L29,0)),0,MATCH("x",$H29:$L29,0)) -> 3 | G29: =IF(F29=0,0,F29-1) -> 2 | J29: x | M29: Nice to have. More critical for Quants or Macro Economists, though highly beneficial for advanced predictive financial modeling.
A30: 28 | B30: Ability to communicate | C30: F | D30: co | F30: =IF(ISNA(MATCH("x",$H30:$L30,0)),0,MATCH("x",$H30:$L30,0)) -> 5 | G30: =IF(F30=0,0,F30-1) -> 4 | L30: x | M30: Clarity, conciseness, and the ability to tailor your financial jargon to non-financial stakeholders are vital.
A31: 29 | B31: Right degree of self-confidence | C31: F | D31: sa | F31: =IF(ISNA(MATCH("x",$H31:$L31,0)),0,MATCH("x",$H31:$L31,0)) -> 4 | G31: =IF(F31=0,0,F31-1) -> 3 | K31: x | M31: Must confidently back up financial models and assumptions when challenged aggressively by senior executives.
A32: 30 | B32: Independence in drawing unbiased conclusions | C32: A | D32: eth | F32: =IF(ISNA(MATCH("x",$H32:$L32,0)),0,MATCH("x",$H32:$L32,0)) -> 5 | G32: =IF(F32=0,0,F32-1) -> 4 | L32: x | M32: Must avoid confirmation bias. Valuation must reflect reality, not what the management team or directors hope the numbers say.
A33: 31 | B33: Forecasting / scenario analysis | C33: A1 | D33: tech | F33: =IF(ISNA(MATCH("x",$H33:$L33,0)),0,MATCH("x",$H33:$L33,0)) -> 5 | G33: =IF(F33=0,0,F33-1) -> 4 | L33: x | M33: The absolute core of FP&A and Investment Banking. Building 3-statement models, DCFs, and running sensitivity/stress tests is a daily job.
A34: 32 | B34: Respect and tolerance for other people | C34: D | D34: is | F34: =IF(ISNA(MATCH("x",$H34:$L34,0)),0,MATCH("x",$H34:$L34,0)) -> 4 | G34: =IF(F34=0,0,F34-1) -> 3 | K34: x | M34: A baseline professional standard to maintain a healthy, compliant, and collaborative corporate environment.
A35: 33 | B35: Courage, initiative, and perseverance in action | C35: F | D35: re | F35: =IF(ISNA(MATCH("x",$H35:$L35,0)),0,MATCH("x",$H35:$L35,0)) -> 4 | G35: =IF(F35=0,0,F35-1) -> 3 | K35: x | M35: Required to dig deeper into financial discrepancies, flag potential risks, or advocate for accurate financial realities even if unpopular.
A36: 34 | B36: Tools (Excel + R/Python/Stata/AI tools) | C36: A1 | D36: tech | F36: =IF(ISNA(MATCH("x",$H36:$L36,0)),0,MATCH("x",$H36:$L36,0)) -> 5 | G36: =IF(F36=0,0,F36-1) -> 4 | L36: x | M36: Elite Excel skills are mandatory (without using a mouse). Python/SQL and AI tools are rapidly becoming industry standards for automating workflows.
A37: 35 | B37: Flexibility and adaptability to changed conditions | C37: F | D37: re | F37: =IF(ISNA(MATCH("x",$H37:$L37,0)),0,MATCH("x",$H37:$L37,0)) -> 5 | G37: =IF(F37=0,0,F37-1) -> 4 | L37: x | M37: Markets pivot instantly. Must be able to rapidly update your financial models based on breaking news, earnings misses, or sudden macroeconomic shifts.
A38: 36 | B38: Ability to synthesize and generalize | C38: A | D38: int | F38: =IF(ISNA(MATCH("x",$H38:$L38,0)),0,MATCH("x",$H38:$L38,0)) -> 5 | G38: =IF(F38=0,0,F38-1) -> 4 | L38: x | M38: Essential. The core of this role involves digesting massive volumes of raw data, 10-K reports, and market research, then distilling them into a concise, one-page executive summary or a clear investment thesis for the Board of Directors.
A39: 37 | B39: Personal drive and initiative | C39: E | D39: re | F39: =IF(ISNA(MATCH("x",$H39:$L39,0)),0,MATCH("x",$H39:$L39,0)) -> 4 | G39: =IF(F39=0,0,F39-1) -> 3 | K39: x | M39: Proactively identifying cost-saving opportunities, automating a slow process, or pitching a unique investment idea adds immense value.
A40: 38 | B40: Entrepreneurial spirit | C40: E | D40: cr | F40: =IF(ISNA(MATCH("x",$H40:$L40,0)),0,MATCH("x",$H40:$L40,0)) -> 3 | G40: =IF(F40=0,0,F40-1) -> 2 | J40: x | M40: Nice to have, but secondary for an analyst. While proactive problem-solving and finding new efficiencies are valued, traditional banking prioritizes strict regulatory compliance, risk mitigation, and adherence to established financial methodologies over aggressive, entrepreneurial risk-taking.
A41: 39 | B41: Stability of behaviour and action | C41: F | D41: re | F41: =IF(ISNA(MATCH("x",$H41:$L41,0)),0,MATCH("x",$H41:$L41,0)) -> 4 | G41: =IF(F41=0,0,F41-1) -> 3 | K41: x | M41: Consistency and reliability are heavily prized. Stakeholders need to know the output will be consistently accurate and dependable.
B43: Competences/Capabilities as listed by Canadian Management Consultancy Competence Framework
B44: https://www.cmc-canada.ca/web/default/files/CMC_Competency_Framework_2018.pdf

Sheet Assessment of your Programme
B1: Quality | D1: area | G1: 0 | H1: 0 | I1: 1 | J1: 2 | K1: 3 | L1: 4 | M1: Comments
B2: Are these competences and skills covered by any module across your first year? | H2: not covered at all on my programme | I2: I am aware of this on my programme (but I have not done it) | J2: I am developing this with modules on my programme | K2: I am competent in this through work on my programme | L2: The programme ensures strong competency in this | M2: Outline the modules and the tasks in those modules where you either learnt or developed the skill and competence you claim | O2: Instructions
A3: 1 | B3: Ability to admit mistakes and learn from failure | C3: E | D3: sa | F3: =IF(ISNA(MATCH("x",$H3:$L3,0)),0,MATCH("x",$H3:$L3,0)) -> 4 | G3: =IF(F3=0,0,F3-1) -> 3 | K3: x | M3: Developed through "Working with feedback" and "Career management" topics in the PSBF module
A4: 2 | B4: Ability to observe, gather, select, and evaluate facts | C4: A | D4: int | F4: =IF(ISNA(MATCH("x",$H4:$L4,0)),0,MATCH("x",$H4:$L4,0)) -> 4 | G4: =IF(F4=0,0,F4-1) -> 3 | K4: x | M4: Practised extensively in EBF (macroeconomic measurement) and FIM (interpreting financial news and market data)
A5: 3 | B5: Creative imagination and original thinking | C5: A | D5: cr | F5: =IF(ISNA(MATCH("x",$H5:$L5,0)),0,MATCH("x",$H5:$L5,0)) -> 3 | G5: =IF(F5=0,0,F5-1) -> 2 | J5: x | M5: Cultivated via "Design thinking and wicked problems" covered in weeks 5 and 6 of PSBF
A6: 4 | B6: Intellectual and emotional maturity | C6: F | D6: re | F6: =IF(ISNA(MATCH("x",$H6:$L6,0)),0,MATCH("x",$H6:$L6,0)) -> 3 | G6: =IF(F6=0,0,F6-1) -> 2 | J6: x | M6: Developed indirectly by managing the rigorous independent study and complex theoretical models in EBF and FIM
A7: 5 | B7: Ability to act with poise, in a calm and objective manner | C7: F | D7: is | F7: =IF(ISNA(MATCH("x",$H7:$L7,0)),0,MATCH("x",$H7:$L7,0)) -> 3 | G7: =IF(F7=0,0,F7-1) -> 2 | J7: x | M7: Developed through handling strict assessment deadlines and objective quantitative analyses in AFDM and PSBF
A8: 6 | B8: Extreme honesty | C8: F | D8: eth | F8: =IF(ISNA(MATCH("x",$H8:$L8,0)),0,MATCH("x",$H8:$L8,0)) -> 4 | G8: =IF(F8=0,0,F8-1) -> 3 | K8: x | M8: Underpinned by the university's strict academic integrity rules and the study of financial regulation in FIM
A9: 7 | B9: Ethics and integrity | C9: F | D9: eth | F9: =IF(ISNA(MATCH("x",$H9:$L9,0)),0,MATCH("x",$H9:$L9,0)) -> 4 | G9: =IF(F9=0,0,F9-1) -> 3 | K9: x | M9: Explored theoretically through financial regulation, bubbles, and crash phenomena discussed in FIM
A10: 8 | B10: Facility in oral and written communication | C10: F | D10: co | F10: =IF(ISNA(MATCH("x",$H10:$L10,0)),0,MATCH("x",$H10:$L10,0)) -> 4 | G10: =IF(F10=0,0,F10-1) -> 3 | K10: x | M10: Developed by articulating economic concepts (EBF) and presenting financial evaluations in professional contexts (AFDM)
A11: 9 | B11: Ability to withstand pressures, and live with frustrations and uncertainties | C11: F | D11: re | F11: =IF(ISNA(MATCH("x",$H11:$L11,0)),0,MATCH("x",$H11:$L11,0)) -> 3 | G11: =IF(F11=0,0,F11-1) -> 2 | J11: x | M11: Fostered through tackling "wicked problems" (PSBF) and navigating challenging first-year transitions | O11: 2 in the columns headed 1 to 4 for the question rank yourself by
A12: 10 | B12: Economic reasoning (micro/ macro fundamentals) | C12: A | D12: tech | F12: =IF(ISNA(MATCH("x",$H12:$L12,0)),0,MATCH("x",$H12:$L12,0)) -> 5 | G12: =IF(F12=0,0,F12-1) -> 4 | L12: x | M12: Core focus of the EBF module, covering consumer/firm theory, macroeconomic measurement, and policy | O12: 3 Putting 1 in the column for the quality
A13: 11 | B13: Good judgment | C13: B | D13: int | F13: =IF(ISNA(MATCH("x",$H13:$L13,0)),0,MATCH("x",$H13:$L13,0)) -> 4 | G13: =IF(F13=0,0,F13-1) -> 3 | K13: x | M13: Central to AFDM, where students must evaluate investment opportunities and make informed financial recommendations | O13: 4 Complete for all of the questions
A14: 12 | B14: Courtesy and good manners | C14: D | D14: is | F14: =IF(ISNA(MATCH("x",$H14:$L14,0)),0,MATCH("x",$H14:$L14,0)) -> 3 | G14: =IF(F14=0,0,F14-1) -> 2 | J14: x | M14: Developed through group collaboration, classroom participation, and interaction with module leaders across all subjects | O14: 5 when completed (and not before) review the results on the Results Sheet
A15: 13 | B15: Ability to learn quickly and easily | C15: E | D15: int | F15: =IF(ISNA(MATCH("x",$H15:$L15,0)),0,MATCH("x",$H15:$L15,0)) -> 4 | G15: =IF(F15=0,0,F15-1) -> 3 | K15: x | M15: Essential for grasping fast-paced technical skills like Python programming from scratch in PSBF
A16: 14 | B16: Ability to gain trust and respect | C16: C | D16: is | F16: =IF(ISNA(MATCH("x",$H16:$L16,0)),0,MATCH("x",$H16:$L16,0)) -> 0 | G16: =IF(F16=0,0,F16-1) -> 0 | M16: Built through reliable participation in applied group scenarios and peer interactions, particularly in AFDM and FIM
A17: 15 | B17: Data handling (cleaning, structuring datasets) | C17: A1 | D17: tech | F17: =IF(ISNA(MATCH("x",$H17:$L17,0)),0,MATCH("x",$H17:$L17,0)) -> 4 | G17: =IF(F17=0,0,F17-1) -> 3 | K17: x | M17: Strongly emphasized in PSBF, using packages like NumPy, Pandas, and SciPy to manage data
A18: 16 | B18: Ability to recognize the limitations of one's competence | C18: F | D18: sa | F18: =IF(ISNA(MATCH("x",$H18:$L18,0)),0,MATCH("x",$H18:$L18,0)) -> 3 | G18: =IF(F18=0,0,F18-1) -> 2 | J18: x | M18: Encouraged through engaging with formative feedback loops and continuous development in PSBF
A19: 17 | B19: Ability to share knowledge, teach, and train people | C19: B | D19: co | F19: =IF(ISNA(MATCH("x",$H19:$L19,0)),0,MATCH("x",$H19:$L19,0)) -> 2 | G19: =IF(F19=0,0,F19-1) -> 1 | I19: x | M19: Not formally taught, but students are aware of it through peer-to-peer discussions and group study sessions
A20: 18 | B20: Policy analysis & trade-off thinking | C20: A | D20: tech | F20: =IF(ISNA(MATCH("x",$H20:$L20,0)),0,MATCH("x",$H20:$L20,0)) -> 4 | G20: =IF(F20=0,0,F20-1) -> 3 | K20: x | M20: Covered via macroeconomic policy in EBF and the study of financial systems/economic policy impacts in FIM
A21: 19 | B21: Ability to anticipate and evaluate human reactions | C21: C | D21: is | F21: =IF(ISNA(MATCH("x",$H21:$L21,0)),0,MATCH("x",$H21:$L21,0)) -> 3 | G21: =IF(F21=0,0,F21-1) -> 2 | J21: x | M21: Explored conceptually through "Design thinking" frameworks in PSBF
A22: 20 | B22: Genuine desire to help others | C22: C | D22: eth | F22: =IF(ISNA(MATCH("x",$H22:$L22,0)),0,MATCH("x",$H22:$L22,0)) -> 2 | G22: =IF(F22=0,0,F22-1) -> 1 | I22: x | M22: Indirectly supported by the collaborative nature of the university environment, though not a specific module outcome
A23: 21 | B23: Data visualisation & dashboards | C23: A1 | D23: tech | F23: =IF(ISNA(MATCH("x",$H23:$L23,0)),0,MATCH("x",$H23:$L23,0)) -> 5 | G23: =IF(F23=0,0,F23-1) -> 4 | L23: x | M23: Explicitly taught in PSBF using Matplotlib and techniques for "telling stories with numbers" (graphical analysis)
A24: 22 | B24: Healthy ambition | C24: E | D24: re | F24: =IF(ISNA(MATCH("x",$H24:$L24,0)),0,MATCH("x",$H24:$L24,0)) -> 3 | G24: =IF(F24=0,0,F24-1) -> 2 | J24: x | M24: Addressed directly in the "Career management" and "What jobs do economic analysts do?" lectures in PSBF
A25: 23 | B25: Ability to persuade and motivate | C25: C | D25: is | F25: =IF(ISNA(MATCH("x",$H25:$L25,0)),0,MATCH("x",$H25:$L25,0)) -> 3 | G25: =IF(F25=0,0,F25-1) -> 2 | J25: x | M25: Developed when justifying investment appraisals and funding decisions in the AFDM module assessments
A26: 24 | B26: Ability to listen | C26: D | D26: co | F26: =IF(ISNA(MATCH("x",$H26:$L26,0)),0,MATCH("x",$H26:$L26,0)) -> 4 | G26: =IF(F26=0,0,F26-1) -> 3 | K26: x | M26: Practised actively in all lectures/tutorials, particularly when digesting complex instructions for Python coding in PSBF
A27: 25 | B27: Inductive and deductive reasoning | C27: A | D27: int | F27: =IF(ISNA(MATCH("x",$H27:$L27,0)),0,MATCH("x",$H27:$L27,0)) -> 4 | G27: =IF(F27=0,0,F27-1) -> 3 | K27: x | M27: Applied when transitioning from baseline statistics to broader conclusions in PSBF and theory application in EBF
A28: 26 | B28: Ability to understand people and work with them | C28: C | D28: is | F28: =IF(ISNA(MATCH("x",$H28:$L28,0)),0,MATCH("x",$H28:$L28,0)) -> 4 | G28: =IF(F28=0,0,F28-1) -> 3 | K28: x | M28: Fostered through the group assessment components and applied scenarios focused on industry practice in AFDM
A29: 27 | B29: Econometrics & causal inference | C29: A1 | D29: tech | F29: =IF(ISNA(MATCH("x",$H29:$L29,0)),0,MATCH("x",$H29:$L29,0)) -> 4 | G29: =IF(F29=0,0,F29-1) -> 3 | K29: x | M29: Developed via the "Relationships, correlation, scatter graph" and baseline statistics modules in PSBF
A30: 28 | B30: Ability to communicate | C30: F | D30: co | F30: =IF(ISNA(MATCH("x",$H30:$L30,0)),0,MATCH("x",$H30:$L30,0)) -> 5 | G30: =IF(F30=0,0,F30-1) -> 4 | L30: x | M30: The programme ensures this through "telling stories with numbers" (PSBF) and articulating real-world cases (EBF)
A31: 29 | B31: Right degree of self-confidence | C31: F | D31: sa | F31: =IF(ISNA(MATCH("x",$H31:$L31,0)),0,MATCH("x",$H31:$L31,0)) -> 3 | G31: =IF(F31=0,0,F31-1) -> 2 | J31: x | M31: Built incrementally by mastering technical tools (Python/Jupyter) and financial models (NPV/IRR)
A32: 30 | B32: Independence in drawing unbiased conclusions | C32: A | D32: eth | F32: =IF(ISNA(MATCH("x",$H32:$L32,0)),0,MATCH("x",$H32:$L32,0)) -> 4 | G32: =IF(F32=0,0,F32-1) -> 3 | K32: x | M32: Required for interpreting financial information accurately and objectively in the AFDMand FIM modules
A33: 31 | B33: Forecasting / scenario analysis | C33: A1 | D33: tech | F33: =IF(ISNA(MATCH("x",$H33:$L33,0)),0,MATCH("x",$H33:$L33,0)) -> 4 | G33: =IF(F33=0,0,F33-1) -> 3 | K33: x | M33: Heavily integrated into AFDM through the time value of money, investment appraisal techniques (NPV, IRR), and ratio analysis
A34: 32 | B34: Respect and tolerance for other people | C34: D | D34: is | F34: =IF(ISNA(MATCH("x",$H34:$L34,0)),0,MATCH("x",$H34:$L34,0)) -> 4 | G34: =IF(F34=0,0,F34-1) -> 3 | K34: x | M34: Embedded in the university's code of conduct and essential for successful collaboration in diverse seminar groups
A35: 33 | B35: Courage, initiative, and perseverance in action | C35: F | D35: re | F35: =IF(ISNA(MATCH("x",$H35:$L35,0)),0,MATCH("x",$H35:$L35,0)) -> 3 | G35: =IF(F35=0,0,F35-1) -> 2 | J35: x | M35: Required to persist through challenging quantitative learning curves, such as learning Python syntax in PSBF
A36: 34 | B36: Tools (Excel + R/Python/Stata/AI tools) | C36: A1 | D36: tech | F36: =IF(ISNA(MATCH("x",$H36:$L36,0)),0,MATCH("x",$H36:$L36,0)) -> 5 | G36: =IF(F36=0,0,F36-1) -> 4 | L36: x | M36: Strongly covered in PSBF, which dedicates multiple weeks to Introduction to Python, Jupyter Notebooks, and specific packages
A37: 35 | B37: Flexibility and adaptability to changed conditions | C37: F | D37: re | F37: =IF(ISNA(MATCH("x",$H37:$L37,0)),0,MATCH("x",$H37:$L37,0)) -> 3 | G37: =IF(F37=0,0,F37-1) -> 2 | J37: x | M37: Developed by analyzing dynamic financial markets, bubbles, and crashes in the FIM module
A38: 36 | B38: Ability to synthesize and generalize | C38: A | D38: int | F38: =IF(ISNA(MATCH("x",$H38:$L38,0)),0,MATCH("x",$H38:$L38,0)) -> 4 | G38: =IF(F38=0,0,F38-1) -> 3 | K38: x | M38: Crucial for digesting macroeconomic measurements (Econ) and the comprehensive workings of global systems (FIM)
A39: 37 | B39: Personal drive and initiative | C39: E | D39: re | F39: =IF(ISNA(MATCH("x",$H39:$L39,0)),0,MATCH("x",$H39:$L39,0)) -> 4 | G39: =IF(F39=0,0,F39-1) -> 3 | K39: x | M39: Essential for completing independent reading (eg, Parkin's Economics textbook) and preparing for classes beforehand
A40: 38 | B40: Entrepreneurial spirit | C40: E | D40: cr | F40: =IF(ISNA(MATCH("x",$H40:$L40,0)),0,MATCH("x",$H40:$L40,0)) -> 3 | G40: =IF(F40=0,0,F40-1) -> 2 | J40: x | M40: Stimulated through the "Design thinking" frameworks in PSBF, which encourage innovative approaches to problems
A41: 39 | B41: Stability of behaviour and action | C41: F | D41: re | F41: =IF(ISNA(MATCH("x",$H41:$L41,0)),0,MATCH("x",$H41:$L41,0)) -> 3 | G41: =IF(F41=0,0,F41-1) -> 2 | J41: x | M41: Demonstrated through consistent attendance, methodical study habits, and timely coursework submissions across all 4 modules
B43: Competences/Capabilities as listed by Canadian Management Consultancy Competence Framework
B44: https://wwwcmc-canadaca/web/default/files/CMC_Competency_Framework_2018pdf

Sheet Results
B2: SELF-ASSESSMENT BASED ON LONGER ASSESSMENT MATRIX | M2: ASSESSMENT OF JOB DESCRIPTION FOR GRADUATE ECONOMIST | V2: Your personal reflections on the different capability assessments (of myself, the job description and my programme)
B3: Category | F3: Mean | G3: Min | H3: Max | J3: your ranking | M3: Category | Q3: Mean | R3: Min | S3: Max
B4: Economics Thinking Capability | C4: A | D4: =COUNTIF('Self-assessment'!$C$3:$C$41,$C4)*5 -> 35 | E4: =SUMIF('Self-assessment'!$C$3:$C$41,$C4,'Self-assessment'!$G$3:$G$41) -> 11 | F4: =(E4/D4)*4 -> 1.2571429 | G4: =_xlfn.MINIFS('Self-assessment'!$G$3:$G$41,'Self-assessment'!$C$3:'Self-assessment'!$C$41,$C4,'Self-assessment'!$G$3:$G$41,">0") -> 1 | H4: =_xlfn.MAXIFS('Self-assessment'!$G$3:$G$41,'Self-assessment'!$C$3:$C$41,$C4,'Self-assessment'!$G$3:$G$41,">0") -> 2 | J4: ='initial assessment'!J4 -> 1 | M4: Economics Thinking Capability | N4: A | O4: =COUNTIF('Job Description'!$C$3:$C$41,$N4)*5 -> 35 | P4: =SUMIF('Job Description'!$C$3:$C$41,$N4,'Job Description'!$G$3:$G$41) -> 25 | Q4: =(P4/O4)*4 -> 2.8571429 | R4: =_xlfn.MINIFS('Self-assessment'!$G$3:$G$41,'Self-assessment'!$C$3:'Self-assessment'!$C$41,$C4,'Self-assessment'!$G$3:$G$41,">0") -> 1 | S4: =_xlfn.MAXIFS('Self-assessment'!$G$3:$G$41,'Self-assessment'!$C$3:$C$41,$C4,'Self-assessment'!$G$3:$G$41,">0") -> 2
B5: Economic Skills | C5: A1 | D5: =COUNTIF('Self-assessment'!$C$3:$C$41,$C5)*5 -> 25 | E5: =SUMIF('Self-assessment'!$C$3:$C$41,$C5,'Self-assessment'!$G$3:$G$41) -> 6 | F5: =(E5/D5)*4 -> 0.96 | G5: =_xlfn.MINIFS('Self-assessment'!$G$3:$G$41,'Self-assessment'!$C$3:'Self-assessment'!$C$41,$C5,'Self-assessment'!$G$3:$G$41,">0") -> 1 | H5: =_xlfn.MAXIFS('Self-assessment'!$G$3:$G$41,'Self-assessment'!$C$3:$C$41,$C5,'Self-assessment'!$G$3:$G$41,">0") -> 2 | J5: ='initial assessment'!J5 -> 1 | M5: Economic Skills | N5: A1 | O5: =COUNTIF('Job Description'!$C$3:$C$41,$N5)*5 -> 25 | P5: =SUMIF('Job Description'!$C$3:$C$41,$N5,'Job Description'!$G$3:$G$41) -> 18 | Q5: =(P5/O5)*4 -> 2.88 | R5: =_xlfn.MINIFS('Self-assessment'!$G$3:$G$41,'Self-assessment'!$C$3:'Self-assessment'!$C$41,$C5,'Self-assessment'!$G$3:$G$41,">0") -> 1 | S5: =_xlfn.MAXIFS('Self-assessment'!$G$3:$G$41,'Self-assessment'!$C$3:$C$41,$C5,'Self-assessment'!$G$3:$G$41,">0") -> 2
B6: Research & Delivery Skills | C6: B | D6: =COUNTIF('Self-assessment'!$C$3:$C$41,$C6)*5 -> 10 | E6: =SUMIF('Self-assessment'!$C$3:$C$41,$C6,'Self-assessment'!$G$3:$G$41) -> 4 | F6: =(E6/D6)*4 -> 1.6 | G6: =_xlfn.MINIFS('Self-assessment'!$G$3:$G$41,'Self-assessment'!$C$3:'Self-assessment'!$C$41,$C6,'Self-assessment'!$G$3:$G$41,">0") -> 2 | H6: =_xlfn.MAXIFS('Self-assessment'!$G$3:$G$41,'Self-assessment'!$C$3:$C$41,$C6,'Self-assessment'!$G$3:$G$41,">0") -> 2 | J6: ='initial assessment'!J6 -> 2 | M6: Research & Delivery Skills | N6: B | O6: =COUNTIF('Job Description'!$C$3:$C$41,$N6)*5 -> 10 | P6: =SUMIF('Job Description'!$C$3:$C$41,$N6,'Job Description'!$G$3:$G$41) -> 5 | Q6: =(P6/O6)*4 -> 2 | R6: =_xlfn.MINIFS('Self-assessment'!$G$3:$G$41,'Self-assessment'!$C$3:'Self-assessment'!$C$41,$C6,'Self-assessment'!$G$3:$G$41,">0") -> 2 | S6: =_xlfn.MAXIFS('Self-assessment'!$G$3:$G$41,'Self-assessment'!$C$3:$C$41,$C6,'Self-assessment'!$G$3:$G$41,">0") -> 2
B7: Stakeholder & Customer Awareness | C7: C | D7: =COUNTIF('Self-assessment'!$C$3:$C$41,$C7)*5 -> 25 | E7: =SUMIF('Self-assessment'!$C$3:$C$41,$C7,'Self-assessment'!$G$3:$G$41) -> 11 | F7: =(E7/D7)*4 -> 1.76 | G7: =_xlfn.MINIFS('Self-assessment'!$G$3:$G$41,'Self-assessment'!$C$3:'Self-assessment'!$C$41,$C7,'Self-assessment'!$G$3:$G$41,">0") -> 2 | H7: =_xlfn.MAXIFS('Self-assessment'!$G$3:$G$41,'Self-assessment'!$C$3:$C$41,$C7,'Self-assessment'!$G$3:$G$41,">0") -> 3 | J7: ='initial assessment'!J7 -> 1 | M7: Stakeholder & Customer Awareness | N7: C | O7: =COUNTIF('Job Description'!$C$3:$C$41,$N7)*5 -> 25 | P7: =SUMIF('Job Description'!$C$3:$C$41,$N7,'Job Description'!$G$3:$G$41) -> 12 | Q7: =(P7/O7)*4 -> 1.92 | R7: =_xlfn.MINIFS('Self-assessment'!$G$3:$G$41,'Self-assessment'!$C$3:'Self-assessment'!$C$41,$C7,'Self-assessment'!$G$3:$G$41,">0") -> 2 | S7: =_xlfn.MAXIFS('Self-assessment'!$G$3:$G$41,'Self-assessment'!$C$3:$C$41,$C7,'Self-assessment'!$G$3:$G$41,">0") -> 3
B8: Collaboration & Ways of Working | C8: D | D8: =COUNTIF('Self-assessment'!$C$3:$C$41,$C8)*5 -> 15 | E8: =SUMIF('Self-assessment'!$C$3:$C$41,$C8,'Self-assessment'!$G$3:$G$41) -> 6 | F8: =(E8/D8)*4 -> 1.6 | G8: =_xlfn.MINIFS('Self-assessment'!$G$3:$G$41,'Self-assessment'!$C$3:'Self-assessment'!$C$41,$C8,'Self-assessment'!$G$3:$G$41,">0") -> 2 | H8: =_xlfn.MAXIFS('Self-assessment'!$G$3:$G$41,'Self-assessment'!$C$3:$C$41,$C8,'Self-assessment'!$G$3:$G$41,">0") -> 2 | J8: ='initial assessment'!J8 -> 2 | M8: Collaboration & Ways of Working | N8: D | O8: =COUNTIF('Job Description'!$C$3:$C$41,$N8)*5 -> 15 | P8: =SUMIF('Job Description'!$C$3:$C$41,$N8,'Job Description'!$G$3:$G$41) -> 9 | Q8: =(P8/O8)*4 -> 2.4 | R8: =_xlfn.MINIFS('Self-assessment'!$G$3:$G$41,'Self-assessment'!$C$3:'Self-assessment'!$C$41,$C8,'Self-assessment'!$G$3:$G$41,">0") -> 2 | S8: =_xlfn.MAXIFS('Self-assessment'!$G$3:$G$41,'Self-assessment'!$C$3:$C$41,$C8,'Self-assessment'!$G$3:$G$41,">0") -> 2
B9: Feedback, Development & Career Management | C9: E | D9: =COUNTIF('Self-assessment'!$C$3:$C$41,$C9)*5 -> 25 | E9: =SUMIF('Self-assessment'!$C$3:$C$41,$C9,'Self-assessment'!$G$3:$G$41) -> 9 | F9: =(E9/D9)*4 -> 1.44 | G9: =_xlfn.MINIFS('Self-assessment'!$G$3:$G$41,'Self-assessment'!$C$3:'Self-assessment'!$C$41,$C9,'Self-assessment'!$G$3:$G$41,">0") -> 1 | H9: =_xlfn.MAXIFS('Self-assessment'!$G$3:$G$41,'Self-assessment'!$C$3:$C$41,$C9,'Self-assessment'!$G$3:$G$41,">0") -> 2 | J9: ='initial assessment'!J9 -> 1 | M9: Feedback, Development & Career Management | N9: E | O9: =COUNTIF('Job Description'!$C$3:$C$41,$N9)*5 -> 25 | P9: =SUMIF('Job Description'!$C$3:$C$41,$N9,'Job Description'!$G$3:$G$41) -> 16 | Q9: =(P9/O9)*4 -> 2.56 | R9: =_xlfn.MINIFS('Self-assessment'!$G$3:$G$41,'Self-assessment'!$C$3:'Self-assessment'!$C$41,$C9,'Self-assessment'!$G$3:$G$41,">0") -> 1 | S9: =_xlfn.MAXIFS('Self-assessment'!$G$3:$G$41,'Self-assessment'!$C$3:$C$41,$C9,'Self-assessment'!$G$3:$G$41,">0") -> 2
B10: Professionalism & Organisational Skills | C10: F | D10: =COUNTIF('Self-assessment'!$C$3:$C$41,$C10)*5 -> 60 | E10: =SUMIF('Self-assessment'!$C$3:$C$41,$C10,'Self-assessment'!$G$3:$G$41) -> 24 | F10: =(E10/D10)*4 -> 1.6 | G10: =_xlfn.MINIFS('Self-assessment'!$G$3:$G$41,'Self-assessment'!$C$3:'Self-assessment'!$C$41,$C10,'Self-assessment'!$G$3:$G$41,">0") -> 1 | H10: =_xlfn.MAXIFS('Self-assessment'!$G$3:$G$41,'Self-assessment'!$C$3:$C$41,$C10,'Self-assessment'!$G$3:$G$41,">0") -> 3 | J10: ='initial assessment'!J10 -> 2 | M10: Professionalism & Organisational Skills | N10: F | O10: =COUNTIF('Job Description'!$C$3:$C$41,$N10)*5 -> 60 | P10: =SUMIF('Job Description'!$C$3:$C$41,$N10,'Job Description'!$G$3:$G$41) -> 44 | Q10: =(P10/O10)*4 -> 2.9333333 | R10: =_xlfn.MINIFS('Self-assessment'!$G$3:$G$41,'Self-assessment'!$C$3:'Self-assessment'!$C$41,$C10,'Self-assessment'!$G$3:$G$41,">0") -> 1 | S10: =_xlfn.MAXIFS('Self-assessment'!$G$3:$G$41,'Self-assessment'!$C$3:$C$41,$C10,'Self-assessment'!$G$3:$G$41,">0") -> 3
V29: Strategies and actions in relation to my employability and career planning
